Workbook
Name avista: Sup!$D$2
Name b_1000: #REF!
Name b_10000: #REF!
Name b_100000: #REF!
Name b_10001: #REF!
Name b_100k: #REF!
Name b_100k: Sup!$L$2:$L$25
Name b_10k: #REF!
Name b_10k: Sup!$H$2:$H$15
Name b_1k: #REF!
Name b_1k: Sup!$E$2:$E$4
Name b_20000: #REF!
Name b_25001: #REF!
Name b_25k: #REF!
Name b_25k: Sup!$I$2:$I$18
Name b_3000: #REF!
Name b_3001: #REF!
Name b_3k: #REF!
Name b_3k: Sup!$F$2:$F$7
Name b_40000: #REF!
Name b_5000: #REF!
Name b_50001: #REF!
Name b_5001: #REF!
Name b_5001: #REF!
Name b_5001: Sup!$G$2:$G$12
Name b_50k: #REF!
Name b_50k: Sup!$J$2:$J$21
Name b_7500: #REF!
Name b_75000: #REF!
Name b_75001: #REF!
Name b_75k: #REF!
Name b_75k: Sup!$K$2:$K$22
Name cc_10k: Sup!$M$2:$M$7
Name ccr: #REF!
Name ccr: Sup!$M$2:$M$5
Name ccredito: #REF!
Name condpgto: #REF!
Name condpgto: #REF!
Name condpgto: Sup!$B$2:$B$4
Name formadepgto: #REF!
Name formadepgto: #REF!
Name formadepgto: Sup!$C$2:$C$3

Sheet Pedido
D1: Premium
C2: Vigência | D2: 46204
C3: Tabela | D3: FARMACIAS ESP.
C4: Valor total do pedido | D4: =SUMPRODUCT(K17:K307) -> 0
C5: Tipo de cliente | D5: Escolha o Tipo de cliente
C6: Região | D6: Escolha a Região | N6: v3
A8: BARRAS | B8: =SUMIFS($K$17:$K$292,$F$17:$F$292,$A8) -> 0
A9: CREATINAS | B9: =SUMIFS($K$17:$K$292,$F$17:$F$292,$A9) -> 0
A10: SACHES | B10: =SUMIFS($K$17:$K$292,$F$17:$F$292,$A10) -> 0
A11: SHAKES | B11: =SUMIFS($K$17:$K$292,$F$17:$F$292,$A11) -> 0
A12: VITAMINAS | B12: =SUMIFS($K$17:$K$292,$F$17:$F$292,$A12) -> 0
A14: Categoria | C14: Informações do Produto | H14: Dados Financeiros | K14: Dados do Pedido
B16: Cód, SKU | C16: Nome | D16: Sabor/Cor | E16: Embalagem | F16: Família | G16: Volume | H16: Sugerido | I16: Mkup | J16: Preço Unit. | K16: Preço | L16: Qtd. | M16: Cx.
B17: 520412007 | C17: Proteína Sabores (4 unid.) | D17: Banana | E17: Pote | F17: =_xlfn.XLOOKUP(B17,Planilha1!A:A,Planilha1!B:B) -> OUTROS | G17: 600g | H17: 219.9 | I17: =IFERROR(H17/J17,"") -> 1.6599985 | J17: 132.47 | K17: =L17*J17 -> 0 | M17: 4 | S17: 6 | T17: 8 | U17: 4
B18: 520412014 | C18: Proteína Sabores (4 unid.) | D18: Cacau | E18: Pote | F18: =_xlfn.XLOOKUP(B18,Planilha1!A:A,Planilha1!B:B) -> OUTROS | G18: 600g | H18: 219.9 | I18: =IFERROR(H18/J18,"") -> 1.6599985 | J18: 132.47 | K18: =L18*J18 -> 0 | M18: 4 | S18: =S17+6 -> 12 | T18: =T17+8 -> 16 | U18: =U17+4 -> 8
B19: 520412051 | C19: Proteína Sabores (4 unid.) | D19: Cookies | E19: Pote | F19: =_xlfn.XLOOKUP(B19,Planilha1!A:A,Planilha1!B:B) -> OUTROS | G19: 600g | H19: 219.9 | I19: =IFERROR(H19/J19,"") -> 1.6599985 | J19: 132.47 | K19: =L19*J19 -> 0 | M19: 4 | S19: =S18+6 -> 18 | T19: =T18+8 -> 24 | U19: =U18+4 -> 12
B20: 520412027 | C20: Proteína Sabores (4 unid.) | D20: Doce de Leite | E20: Pote | F20: =_xlfn.XLOOKUP(B20,Planilha1!A:A,Planilha1!B:B) -> OUTROS | G20: 600g | H20: 219.9 | I20: =IFERROR(H20/J20,"") -> 1.6599985 | J20: 132.47 | K20: =L20*J20 -> 0 | M20: 4 | S20: =S19+6 -> 24 | T20: =T19+8 -> 32 | U20: =U19+4 -> 16
B21: 520412039 | C21: Proteína Sabores (4 unid.) | D21: Morango | E21: Pote | F21: =_xlfn.XLOOKUP(B21,Planilha1!A:A,Planilha1!B:B) -> OUTROS | G21: 600g | H21: 219.9 | I21: =IFERROR(H21/J21,"") -> 1.6599985 | J21: 132.47 | K21: =L21*J21 -> 0 | M21: 4 | S21: =S20+6 -> 30 | T21: =T20+8 -> 40 | U21: =U20+4 -> 20
B22: 520412093 | C22: Proteína Sabores (4 unid.) | D22: Sem Sabor | E22: Pote | F22: =_xlfn.XLOOKUP(B22,Planilha1!A:A,Planilha1!B:B) -> OUTROS | G22: 600g | H22: 219.9 | I22: =IFERROR(H22/J22,"") -> 1.6599985 | J22: 132.47 | K22: =L22*J22 -> 0 | M22: 4 | S22: =S21+6 -> 36 | T22: =T21+8 -> 48 | U22: =U21+4 -> 24
B23: 520412079 | C23: Proteína Sabores (4 unid.) | D23: Salted Caramel | E23: Pote | F23: =_xlfn.XLOOKUP(B23,Planilha1!A:A,Planilha1!B:B) -> OUTROS | G23: 600g | H23: 219.9 | I23: =IFERROR(H23/J23,"") -> 1.6599985 | J23: 132.47 | K23: =L23*J23 -> 0 | M23: 4 | S23: =S22+6 -> 42 | T23: =T22+8 -> 56 | U23: =U22+4 -> 28
B24: 520349101 | C24: Display Barra Frutas (12 unid.) | D24: Bananinha com Paçoca | E24: Barra | F24: =_xlfn.XLOOKUP(B24,Planilha1!A:A,Planilha1!B:B) -> BARRAS | G24: 30g | H24: 9.9 | I24: =IFERROR(H24/J24,"") -> 1.5114504 | J24: 6.55 | K24: =L24*J24 -> 0 | M24: 12 | S24: =#REF!+6 -> #REF! | T24: =#REF!+8 -> #REF! | U24: =#REF!+4 -> #REF!
B25: 520349100 | C25: Display Barra Frutas (12 unid.) | D25: Berries | E25: Barra | F25: =_xlfn.XLOOKUP(B25,Planilha1!A:A,Planilha1!B:B) -> BARRAS | G25: 30g | H25: 9.9 | I25: =IFERROR(H25/J25,"") -> 1.5114504 | J25: 6.55 | K25: =L25*J25 -> 0 | M25: 12 | S25: =S24+6 -> #REF! | T25: =T24+8 -> #REF! | U25: =U24+4 -> #REF!
B26: 520349080 | C26: Display Barra de Proteína (12 unid.) | D26: Chocolate Belga | E26: Barra | F26: =_xlfn.XLOOKUP(B26,Planilha1!A:A,Planilha1!B:B) -> BARRAS | G26: 45g | H26: 11.9 | I26: =IFERROR(H26/J26,"") -> 1.5657895 | J26: 7.6 | K26: =L26*J26 -> 0 | M26: 12 | S26: =S25+6 -> #REF! | T26: =T25+8 -> #REF! | U26: =U25+4 -> #REF!
B27: 520349051 | C27: Display Barra de Proteína (12 unid.) | D27: Cookies & Cream | E27: Barra | F27: =_xlfn.XLOOKUP(B27,Planilha1!A:A,Planilha1!B:B) -> BARRAS | G27: 45g | H27: 11.9 | I27: =IFERROR(H27/J27,"") -> 1.5657895 | J27: 7.6 | K27: =L27*J27 -> 0 | M27: 12 | S27: =S26+6 -> #REF! | T27: =T26+8 -> #REF! | U27: =U26+4 -> #REF!
B28: 520349027 | C28: Display Barra de Proteína (12 unid.) | D28: Doce de Leite | E28: Barra | F28: =_xlfn.XLOOKUP(B28,Planilha1!A:A,Planilha1!B:B) -> BARRAS | G28: 45g | H28: 11.9 | I28: =IFERROR(H28/J28,"") -> 1.5657895 | J28: 7.6 | K28: =L28*J28 -> 0 | M28: 12 | S28: =S27+6 -> #REF! | T28: =T27+8 -> #REF! | U28: =U27+4 -> #REF!
B29: 520349081 | C29: Display Barra de Proteína (12 unid.) | D29: Morango & Chocolate Branco | E29: Barra | F29: =_xlfn.XLOOKUP(B29,Planilha1!A:A,Planilha1!B:B) -> BARRAS | G29: 45g | H29: 11.9 | I29: =IFERROR(H29/J29,"") -> 1.5657895 | J29: 7.6 | K29: =L29*J29 -> 0 | M29: 12 | S29: =S28+6 -> #REF! | T29: =T28+8 -> #REF! | U29: =U28+4 -> #REF!
B30: 520349083 | C30: Display Barra de Proteína (12 unid.) | D30: Pistache | E30: Barra | F30: =_xlfn.XLOOKUP(B30,Planilha1!A:A,Planilha1!B:B) -> BARRAS | G30: 45g | H30: 11.9 | I30: =IFERROR(H30/J30,"") -> 1.5657895 | J30: 7.6 | K30: =L30*J30 -> 0 | M30: 12 | S30: =S29+6 -> #REF! | T30: =T29+8 -> #REF! | U30: =U29+4 -> #REF!
B31: 520349079 | C31: Display Barra de Proteína (12 unid.) | D31: Salted Caramel | E31: Barra | F31: =_xlfn.XLOOKUP(B31,Planilha1!A:A,Planilha1!B:B) -> BARRAS | G31: 45g | H31: 11.9 | I31: =IFERROR(H31/J31,"") -> 1.5657895 | J31: 7.6 | K31: =L31*J31 -> 0 | M31: 12 | S31: =S30+6 -> #REF! | T31: =T30+8 -> #REF! | U31: =U30+4 -> #REF!
B32: 520204080 | C32: Pasta Amendoim | D32: Chocolate Belga | E32: Pote | F32: =_xlfn.XLOOKUP(B32,Planilha1!A:A,Planilha1!B:B) -> OUTROS | G32: 300g | H32: 33.9 | I32: =IFERROR(H32/J32,"") -> 1.6593245 | J32: 20.43 | K32: =L32*J32 -> 0 | M32: 6 | S32: =#REF!+6 -> #REF! | T32: =#REF!+8 -> #REF! | U32: =#REF!+4 -> #REF!
B33: 520204078 | C33: Pasta Amendoim | D33: Integral | E33: Pote | F33: =_xlfn.XLOOKUP(B33,Planilha1!A:A,Planilha1!B:B) -> OUTROS | G33: 300g | H33: 33.9 | I33: =IFERROR(H33/J33,"") -> 1.6593245 | J33: 20.43 | K33: =L33*J33 -> 0 | M33: 6 | S33: =#REF!+6 -> #REF! | T33: =#REF!+8 -> #REF! | U33: =#REF!+4 -> #REF!
B34: 520204079 | C34: Pasta Amendoim | D34: Salted Caramel | E34: Pote | F34: =_xlfn.XLOOKUP(B34,Planilha1!A:A,Planilha1!B:B) -> OUTROS | G34: 300g | H34: 33.9 | I34: =IFERROR(H34/J34,"") -> 1.6593245 | J34: 20.43 | K34: =L34*J34 -> 0 | M34: 6 | S34: =#REF!+6 -> #REF! | T34: =#REF!+8 -> #REF! | U34: =#REF!+4 -> #REF!
B35: 521304083 | C35: Pasta de Pistache | D35: - | E35: Pote | F35: =_xlfn.XLOOKUP(B35,Planilha1!A:A,Planilha1!B:B) -> OUTROS | G35: 300g | H35: 79.9 | I35: =IFERROR(H35/J35,"") -> 1.6597424 | J35: 48.14 | K35: =L35*J35 -> 0 | M35: 6 | S35: =#REF!+6 -> #REF! | T35: =#REF!+8 -> #REF! | U35: =#REF!+4 -> #REF!
B36: 521304095 | C36: Pasta de Avelã | D36: - | E36: Pote | F36: =_xlfn.XLOOKUP(B36,Planilha1!A:A,Planilha1!B:B) -> OUTROS | G36: 300g | H36: 79.9 | I36: =IFERROR(H36/J36,"") -> 1.6597424 | J36: 48.14 | K36: =L36*J36 -> 0 | M36: 6 | S36: =S35+6 -> #REF! | T36: =T35+8 -> #REF! | U36: =U35+4 -> #REF!
B37: 521304097 | C37: Pasta de Macadâmia | D37: - | E37: Pote | F37: =_xlfn.XLOOKUP(B37,Planilha1!A:A,Planilha1!B:B) -> OUTROS | G37: 300g | H37: 79.9 | I37: =IFERROR(H37/J37,"") -> 1.6597424 | J37: 48.14 | K37: =L37*J37 -> 0 | M37: 6 | S37: =S36+6 -> #REF! | T37: =T36+8 -> #REF! | U37: =U36+4 -> #REF!
B38: 520104088 | C38: Pasta Castanha | D38: Cacau Nibs | E38: Pote | F38: =_xlfn.XLOOKUP(B38,Planilha1!A:A,Planilha1!B:B) -> OUTROS | G38: 300g | H38: 37.9 | I38: =IFERROR(H38/J38,"") -> 1.2864902 | J38: 29.46 | K38: =L38*J38 -> 0 | M38: 6 | S38: =#REF!+6 -> #REF! | T38: =#REF!+8 -> #REF! | U38: =#REF!+4 -> #REF!
B39: 520104080 | C39: Pasta Castanha | D39: Chocolate Belga | E39: Pote | F39: =_xlfn.XLOOKUP(B39,Planilha1!A:A,Planilha1!B:B) -> OUTROS | G39: 300g | H39: 37.9 | I39: =IFERROR(H39/J39,"") -> 1.2864902 | J39: 29.46 | K39: =L39*J39 -> 0 | M39: 6 | S39: =#REF!+6 -> #REF! | T39: =#REF!+8 -> #REF! | U39: =#REF!+4 -> #REF!
B40: 520104051 | C40: Pasta Castanha | D40: Cookies 'N' Cream | E40: Pote | F40: =_xlfn.XLOOKUP(B40,Planilha1!A:A,Planilha1!B:B) -> OUTROS | G40: 300g | H40: 37.9 | I40: =IFERROR(H40/J40,"") -> 1.2864902 | J40: 29.46 | K40: =L40*J40 -> 0 | M40: 6 | S40: =S39+6 -> #REF! | T40: =T39+8 -> #REF! | U40: =U39+4 -> #REF!
B41: 520104027 | C41: Pasta Castanha | D41: Doce de Leite | E41: Pote | F41: =_xlfn.XLOOKUP(B41,Planilha1!A:A,Planilha1!B:B) -> OUTROS | G41: 300g | H41: 37.9 | I41: =IFERROR(H41/J41,"") -> 1.2864902 | J41: 29.46 | K41: =L41*J41 -> 0 | M41: 6 | S41: =S40+6 -> #REF! | T41: =T40+8 -> #REF! | U41: =U40+4 -> #REF!
B42: 520104078 | C42: Pasta Castanha | D42: Integral | E42: Pote | F42: =_xlfn.XLOOKUP(B42,Planilha1!A:A,Planilha1!B:B) -> OUTROS | G42: 300g | H42: 37.9 | I42: =IFERROR(H42/J42,"") -> 1.2864902 | J42: 29.46 | K42: =L42*J42 -> 0 | M42: 6 | S42: =S41+6 -> #REF! | T42: =T41+8 -> #REF! | U42: =U41+4 -> #REF!
B43: 520104094 | C43: Pasta Castanha | D43: Morango com Choc Branco | E43: Pote | F43: =_xlfn.XLOOKUP(B43,Planilha1!A:A,Planilha1!B:B) -> OUTROS | G43: 300g | H43: 37.9 | I43: =IFERROR(H43/J43,"") -> 1.2864902 | J43: 29.46 | K43: =L43*J43 -> 0 | M43: 6 | S43: =#REF!+6 -> #REF! | T43: =#REF!+8 -> #REF! | U43: =#REF!+4 -> #REF!
B44: 520104079 | C44: Pasta Castanha | D44: Salted Caramel | E44: Pote | F44: =_xlfn.XLOOKUP(B44,Planilha1!A:A,Planilha1!B:B) -> OUTROS | G44: 300g | H44: 37.9 | I44: =IFERROR(H44/J44,"") -> 1.2864902 | J44: 29.46 | K44: =L44*J44 -> 0 | M44: 6 | S44: =#REF!+6 -> #REF! | T44: =#REF!+8 -> #REF! | U44: =#REF!+4 -> #REF!
B45: 50000062 | C45: Mini Galão | D45: Fumê | E45: Unissex | F45: =_xlfn.XLOOKUP(B45,Planilha1!A:A,Planilha1!B:B) -> OUTROS | G45: 1875 | H45: 39.9 | I45: =IFERROR(H45/J45,"") -> 1.5495146 | J45: 25.75 | K45: =L45*J45 -> 0 | M45: 5 | S45: =S44+6 -> #REF! | T45: =T44+8 -> #REF! | U45: =U44+4 -> #REF!
B46: 50000030 | C46: Coqueteleira DUX | D46: Fumê | E46: Unissex | F46: =_xlfn.XLOOKUP(B46,Planilha1!A:A,Planilha1!B:B) -> OUTROS | G46: 800 | H46: 21.9 | I46: =IFERROR(H46/J46,"") -> 1.5869565 | J46: 13.8 | K46: =L46*J46 -> 0 | M46: 12 | S46: =S45+6 -> #REF! | T46: =T45+8 -> #REF! | U46: =U45+4 -> #REF!
B47: 50000075 | C47: Coqueteleira Strada | D47: Branca | E47: Unissex | F47: =_xlfn.XLOOKUP(B47,Planilha1!A:A,Planilha1!B:B) -> OUTROS | G47: 710ml | H47: 209.9 | I47: =IFERROR(H47/J47,"") -> 1.3832872 | J47: 151.74 | K47: =L47*J47 -> 0 | S47: =#REF!+6 -> #REF! | T47: =#REF!+8 -> #REF! | U47: =#REF!+4 -> #REF!
B48: 50000061 | C48: Coqueteleira Strada | D48: Preta | E48: Unissex | F48: =_xlfn.XLOOKUP(B48,Planilha1!A:A,Planilha1!B:B) -> OUTROS | G48: 710ml | H48: 209.9 | I48: =IFERROR(H48/J48,"") -> 1.3832872 | J48: 151.74 | K48: =L48*J48 -> 0 | S48: =S47+6 -> #REF! | T48: =T47+8 -> #REF! | U48: =U47+4 -> #REF!
B49: 50000029 | C49: Squeeze automático | D49: Preto | E49: Unissex | F49: =_xlfn.XLOOKUP(B49,Planilha1!A:A,Planilha1!B:B) -> OUTROS | G49: 800 | H49: 18.9 | I49: =IFERROR(H49/J49,"") -> 1.4318182 | J49: 13.2 | K49: =L49*J49 -> 0 | M49: - | S49: =S48+6 -> #REF! | T49: =T48+8 -> #REF! | U49: =U48+4 -> #REF!
B50: 410103002 | C50: BCAA Powder | D50: Abacaxi | E50: Pote | F50: =_xlfn.XLOOKUP(B50,Planilha1!A:A,Planilha1!B:B) -> VITAMINAS | G50: 200 | H50: 99.9 | I50: =IFERROR(H50/J50,"") -> 1.6597441 | J50: 60.19 | K50: =L50*J50 -> 0 | M50: 12 | S50: =S49+6 -> #REF! | T50: =T49+8 -> #REF! | U50: =U49+4 -> #REF!
B51: 410103031 | C51: BCAA Powder | D51: Laranja | E51: Pote | F51: =_xlfn.XLOOKUP(B51,Planilha1!A:A,Planilha1!B:B) -> VITAMINAS | G51: 200 | H51: 99.9 | I51: =IFERROR(H51/J51,"") -> 1.6597441 | J51: 60.19 | K51: =L51*J51 -> 0 | M51: 12 | S51: =S50+6 -> #REF! | T51: =T50+8 -> #REF! | U51: =U50+4 -> #REF!
B52: 410103032 | C52: BCAA Powder | D52: Limão | E52: Pote | F52: =_xlfn.XLOOKUP(B52,Planilha1!A:A,Planilha1!B:B) -> VITAMINAS | G52: 200 | H52: 99.9 | I52: =IFERROR(H52/J52,"") -> 1.6597441 | J52: 60.19 | K52: =L52*J52 -> 0 | M52: 12 | S52: =S51+6 -> #REF! | T52: =T51+8 -> #REF! | U52: =U51+4 -> #REF!
B53: 410201001 | C53: Creatina Creapure | D53: Sem Sabor | E53: Pote | F53: =_xlfn.XLOOKUP(B53,Planilha1!A:A,Planilha1!B:B) -> CREATINAS | G53: 100 | H53: 116.9 | I53: =IFERROR(H53/J53,"") -> 1.6590974 | J53: 70.46 | K53: =L53*J53 -> 0 | M53: 27 | S53: =#REF!+6 -> #REF! | T53: =#REF!+8 -> #REF! | U53: =#REF!+4 -> #REF!
B54: 410368001 | C54: Creatina Monohidratada - 6 UNIDADES | D54: Sem Sabor | E54: Pote | F54: =_xlfn.XLOOKUP(B54,Planilha1!A:A,Planilha1!B:B) -> CREATINAS | G54: 300 | H54: 69.9 | I54: =IFERROR(H54/J54,"") -> 1.5498891 | J54: 45.1 | K54: =L54*J54 -> 0 | M54: 18 | S54: =#REF!+6 -> #REF! | T54: =#REF!+8 -> #REF! | U54: =#REF!+4 -> #REF!
B55: 414576001 | C55: CREATINA MONOHIDRATADA DC | D55: Sem Sabor | E55: Pouch | F55: =_xlfn.XLOOKUP(B55,[1]Planilha1!A:A,[1]Planilha1!B:B) -> CREATINAS | G55: 450g | H55: 101.12 | I55: =IFERROR(H55/J55,"") -> 1.5499693 | J55: 65.24 | K55: =L55*J55 -> 0 | M55: 5
B56: 410312001 | C56: Creatina Monohidratada - 4 UNIDADES | D56: Sem Sabor | E56: Pote | F56: =_xlfn.XLOOKUP(B56,Planilha1!A:A,Planilha1!B:B) -> CREATINAS | G56: 600g | H56: 118.9 | I56: =IFERROR(H56/J56,"") -> 1.5508021 | J56: 76.67 | K56: =L56*J56 -> 0 | M56: 4 | S56: =S54+6 -> #REF! | T56: =T54+8 -> #REF! | U56: =U54+4 -> #REF!
B57: 410468001 | C57: Glutamina - 6 UNIDADES | D57: Sem Sabor | E57: Pote | F57: =_xlfn.XLOOKUP(B57,Planilha1!A:A,Planilha1!B:B) -> OUTROS | G57: 300 | H57: 94.9 | I57: =IFERROR(H57/J57,"") -> 1.6599615 | J57: 57.17 | K57: =L57*J57 -> 0 | M57: 18 | S57: =#REF!+6 -> #REF! | T57: =#REF!+8 -> #REF! | U57: =#REF!+4 -> #REF!
B58: 420737063 | C58: Energy Gel (10 unid.) | D58: Caramelo | E58: Sachê | F58: =_xlfn.XLOOKUP(B58,Planilha1!A:A,Planilha1!B:B) -> OUTROS | G58: 30 | H58: 11.9 | I58: =IFERROR(H58/J58,"") -> 1.5494792 | J58: 7.68 | K58: =L58*J58 -> 0 | M58: 7 | S58: =S57+6 -> #REF! | T58: =T57+8 -> #REF! | U58: =U57+4 -> #REF!
B59: 420737030 | C59: Energy Gel (10 unid.) | D59: Guaraná | E59: Sachê | F59: =_xlfn.XLOOKUP(B59,Planilha1!A:A,Planilha1!B:B) -> OUTROS | G59: 30 | H59: 11.9 | I59: =IFERROR(H59/J59,"") -> 1.5494792 | J59: 7.68 | K59: =L59*J59 -> 0 | M59: 7 | S59: =S58+6 -> #REF! | T59: =T58+8 -> #REF! | U59: =U58+4 -> #REF!
B60: 420737066 | C60: Energy Gel (10 unid.) | D60: Jabuticaba | E60: Sachê | F60: =_xlfn.XLOOKUP(B60,Planilha1!A:A,Planilha1!B:B) -> OUTROS | G60: 30 | H60: 11.9 | I60: =IFERROR(H60/J60,"") -> 1.5494792 | J60: 7.68 | K60: =L60*J60 -> 0 | M60: 7 | S60: =S59+6 -> #REF! | T60: =T59+8 -> #REF! | U60: =U59+4 -> #REF!
B61: 420737036 | C61: Energy Gel (10 unid.) | D61: Maracujá | E61: Sachê | F61: =_xlfn.XLOOKUP(B61,Planilha1!A:A,Planilha1!B:B) -> OUTROS | G61: 30 | H61: 11.9 | I61: =IFERROR(H61/J61,"") -> 1.5494792 | J61: 7.68 | K61: =L61*J61 -> 0 | M61: 7 | S61: =S60+6 -> #REF! | T61: =T60+8 -> #REF! | U61: =U60+4 -> #REF!
B62: 420737044 | C62: Energy Gel (10 unid.) | D62: Neutro | E62: Sachê | F62: =_xlfn.XLOOKUP(B62,Planilha1!A:A,Planilha1!B:B) -> OUTROS | G62: 30 | H62: 11.9 | I62: =IFERROR(H62/J62,"") -> 1.5494792 | J62: 7.68 | K62: =L62*J62 -> 0 | M62: 7 | S62: =S61+6 -> #REF! | T62: =T61+8 -> #REF! | U62: =U61+4 -> #REF!
B63: 420737046 | C63: Energy Gel (10 unid.) | D63: Tangerina | E63: Sachê | F63: =_xlfn.XLOOKUP(B63,Planilha1!A:A,Planilha1!B:B) -> OUTROS | G63: 30 | H63: 11.9 | I63: =IFERROR(H63/J63,"") -> 1.5494792 | J63: 7.68 | K63: =L63*J63 -> 0 | M63: 7 | S63: =S62+6 -> #REF! | T63: =T62+8 -> #REF! | U63: =U62+4 -> #REF!
B64: 420737064 | C64: Energy Gel (10 unid.) | D64: Caramelo com Cafeína | E64: Sachê | F64: =_xlfn.XLOOKUP(B64,Planilha1!A:A,Planilha1!B:B) -> OUTROS | G64: 30 | H64: 11.9 | I64: =IFERROR(H64/J64,"") -> 1.5494792 | J64: 7.68 | K64: =L64*J64 -> 0 | M64: 7 | S64: =S63+6 -> #REF! | T64: =T63+8 -> #REF! | U64: =U63+4 -> #REF!
B65: 420737111 | C65: Energy Gel (10 unid.) | D65: Guaraná com Cafeína | E65: Sachê | F65: =_xlfn.XLOOKUP(B65,Planilha1!A:A,Planilha1!B:B) -> OUTROS | G65: 30 | H65: 11.9 | I65: =IFERROR(H65/J65,"") -> 1.5494792 | J65: 7.68 | K65: =L65*J65 -> 0 | M65: 7 | S65: =S64+6 -> #REF! | T65: =T64+8 -> #REF! | U65: =U64+4 -> #REF!
B66: 420737067 | C66: Energy Gel (10 unid.) | D66: Jabuticaba com Cafeína | E66: Sachê | F66: =_xlfn.XLOOKUP(B66,Planilha1!A:A,Planilha1!B:B) -> OUTROS | G66: 30 | H66: 11.9 | I66: =IFERROR(H66/J66,"") -> 1.5494792 | J66: 7.68 | K66: =L66*J66 -> 0 | M66: 7 | S66: =S65+6 -> #REF! | T66: =T65+8 -> #REF! | U66: =U65+4 -> #REF!
B67: 420737062 | C67: Energy Gel (10 unid.) | D67: Maracujá com Cafeína | E67: Sachê | F67: =_xlfn.XLOOKUP(B67,Planilha1!A:A,Planilha1!B:B) -> OUTROS | G67: 30 | H67: 11.9 | I67: =IFERROR(H67/J67,"") -> 1.5494792 | J67: 7.68 | K67: =L67*J67 -> 0 | M67: 7 | S67: =S66+6 -> #REF! | T67: =T66+8 -> #REF! | U67: =U66+4 -> #REF!
B68: 420737112 | C68: Energy Gel (10 unid.) | D68: Neutro com Cafeína | E68: Sachê | F68: =_xlfn.XLOOKUP(B68,Planilha1!A:A,Planilha1!B:B) -> OUTROS | G68: 30 | H68: 11.9 | I68: =IFERROR(H68/J68,"") -> 1.5494792 | J68: 7.68 | K68: =L68*J68 -> 0 | M68: 7 | S68: =S67+6 -> #REF! | T68: =T67+8 -> #REF! | U68: =U67+4 -> #REF!
B69: 420737065 | C69: Energy Gel (10 unid.) | D69: Tangerina com Cafeína | E69: Sachê | F69: =_xlfn.XLOOKUP(B69,Planilha1!A:A,Planilha1!B:B) -> OUTROS | G69: 30 | H69: 11.9 | I69: =IFERROR(H69/J69,"") -> 1.5494792 | J69: 7.68 | K69: =L69*J69 -> 0 | M69: 7 | S69: =S68+6 -> #REF! | T69: =T68+8 -> #REF! | U69: =U68+4 -> #REF!
B70: 420114002 | C70: EnergyKick | D70: Abacaxi | E70: Pote | F70: =_xlfn.XLOOKUP(B70,Planilha1!A:A,Planilha1!B:B) -> OUTROS | G70: 1000 | H70: 139.9 | I70: =IFERROR(H70/J70,"") -> 1.659943 | J70: 84.28 | K70: =L70*J70 -> 0 | M70: 5 | S70: =#REF!+6 -> #REF! | T70: =#REF!+8 -> #REF! | U70: =#REF!+4 -> #REF!
B71: 420114031 | C71: EnergyKick | D71: Laranja | E71: Pote | F71: =_xlfn.XLOOKUP(B71,Planilha1!A:A,Planilha1!B:B) -> OUTROS | G71: 1000 | H71: 139.9 | I71: =IFERROR(H71/J71,"") -> 1.659943 | J71: 84.28 | K71: =L71*J71 -> 0 | M71: 5 | S71: =S70+6 -> #REF! | T71: =T70+8 -> #REF! | U71: =U70+4 -> #REF!
B72: 420114032 | C72: EnergyKick | D72: Limão | E72: Pote | F72: =_xlfn.XLOOKUP(B72,Planilha1!A:A,Planilha1!B:B) -> OUTROS | G72: 1000 | H72: 139.9 | I72: =IFERROR(H72/J72,"") -> 1.659943 | J72: 84.28 | K72: =L72*J72 -> 0 | M72: 5 | S72: =S71+6 -> #REF! | T72: =T71+8 -> #REF! | U72: =U71+4 -> #REF!
B73: 420114037 | C73: EnergyKick | D73: Melancia | E73: Pote | F73: =_xlfn.XLOOKUP(B73,Planilha1!A:A,Planilha1!B:B) -> OUTROS | G73: 1000 | H73: 139.9 | I73: =IFERROR(H73/J73,"") -> 1.659943 | J73: 84.28 | K73: =L73*J73 -> 0 | M73: 5 | S73: =S72+6 -> #REF! | T73: =T72+8 -> #REF! | U73: =U72+4 -> #REF!
B74: 420114034 | C74: EnergyKick | D74: Maçã Verde | E74: Pote | F74: =_xlfn.XLOOKUP(B74,Planilha1!A:A,Planilha1!B:B) -> OUTROS | G74: 1000 | H74: 139.9 | I74: =IFERROR(H74/J74,"") -> 1.659943 | J74: 84.28 | K74: =L74*J74 -> 0 | M74: 5 | S74: =S73+6 -> #REF! | T74: =T73+8 -> #REF! | U74: =U73+4 -> #REF!
B75: 420214002 | C75: EnergyKick Caffeine | D75: Abacaxi | E75: Pote | F75: =_xlfn.XLOOKUP(B75,Planilha1!A:A,Planilha1!B:B) -> OUTROS | G75: 1000 | H75: 139.9 | I75: =IFERROR(H75/J75,"") -> 1.659943 | J75: 84.28 | K75: =L75*J75 -> 0 | M75: 5 | S75: =#REF!+6 -> #REF! | T75: =#REF!+8 -> #REF! | U75: =#REF!+4 -> #REF!
B76: 420214031 | C76: EnergyKick Caffeine | D76: Laranja | E76: Pote | F76: =_xlfn.XLOOKUP(B76,Planilha1!A:A,Planilha1!B:B) -> OUTROS | G76: 1000 | H76: 139.9 | I76: =IFERROR(H76/J76,"") -> 1.659943 | J76: 84.28 | K76: =L76*J76 -> 0 | M76: 5 | S76: =S75+6 -> #REF! | T76: =T75+8 -> #REF! | U76: =U75+4 -> #REF!
B77: 420214032 | C77: EnergyKick Caffeine | D77: Limão | E77: Pote | F77: =_xlfn.XLOOKUP(B77,Planilha1!A:A,Planilha1!B:B) -> OUTROS | G77: 1000 | H77: 139.9 | I77: =IFERROR(H77/J77,"") -> 1.659943 | J77: 84.28 | K77: =L77*J77 -> 0 | M77: 5 | S77: =S76+6 -> #REF! | T77: =T76+8 -> #REF! | U77: =U76+4 -> #REF!
B78: 420314031 | C78: Hydrolite | D78: Laranja | E78: Pote | F78: =_xlfn.XLOOKUP(B78,Planilha1!A:A,Planilha1!B:B) -> OUTROS | G78: 1000 | H78: 99.9 | I78: =IFERROR(H78/J78,"") -> 1.6597441 | J78: 60.19 | K78: =L78*J78 -> 0 | M78: 5 | S78: =S77+6 -> #REF! | T78: =T77+8 -> #REF! | U78: =U77+4 -> #REF!
B79: 420314032 | C79: Hydrolite | D79: Limão | E79: Pote | F79: =_xlfn.XLOOKUP(B79,Planilha1!A:A,Planilha1!B:B) -> OUTROS | G79: 1000 | H79: 99.9 | I79: =IFERROR(H79/J79,"") -> 1.6597441 | J79: 60.19 | K79: =L79*J79 -> 0 | M79: 5 | S79: =S78+6 -> #REF! | T79: =T78+8 -> #REF! | U79: =U78+4 -> #REF!
B80: 420314029 | C80: Hydrolite | D80: Frutas Vermelhas | E80: Pote | F80: =_xlfn.XLOOKUP(B80,Planilha1!A:A,Planilha1!B:B) -> OUTROS | G80: 1000 | H80: 99.9 | I80: =IFERROR(H80/J80,"") -> 1.6597441 | J80: 60.19 | K80: =L80*J80 -> 0 | M80: 5 | S80: =S79+6 -> #REF! | T80: =T79+8 -> #REF! | U80: =U79+4 -> #REF!
B81: 420514002 | C81: Recharge 4:1 | D81: Abacaxi | E81: Pote | F81: =_xlfn.XLOOKUP(B81,Planilha1!A:A,Planilha1!B:B) -> OUTROS | G81: 1000 | H81: 149.9 | I81: =IFERROR(H81/J81,"") -> 1.3515463 | J81: 110.91 | K81: =L81*J81 -> 0 | M81: 5 | S81: =S80+6 -> #REF! | T81: =T80+8 -> #REF! | U81: =U80+4 -> #REF!
B82: 420514018 | C82: Recharge 4:1 | D82: Chocolate | E82: Pote | F82: =_xlfn.XLOOKUP(B82,Planilha1!A:A,Planilha1!B:B) -> OUTROS | G82: 1000 | H82: 149.9 | I82: =IFERROR(H82/J82,"") -> 1.3515463 | J82: 110.91 | K82: =L82*J82 -> 0 | M82: 5 | S82: =S81+6 -> #REF! | T82: =T81+8 -> #REF! | U82: =U81+4 -> #REF!
B83: 420514022 | C83: Recharge 4:1 | D83: Coco | E83: Pote | F83: =_xlfn.XLOOKUP(B83,Planilha1!A:A,Planilha1!B:B) -> OUTROS | G83: 1000 | H83: 149.9 | I83: =IFERROR(H83/J83,"") -> 1.3515463 | J83: 110.91 | K83: =L83*J83 -> 0 | M83: 5 | S83: =S82+6 -> #REF! | T83: =T82+8 -> #REF! | U83: =U82+4 -> #REF!
B84: 420514036 | C84: Recharge 4:1 | D84: Maracujá | E84: Pote | F84: =_xlfn.XLOOKUP(B84,Planilha1!A:A,Planilha1!B:B) -> OUTROS | G84: 1000 | H84: 149.9 | I84: =IFERROR(H84/J84,"") -> 1.3515463 | J84: 110.91 | K84: =L84*J84 -> 0 | M84: 5 | S84: =S83+6 -> #REF! | T84: =T83+8 -> #REF! | U84: =U83+4 -> #REF!
B85: 421864129 | C85: Nitra Beet | D85: Laranja e Beterraba | E85: Pote | F85: OUTROS | G85: 405g | H85: 209.9 | I85: =IFERROR(H85/J85,"") -> 1.6600759 | J85: 126.44 | K85: =L85*J85 -> 0 | M85: 6 | S85: =S84+6 -> #REF! | T85: =T84+8 -> #REF! | U85: =U84+4 -> #REF!
B86: 421864130 | C86: Nitra Beet | D86: Limão e Beterraba | E86: Pote | F86: OUTROS | G86: 405g | H86: 209.9 | I86: =IFERROR(H86/J86,"") -> 1.6600759 | J86: 126.44 | K86: =L86*J86 -> 0 | M86: 6 | S86: =S85+6 -> #REF! | T86: =T85+8 -> #REF! | U86: =U85+4 -> #REF!
B87: 413804029 | C87: Pre Workout Original Stim Free | D87: Frutas Vermelhas | E87: Pote | F87: =_xlfn.XLOOKUP(B87,Planilha1!A:A,Planilha1!B:B) -> OUTROS | G87: 300 | H87: 129.9 | I87: =IFERROR(H87/J87,"") -> 1.6598518 | J87: 78.26 | K87: =L87*J87 -> 0 | M87: 14 | S87: =S86+6 -> #REF! | T87: =T86+8 -> #REF! | U87: =U86+4 -> #REF!
B88: 413804034 | C88: Pre Workout Original Stim Free | D88: Maçã Verde | E88: Pote | F88: =_xlfn.XLOOKUP(B88,Planilha1!A:A,Planilha1!B:B) -> OUTROS | G88: 300 | H88: 129.9 | I88: =IFERROR(H88/J88,"") -> 1.6598518 | J88: 78.26 | K88: =L88*J88 -> 0 | M88: 14 | S88: =S87+6 -> #REF! | T88: =T87+8 -> #REF! | U88: =U87+4 -> #REF!
B89: 411604029 | C89: Pre Workout Original | D89: Frutas Vermelhas | E89: Pote | F89: =_xlfn.XLOOKUP(B89,Planilha1!A:A,Planilha1!B:B) -> OUTROS | G89: 300 | H89: 129.9 | I89: =IFERROR(H89/J89,"") -> 1.6598518 | J89: 78.26 | K89: =L89*J89 -> 0 | M89: 14 | S89: =S88+6 -> #REF! | T89: =T88+8 -> #REF! | U89: =U88+4 -> #REF!
B90: 411604042 | C90: Pre Workout Original | D90: Pink Lemonade | E90: Pote | F90: =_xlfn.XLOOKUP(B90,Planilha1!A:A,Planilha1!B:B) -> OUTROS | G90: 300 | H90: 129.9 | I90: =IFERROR(H90/J90,"") -> 1.6598518 | J90: 78.26 | K90: =L90*J90 -> 0 | M90: 14 | S90: =S89+6 -> #REF! | T90: =T89+8 -> #REF! | U90: =U89+4 -> #REF!
B91: 411604056 | C91: Pre Workout Original | D91: Maçã Verde | E91: Pote | F91: =_xlfn.XLOOKUP(B91,Planilha1!A:A,Planilha1!B:B) -> OUTROS | G91: 300 | H91: 129.9 | I91: =IFERROR(H91/J91,"") -> 1.6598518 | J91: 78.26 | K91: =L91*J91 -> 0 | M91: 14 | S91: =#REF!+6 -> #REF! | T91: =#REF!+8 -> #REF! | U91: =#REF!+4 -> #REF!
B92: 411604057 | C92: Pre Workout Original | D92: Mango Twist | E92: Pote | F92: =_xlfn.XLOOKUP(B92,Planilha1!A:A,Planilha1!B:B) -> OUTROS | G92: 300 | H92: 129.9 | I92: =IFERROR(H92/J92,"") -> 1.6598518 | J92: 78.26 | K92: =L92*J92 -> 0 | M92: 14 | S92: =S91+6 -> #REF! | T92: =T91+8 -> #REF! | U92: =U91+4 -> #REF!
B93: 440218001 | C93: Control Original | D93: Sem Sabor | E93: Pote | F93: =_xlfn.XLOOKUP(B93,Planilha1!A:A,Planilha1!B:B) -> VITAMINAS | G93: 60 | H93: 75.9 | I93: =IFERROR(H93/J93,"") -> 1.5601233 | J93: 48.65 | K93: =L93*J93 -> 0 | M93: 24 | S93: =#REF!+6 -> #REF! | T93: =#REF!+8 -> #REF! | U93: =#REF!+4 -> #REF!
B94: 440118001 | C94: Control Night | D94: Sem Sabor | E94: Pote | F94: =_xlfn.XLOOKUP(B94,Planilha1!A:A,Planilha1!B:B) -> VITAMINAS | G94: 60 | H94: 65.9 | I94: =IFERROR(H94/J94,"") -> 1.5590253 | J94: 42.27 | K94: =L94*J94 -> 0 | M94: 24 | S94: =S93+6 -> #REF! | T94: =T93+8 -> #REF! | U94: =U93+4 -> #REF!
B95: 440318001 | C95: Supercut | D95: Sem Sabor | E95: Pote | F95: =_xlfn.XLOOKUP(B95,Planilha1!A:A,Planilha1!B:B) -> VITAMINAS | G95: 60 | H95: 79.9 | I95: =IFERROR(H95/J95,"") -> 1.6597424 | J95: 48.14 | K95: =L95*J95 -> 0 | M95: 24 | S95: =S94+6 -> #REF! | T95: =T94+8 -> #REF! | U95: =U94+4 -> #REF!
B96: 410608001 | C96: Palatinose™ | D96: Sem Sabor | E96: Pote | F96: =_xlfn.XLOOKUP(B96,Planilha1!A:A,Planilha1!B:B) -> OUTROS | G96: 400 | H96: 79.9 | I96: =IFERROR(H96/J96,"") -> 1.6597424 | J96: 48.14 | K96: =L96*J96 -> 0 | M96: 18 | S96: =S95+6 -> #REF! | T96: =T95+8 -> #REF! | U96: =U95+4 -> #REF!
B97: 430317001 | C97: Própolis Verde | D97: Sem Sabor | E97: Pote | F97: =_xlfn.XLOOKUP(B97,Planilha1!A:A,Planilha1!B:B) -> VITAMINAS | G97: 30 | H97: 77.9 | I97: =IFERROR(H97/J97,"") -> 1.659919 | J97: 46.93 | K97: =L97*J97 -> 0 | M97: 60 | S97: =S96+6 -> #REF! | T97: =T96+8 -> #REF! | U97: =U96+4 -> #REF!
B98: 431448032 | C98: Vitamina D3 + K2 | D98: Limão | E98: Frasco | F98: =_xlfn.XLOOKUP(B98,Planilha1!A:A,Planilha1!B:B) -> VITAMINAS | G98: 20ml | H98: 109.9 | I98: =IFERROR(H98/J98,"") -> 1.6598701 | J98: 66.21 | K98: =L98*J98 -> 0 | M98: 16 | S98: =S97+6 -> #REF! | T98: =T97+8 -> #REF! | U98: =U97+4 -> #REF!
B99: 430718001 | C99: Vitamina D3 - Mini caps | D99: - | E99: Pote | F99: =_xlfn.XLOOKUP(B99,Planilha1!A:A,Planilha1!B:B) -> VITAMINAS | G99: 60 cápsulas | H99: 45.9 | I99: =IFERROR(H99/J99,"") -> 1.6745713 | J99: 27.41 | K99: =L99*J99 -> 0 | M99: 15 | S99: =S98+6 -> #REF! | T99: =T98+8 -> #REF! | U99: =U98+4 -> #REF!
B100: 430716001 | C100: Vitamina D3 - Mini caps | D100: - | E100: Pote | F100: =_xlfn.XLOOKUP(B100,Planilha1!A:A,Planilha1!B:B) -> VITAMINAS | G100: 120 cápsulas | H100: 77.9 | I100: =IFERROR(H100/J100,"") -> 1.659919 | J100: 46.93 | K100: =L100*J100 -> 0 | M100: 15 | S100: =S99+6 -> #REF! | T100: =T99+8 -> #REF! | U100: =U99+4 -> #REF!
B101: 431317001 | C101: Coenzima Q10 | D101: Sem Sabor | E101: Pote | F101: =_xlfn.XLOOKUP(B101,Planilha1!A:A,Planilha1!B:B) -> VITAMINAS | G101: 30 | H101: 99.9 | I101: =IFERROR(H101/J101,"") -> 1.6683367 | J101: 59.88 | K101: =L101*J101 -> 0 | M101: 15 | S101: =S100+6 -> #REF! | T101: =T100+8 -> #REF! | U101: =U100+4 -> #REF!
B102: 431318001 | C102: Coenzima Q10 | D102: Sem Sabor | E102: Pote | F102: =_xlfn.XLOOKUP(B102,Planilha1!A:A,Planilha1!B:B) -> VITAMINAS | G102: 60 | H102: 169.9 | I102: =IFERROR(H102/J102,"") -> 1.6599902 | J102: 102.35 | K102: =L102*J102 -> 0 | M102: 15 | S102: =S101+6 -> #REF! | T102: =T101+8 -> #REF! | U102: =U101+4 -> #REF!
B103: 431517001 | C103: Complexo B | D103: Sem Sabor | E103: Pote | F103: =_xlfn.XLOOKUP(B103,Planilha1!A:A,Planilha1!B:B) -> VITAMINAS | G103: 30 | H103: 45.9 | I103: =IFERROR(H103/J103,"") -> 1.659436 | J103: 27.66 | K103: =L103*J103 -> 0 | M103: 15 | S103: =S102+6 -> #REF! | T103: =T102+8 -> #REF! | U103: =U102+4 -> #REF!
...

Sheet Planilha2
A1: 450327107 | B1: Collagen Advanced (10 unidades) | C1: Tangerina e Hibisco | D1: Sachê
A2: 460469001 | B2: Protein Brownie | D2: Pouch
A3: 430213134 | B3: Fresh Whey | C3: Fior Di Latte e Especiarias | D3: Pote
A4: 430213133 | B4: Fresh Whey | C4: Fior Di Latte e Limão Siciliano | D4: Pote
A5: 411127116 | B5: Whey Protein Isolado (10 und.) | C5: Caramelo Salgado | D5: Sachê

Sheet Planilha1
A1: codigo_produto | B1: grupo_remuneracao_variavel
A2: 520349101 | B2: BARRAS
A3: 520349100 | B3: BARRAS
A4: 520349079 | B4: BARRAS
A5: 520349051 | B5: BARRAS
A6: 520349027 | B6: BARRAS
A7: 520349080 | B7: BARRAS
A8: 520349083 | B8: BARRAS
A9: 520349081 | B9: BARRAS
A10: 510339080 | B10: BARRAS
A11: 510339081 | B11: BARRAS
A12: 510339079 | B12: BARRAS
A13: 510339023 | B13: BARRAS
... A650: 433809040 | B650: OUTROS

Sheet Cálculo
E1: Vendedor | CC1: Escolha o Tipo de cliente | CE1: Escolha a Região
D2: Vigência | E2: 45383 | CC2: BODYSHOP | CD2: 1 | CE2: Norte/Nordeste | CF2: 1
D3: Versão | E3: Vendedor V1 | CC3: CANAL VERDE | CD3: 1 | CE3: Centro Oeste | CF3: 1
D4: Valor total do pedido | E4: =SUMPRODUCT(U61:U368,X61:X368)+SUMPRODUCT(U61:U368,W61:W368) -> 0 | CC4: OUTROS ESPECIALIZADO | CD4: 1 | CE4: Sul/Sudeste | CF4: 1
D5: ID do Pedido | CC5: E-COMMERCE ESPECIALIZADO | CD5: 1 | CE5: Contas Nacionais | CF5: 1
D6: ID do Cliente | BF6: v3
D7: ID do Vendedor | F7: COMBOS NO PEDIDO | G7: =Pedido!G7 -> 0 | CD7: =IFERROR(VLOOKUP(Pedido!D5,Cálculo!CC1:CD5,2,0),0) -> 0 | CF7: =IFERROR(VLOOKUP(Pedido!D6,Cálculo!CE1:CF5,2,0),0) -> 0
D8: Frete | Q8: =TODAY() -> 46203 | BG8: 0
D9: Condição de Pagamento | F9: CASHBACK | Q9: 45327 | AR9: DUX | AX9: =SUMPRODUCT(U61:U350,W61:W350) -> 0 | BG9: Coqueteleiras | CD9: 1 | CE9: 1
D10: Desconto à vista | E10: 0.05
D11: Desconto Cartão de Crédito | E11: =IFERROR(VLOOKUP(E15,Sup!M:O,3,0),0) -> 0
D12: Desconto Frete FOB | E12: 0.02
D13: Multiplicador | E13: =IF(E9="À vista",1-E10,IF(AND(E9="A prazo",E15=15),0.96,IF(AND(E9="A prazo",E15=30),0.985,IF(AND(E9="A prazo",E15="15/30"),0.985,IF(AND(E9="A prazo",E15="14/21/28/35"),0.985,IF(AND(E9="A prazo",E14="C. Crédito",E15<=4),1-E11,1))))))*IF(E8="FOB",1-E12,1) -> 1
D14: Forma de Pagamento | Q14: =Q9-Q8 -> -876 | AR14: Eat Clean | AX14: =SUMPRODUCT(U28:U60,W28:W60) -> 0 | BG14: 900 | BH14: =SUMIF(G189:G192,BG14,W189:W192)+SUMIF(G223:G234,BG14,W223:W234)+SUMIF(G259:G266,BG14,W259:W266) -> 0 | BI14: =BH14/2 -> 0 | BJ14: =ROUNDDOWN(BI14,0) -> 0
A15: =IF(SUM(Pedido!L170:L176)=0,0,ISEVEN(SUM(Pedido!L170:L176))) -> 0 | D15: Prazo de Pagamento | Q15: =SUM(W106:W109) -> 0 | AR15: Total | AX15: =SUM(AX9:AX14) -> 0 | BG15: 1800 | BH15: =SUMIF(G235:G244,BG15,W235:W244)+SUMIF(G268:G275,BG15,W268:W275) -> 0 | BJ15: =BH15 -> 0 | BK15: NOVO/REATIVAÇÃO
D16: Margem Bruta Original (%) | E16: =AF373 -> 0
D17: Margem Bruta (%) | E17: =AT373 -> 0
D18: Resultado Bruto (R$) | E18: =E4*E17 -> 0
D22: Verba do pedido | E22: =BB372-AD373+BC372+Cálculo!CD24 -> 0
D23: Status | E23: =IF(SUM(Z:Z)<0,"Pedido Reprovado",IF(E4>0,IF(E22>=0,"Pedido Aprovado","Pedido Reprovado"),)) -> 0 | BG23: =IF(BH23=0,1,BH23) -> 1 | BH23: =ABS(IF(W73="",AH373,(U73*W73)-AH373)) -> 0
BI24: =IF(W73="",0,IF(BG23=1,BG23,(U73*W73)/BG23)) -> 0 | CC24: Bônus DZ13
A25: Categoria | D25: Informações do Produto | I25: Dados Financeiros | M25: Desconto por volume | T25: Dados do Pedido | AJ25: 0.1 | AK25: 0.085 | AL25: 0.02
F26: Embalagem | M26: 1800 | N26: 1800 | O26: 1800 | P26: 1800 | Q26: 30000 | R26: 45000 | S26: 10000000 | BZ26: Preço mínimo final negociável
B27: Cód. SKU | C27: Cód. Prod. | D27: Nome | E27: Sabor/Cor | F27: Modelo | G27: Volume | I27: Sugerido | J27: Mkup | K27: Desc | L27: Preço | M27: 1500 | N27: 1800 | O27: 1800 | P27: 1800 | Q27: 60 | R27: 120 | S27: 200 | T27: Preço | U27: Preço Efet. | V27: Negociação | W27: Qtd. | X27: Bonif. | Y27: Preço | Z27: ✓ | AA27: Rec. Máx. | AB27: Rec. Orig. | AC27: Dif. | AD27: Verba | AE27: Custo Orig. | AF27: MB Orig. | AG27: Total Sug. | AH27: Receita | AI27: Custo | AJ27: Imposto | AK27: Logistica | AL27: Comissão | AM27: Deduções | AN27: Rec. Líq. | AO27: Lucro Bruto | AP27: MB | AQ27: Preço efet. Mín | AR27: Cx. | AS27: MB | AT27: MB | AU27: MC | AW27: Classe | AX27: Classe | AY27: Peso | AZ27: Verba classif | BA27: Verba preço | BB27: Verba final | BC27: Subtração | BD27: Preço ref | BE27: Dif real
B28: 14842467944 | C28: Proteína Sabores | D28: Proteína Sabores | E28: Cacau | F28: Pote | G28: 600g | H28: 157.77 | I28: 648.4896 | J28: =IFERROR(IF(T28<>"",I28/T28,IF(AND(Y28="",V28=""),"",IF(V28="",I28/Y28,I28/V28))),"") | K28: =IF(Y28="","",IFERROR(1-(Y28/I28),0)) | L28: 391.6 | M28: =P28 -> 360.272 | N28: =P28 -> 360.272 | O28: =P28 -> 360.272 | P28: 360.272 | Q28: 360.272 | R28: 360.272 | S28: 360.272 | T28: =IF(V28>0,V28,IFERROR(IF(AND(W28<>"",X28<>""),AH28/W28,Y28),"")) | U28: =IFERROR((T28*W28)/(W28+X28),"") | Y28: =IF(AND(W28="",X28=""),"",$E$13*IF(V28<>"",V28,IF(SUMIF($C:$C,C28,$W:$W)>=$S$27,S28,IF(OR($AA$373>=$R$26,SUMIF($C:$C,C28,$W:$W)>=$R$27),R28,IF(OR($AA$373>=$Q$26,SUMIF($C:$C,C28,$W:$W)>=$Q$27),Q28,IF(OR($AA$373>=$P$26,SUMIF($C:$C,C28,$W:$W)>=$P$27),P28,IF(OR($AA$373>=$O$26,SUMIF($C:$C,C28,$W:$W)>=$O$27),O28,IF(OR($AA$373>=$N$26,SUMIF($C:$C,C28,$W:$W)>=$N$27),N28,IF($AA$373>=$M$26,M28,L28))))))))) | Z28: =IF(X28>W28,-1,IF(W28=0,0,IF(U28<(H28/0.75),-1,IF(W28<=3,0,0.0001)))) -> 0 | AA28: =IFERROR(L28*W28,0) -> 0 | AB28: =IFERROR(IF(OR($AA$373>=$S$26,SUMIF($C:$C,C28,$W:$W)>=$S$27),S28,IF(OR($AA$373>=$R$26,SUMIF($C:$C,C28,$W:$W)>=$R$27),R28,IF(OR($AA$373>=$Q$26,SUMIF($C:$C,C28,$W:$W)>=$Q$27),Q28,IF(OR($AA$373>=$P$26,SUMIF($C:$C,C28,$W:$W)>=$P$27),P28,IF(OR($AA$373>=$O$26,SUMIF($C:$C,C28,$W:$W)>=$O$27),O28,IF(OR($AA$373>=$N$26,SUMIF($C:$C,C28,$W:$W)>=$N$27),N28,IF($AA$373>=$M$26,M28,L28)))))))*W28,0) -> 0 | AC28: =IFERROR(IF(V28="",0,(IF(AND(W28="",X28=""),"",IF(OR($AA$373>=$S$26,SUMIF($C:$C,C28,$W:$W)>=$S$27),S28*$E$13,IF(OR($AA$373>=$R$26,SUMIF($C:$C,C28,$W:$W)>=$R$27),R28*$E$13,IF(OR($AA$373>=$Q$26,SUMIF($C:$C,C28,$W:$W)>=$Q$27),Q28*$E$13,IF(OR($AA$373>=$P$26,SUMIF($C:$C,C28,$W:$W)>=$P$27),P28*$E$13,IF(OR($AA$373>=$O$26,SUMIF($C:$C,C28,$W:$W)>=$O$27),O28*$E$13,IF(OR($AA$373>=$N$26,SUMIF($C:$C,C28,$W:$W)>=$N$27),N28*$E$13,IF($AA$373>=$M$26,M28*$E$13,L28))))))))-V28)*W28),0) -> 0 | AD28: =IFERROR(X28*T28,0) -> 0 | AE28: =IFERROR(W28*H28,0) -> 0 | AF28: =IFERROR(1-(AE28/AB28),0) -> 0 | AG28: =IFERROR(SUM(W28:X28)*I28,0) -> 0 | AH28: =IFERROR(IF(V28>0,V28*W28,(Y28*W28)),0) -> 0 | AI28: =IFERROR(SUM(W28)*H28,0) -> 0 | AJ28: =AH28*$AJ$25 -> 0 | AK28: =AH28*AK$25 -> 0 | AL28: =AH28*AL$25 -> 0 | AM28: =SUM(AJ28:AL28) -> 0 | AN28: =AH28-AM28 -> 0 | AO28: =AN28-AI28 -> 0 | AP28: =IFERROR(IF(V28<>"",1-(H28/V28),IF(Y28<>"",1-(H28/Y28),1-(H28/L28))),0) -> 0.5971144 | AQ28: =H28/0.75 -> 210.36 | AR28: 4 | AS28: =(AP28-MIN($AP$65:$AP$368))/(MAX($AP$65:$AP$368)-MIN($AP$65:$AP$368))*100 -> 59.71144 | AT28: =IFERROR(1-(AI28/AH28),0) -> 0 | AU28: =IFERROR(AO28/AH28,0) -> 0 | AW28: =VLOOKUP(AX28,Sup!#REF!,8,0) -> #REF! | AX28: Premium | AY28: 0 | BC28: =IF(BE28<0,BE28,0) -> 0 | BD28: =IFERROR(IF(AND(W28="",X28=""),"",IF(OR($AA$373>=$S$26,SUMIF($C:$C,C28,$W:$W)>=$S$27),S28,IF(OR($AA$373>=$R$26,SUMIF($C:$C,C28,$W:$W)>=$R$27),R28,IF(OR($AA$373>=$Q$26,SUMIF($C:$C,C28,$W:$W)>=$Q$27),Q28,IF(OR($AA$373>=$P$26,SUMIF($C:$C,C28,$W:$W)>=$P$27),P28,IF(OR($AA$373>=$O$26,SUMIF($C:$C,C28,$W:$W)>=$O$27),O28,IF(OR($AA$373>=$N$26,SUMIF($C:$C,C28,$W:$W)>=$N$27),N28,IF($AA$373>=$M$26,M28,L28)))))))*$E$13),0) | BE28: =IF(V28="",0,(V28*W28)-(BD28*W28)) -> 0 | BM28: =#REF!+24 -> #REF! | BW28: EAT CLEAN | BX28: =IFERROR(W28*U28,0) -> 0 | BY28: =VLOOKUP(B28,#REF!,13,0) -> #REF! | BZ28: 322 | CA28: =VLOOKUP(B28,Pedido!$B$16:$L$292,22,0) -> #N/A | CD28: 12 | CE28: =CD28/12 -> 1 | CF28: =CONCATENATE(CD28,CE28) -> 121 | CG28: válido
B29: 16041273496 | C29: Proteína Sabores | D29: Proteína Sabores | E29: Cookies | F29: Pote | G29: 600g | H29: 175.97 | I29: 648.4896 | J29: =IFERROR(IF(T29<>"",I29/T29,IF(AND(Y29="",V29=""),"",IF(V29="",I29/Y29,I29/V29))),"") | K29: =IF(Y29="","",IFERROR(1-(Y29/I29),0)) | L29: 391.6 | M29: =P29 -> 360.272 | N29: =P29 -> 360.272 | O29: =P29 -> 360.272 | P29: 360.272 | Q29: 360.272 | R29: 360.272 | S29: 360.272 | T29: =IF(V29>0,V29,IFERROR(IF(AND(W29<>"",X29<>""),AH29/W29,Y29),"")) | U29: =IFERROR((T29*W29)/(W29+X29),"") | Y29: =IF(AND(W29="",X29=""),"",$E$13*IF(V29<>"",V29,IF(SUMIF($C:$C,C29,$W:$W)>=$S$27,S29,IF(OR($AA$373>=$R$26,SUMIF($C:$C,C29,$W:$W)>=$R$27),R29,IF(OR($AA$373>=$Q$26,SUMIF($C:$C,C29,$W:$W)>=$Q$27),Q29,IF(OR($AA$373>=$P$26,SUMIF($C:$C,C29,$W:$W)>=$P$27),P29,IF(OR($AA$373>=$O$26,SUMIF($C:$C,C29,$W:$W)>=$O$27),O29,IF(OR($AA$373>=$N$26,SUMIF($C:$C,C29,$W:$W)>=$N$27),N29,IF($AA$373>=$M$26,M29,L29))))))))) | Z29: =IF(X29>W29,-1,IF(W29=0,0,IF(U29<(H29/0.75),-1,IF(W29<=3,0,0.0001)))) -> 0 | AA29: =IFERROR(L29*W29,0) -> 0 | AB29: =IFERROR(IF(OR($AA$373>=$S$26,SUMIF($C:$C,C29,$W:$W)>=$S$27),S29,IF(OR($AA$373>=$R$26,SUMIF($C:$C,C29,$W:$W)>=$R$27),R29,IF(OR($AA$373>=$Q$26,SUMIF($C:$C,C29,$W:$W)>=$Q$27),Q29,IF(OR($AA$373>=$P$26,SUMIF($C:$C,C29,$W:$W)>=$P$27),P29,IF(OR($AA$373>=$O$26,SUMIF($C:$C,C29,$W:$W)>=$O$27),O29,IF(OR($AA$373>=$N$26,SUMIF($C:$C,C29,$W:$W)>=$N$27),N29,IF($AA$373>=$M$26,M29,L29)))))))*W29,0) -> 0 | AC29: =IFERROR(IF(V29="",0,(IF(AND(W29="",X29=""),"",IF(OR($AA$373>=$S$26,SUMIF($C:$C,C29,$W:$W)>=$S$27),S29*$E$13,IF(OR($AA$373>=$R$26,SUMIF($C:$C,C29,$W:$W)>=$R$27),R29*$E$13,IF(OR($AA$373>=$Q$26,SUMIF($C:$C,C29,$W:$W)>=$Q$27),Q29*$E$13,IF(OR($AA$373>=$P$26,SUMIF($C:$C,C29,$W:$W)>=$P$27),P29*$E$13,IF(OR($AA$373>=$O$26,SUMIF($C:$C,C29,$W:$W)>=$O$27),O29*$E$13,IF(OR($AA$373>=$N$26,SUMIF($C:$C,C29,$W:$W)>=$N$27),N29*$E$13,IF($AA$373>=$M$26,M29*$E$13,L29))))))))-V29)*W29),0) -> 0 | AD29: =IFERROR(X29*T29,0) -> 0 | AE29: =IFERROR(W29*H29,0) -> 0 | AF29: =IFERROR(1-(AE29/AB29),0) -> 0 | AG29: =IFERROR(SUM(W29:X29)*I29,0) -> 0 | AH29: =IFERROR(IF(V29>0,V29*W29,(Y29*W29)),0) -> 0 | AI29: =IFERROR(SUM(W29)*H29,0) -> 0 | AJ29: =AH29*$AJ$25 -> 0 | AK29: =AH29*AK$25 -> 0 | AL29: =AH29*AL$25 -> 0 | AM29: =SUM(AJ29:AL29) -> 0 | AN29: =AH29-AM29 -> 0 | AO29: =AN29-AI29 -> 0 | AP29: =IFERROR(IF(V29<>"",1-(H29/V29),IF(Y29<>"",1-(H29/Y29),1-(H29/L29))),0) -> 0.55063841 | AQ29: =H29/0.75 -> 234.62667 | AR29: 4 | AS29: =(AP29-MIN($AP$65:$AP$368))/(MAX($AP$65:$AP$368)-MIN($AP$65:$AP$368))*100 -> 55.063841 | AT29: =IFERROR(1-(AI29/AH29),0) -> 0 | AU29: =IFERROR(AO29/AH29,0) -> 0 | AW29: =VLOOKUP(AX29,Sup!#REF!,8,0) -> #REF! | AX29: Premium | AY29: 0 | BC29: =IF(BE29<0,BE29,0) -> 0 | BD29: =IFERROR(IF(AND(W29="",X29=""),"",IF(OR($AA$373>=$S$26,SUMIF($C:$C,C29,$W:$W)>=$S$27),S29,IF(OR($AA$373>=$R$26,SUMIF($C:$C,C29,$W:$W)>=$R$27),R29,IF(OR($AA$373>=$Q$26,SUMIF($C:$C,C29,$W:$W)>=$Q$27),Q29,IF(OR($AA$373>=$P$26,SUMIF($C:$C,C29,$W:$W)>=$P$27),P29,IF(OR($AA$373>=$O$26,SUMIF($C:$C,C29,$W:$W)>=$O$27),O29,IF(OR($AA$373>=$N$26,SUMIF($C:$C,C29,$W:$W)>=$N$27),N29,IF($AA$373>=$M$26,M29,L29)))))))*$E$13),0) | BE29: =IF(V29="",0,(V29*W29)-(BD29*W29)) -> 0 | BM29: =BM28+24 -> #REF! | BW29: EAT CLEAN | BX29: =IFERROR(W29*U29,0) -> 0 | BY29: =VLOOKUP(B29,#REF!,13,0) -> #REF! | BZ29: 322 | CA29: =VLOOKUP(B29,Pedido!$B$16:$L$292,22,0) -> #N/A | CD29: =CD28+12 -> 24 | CE29: =CD29/12 -> 2 | CF29: =CONCATENATE(CD29,CE29) -> 242 | CG29: válido
B30: 520412027 | C30: Proteína Sabores | D30: Proteína Sabores | E30: Doce de Leite | F30: Pote | G30: 600g | H30: 175.97 | I30: 648.4896 | J30: =IFERROR(IF(T30<>"",I30/T30,IF(AND(Y30="",V30=""),"",IF(V30="",I30/Y30,I30/V30))),"") | K30: =IF(Y30="","",IFERROR(1-(Y30/I30),0)) | L30: 391.6 | M30: =P30 -> 360.272 | N30: =P30 -> 360.272 | O30: =P30 -> 360.272 | P30: 360.272 | Q30: 360.272 | R30: 360.272 | S30: 360.272 | T30: =IF(V30>0,V30,IFERROR(IF(AND(W30<>"",X30<>""),AH30/W30,Y30),"")) | U30: =IFERROR((T30*W30)/(W30+X30),"") | Y30: =IF(AND(W30="",X30=""),"",$E$13*IF(V30<>"",V30,IF(SUMIF($C:$C,C30,$W:$W)>=$S$27,S30,IF(OR($AA$373>=$R$26,SUMIF($C:$C,C30,$W:$W)>=$R$27),R30,IF(OR($AA$373>=$Q$26,SUMIF($C:$C,C30,$W:$W)>=$Q$27),Q30,IF(OR($AA$373>=$P$26,SUMIF($C:$C,C30,$W:$W)>=$P$27),P30,IF(OR($AA$373>=$O$26,SUMIF($C:$C,C30,$W:$W)>=$O$27),O30,IF(OR($AA$373>=$N$26,SUMIF($C:$C,C30,$W:$W)>=$N$27),N30,IF($AA$373>=$M$26,M30,L30))))))))) | Z30: =IF(X30>W30,-1,IF(W30=0,0,IF(U30<(H30/0.75),-1,IF(W30<=3,0,0.0001)))) -> 0 | AA30: =IFERROR(L30*W30,0) -> 0 | AB30: =IFERROR(IF(OR($AA$373>=$S$26,SUMIF($C:$C,C30,$W:$W)>=$S$27),S30,IF(OR($AA$373>=$R$26,SUMIF($C:$C,C30,$W:$W)>=$R$27),R30,IF(OR($AA$373>=$Q$26,SUMIF($C:$C,C30,$W:$W)>=$Q$27),Q30,IF(OR($AA$373>=$P$26,SUMIF($C:$C,C30,$W:$W)>=$P$27),P30,IF(OR($AA$373>=$O$26,SUMIF($C:$C,C30,$W:$W)>=$O$27),O30,IF(OR($AA$373>=$N$26,SUMIF($C:$C,C30,$W:$W)>=$N$27),N30,IF($AA$373>=$M$26,M30,L30)))))))*W30,0) -> 0 | AC30: =IFERROR(IF(V30="",0,(IF(AND(W30="",X30=""),"",IF(OR($AA$373>=$S$26,SUMIF($C:$C,C30,$W:$W)>=$S$27),S30*$E$13,IF(OR($AA$373>=$R$26,SUMIF($C:$C,C30,$W:$W)>=$R$27),R30*$E$13,IF(OR($AA$373>=$Q$26,SUMIF($C:$C,C30,$W:$W)>=$Q$27),Q30*$E$13,IF(OR($AA$373>=$P$26,SUMIF($C:$C,C30,$W:$W)>=$P$27),P30*$E$13,IF(OR($AA$373>=$O$26,SUMIF($C:$C,C30,$W:$W)>=$O$27),O30*$E$13,IF(OR($AA$373>=$N$26,SUMIF($C:$C,C30,$W:$W)>=$N$27),N30*$E$13,IF($AA$373>=$M$26,M30*$E$13,L30))))))))-V30)*W30),0) -> 0 | AD30: =IFERROR(X30*T30,0) -> 0 | AE30: =IFERROR(W30*H30,0) -> 0 | AF30: =IFERROR(1-(AE30/AB30),0) -> 0 | AG30: =IFERROR(SUM(W30:X30)*I30,0) -> 0 | AH30: =IFERROR(IF(V30>0,V30*W30,(Y30*W30)),0) -> 0 | AI30: =IFERROR(SUM(W30)*H30,0) -> 0 | AJ30: =AH30*$AJ$25 -> 0 | AK30: =AH30*AK$25 -> 0 | AL30: =AH30*AL$25 -> 0 | AM30: =SUM(AJ30:AL30) -> 0 | AN30: =AH30-AM30 -> 0 | AO30: =AN30-AI30 -> 0 | AP30: =IFERROR(IF(V30<>"",1-(H30/V30),IF(Y30<>"",1-(H30/Y30),1-(H30/L30))),0) -> 0.55063841 | AQ30: =H30/0.75 -> 234.62667 | AR30: 4 | AS30: =(AP30-MIN($AP$65:$AP$368))/(MAX($AP$65:$AP$368)-MIN($AP$65:$AP$368))*100 -> 55.063841 | AT30: =IFERROR(1-(AI30/AH30),0) -> 0 | AU30: =IFERROR(AO30/AH30,0) -> 0 | AW30: =VLOOKUP(AX30,Sup!#REF!,8,0) -> #REF! | AX30: Premium | AY30: 0 | BC30: =IF(BE30<0,BE30,0) -> 0 | BD30: =IFERROR(IF(AND(W30="",X30=""),"",IF(OR($AA$373>=$S$26,SUMIF($C:$C,C30,$W:$W)>=$S$27),S30,IF(OR($AA$373>=$R$26,SUMIF($C:$C,C30,$W:$W)>=$R$27),R30,IF(OR($AA$373>=$Q$26,SUMIF($C:$C,C30,$W:$W)>=$Q$27),Q30,IF(OR($AA$373>=$P$26,SUMIF($C:$C,C30,$W:$W)>=$P$27),P30,IF(OR($AA$373>=$O$26,SUMIF($C:$C,C30,$W:$W)>=$O$27),O30,IF(OR($AA$373>=$N$26,SUMIF($C:$C,C30,$W:$W)>=$N$27),N30,IF($AA$373>=$M$26,M30,L30)))))))*$E$13),0) | BE30: =IF(V30="",0,(V30*W30)-(BD30*W30)) -> 0 | BM30: =BM29+24 -> #REF! | BW30: EAT CLEAN | BX30: =IFERROR(W30*U30,0) -> 0 | BY30: =VLOOKUP(B30,#REF!,13,0) -> #REF! | BZ30: 322 | CA30: =VLOOKUP(B30,Pedido!$B$16:$L$292,22,0) -> #REF! | CD30: =CD29+12 -> 36 | CE30: =CD30/12 -> 3 | CF30: =CONCATENATE(CD30,CE30) -> 363 | CG30: válido
B31: 14797218847 | C31: Proteína Sabores | D31: Proteína Sabores | E31: Salted Caramel | F31: Pote | G31: 600g | H31: 192.81 | I31: 648.4896 | J31: =IFERROR(IF(T31<>"",I31/T31,IF(AND(Y31="",V31=""),"",IF(V31="",I31/Y31,I31/V31))),"") | K31: =IF(Y31="","",IFERROR(1-(Y31/I31),0)) | L31: 391.6 | M31: =P31 -> 360.272 | N31: =P31 -> 360.272 | O31: =P31 -> 360.272 | P31: 360.272 | Q31: 360.272 | R31: 360.272 | S31: 360.272 | T31: =IF(V31>0,V31,IFERROR(IF(AND(W31<>"",X31<>""),AH31/W31,Y31),"")) | U31: =IFERROR((T31*W31)/(W31+X31),"") | Y31: =IF(AND(W31="",X31=""),"",$E$13*IF(V31<>"",V31,IF(SUMIF($C:$C,C31,$W:$W)>=$S$27,S31,IF(OR($AA$373>=$R$26,SUMIF($C:$C,C31,$W:$W)>=$R$27),R31,IF(OR($AA$373>=$Q$26,SUMIF($C:$C,C31,$W:$W)>=$Q$27),Q31,IF(OR($AA$373>=$P$26,SUMIF($C:$C,C31,$W:$W)>=$P$27),P31,IF(OR($AA$373>=$O$26,SUMIF($C:$C,C31,$W:$W)>=$O$27),O31,IF(OR($AA$373>=$N$26,SUMIF($C:$C,C31,$W:$W)>=$N$27),N31,IF($AA$373>=$M$26,M31,L31))))))))) | Z31: =IF(X31>W31,-1,IF(W31=0,0,IF(U31<(H31/0.75),-1,IF(W31<=3,0,0.0001)))) -> 0 | AA31: =IFERROR(L31*W31,0) -> 0 | AB31: =IFERROR(IF(OR($AA$373>=$S$26,SUMIF($C:$C,C31,$W:$W)>=$S$27),S31,IF(OR($AA$373>=$R$26,SUMIF($C:$C,C31,$W:$W)>=$R$27),R31,IF(OR($AA$373>=$Q$26,SUMIF($C:$C,C31,$W:$W)>=$Q$27),Q31,IF(OR($AA$373>=$P$26,SUMIF($C:$C,C31,$W:$W)>=$P$27),P31,IF(OR($AA$373>=$O$26,SUMIF($C:$C,C31,$W:$W)>=$O$27),O31,IF(OR($AA$373>=$N$26,SUMIF($C:$C,C31,$W:$W)>=$N$27),N31,IF($AA$373>=$M$26,M31,L31)))))))*W31,0) -> 0 | AC31: =IFERROR(IF(V31="",0,(IF(AND(W31="",X31=""),"",IF(OR($AA$373>=$S$26,SUMIF($C:$C,C31,$W:$W)>=$S$27),S31*$E$13,IF(OR($AA$373>=$R$26,SUMIF($C:$C,C31,$W:$W)>=$R$27),R31*$E$13,IF(OR($AA$373>=$Q$26,SUMIF($C:$C,C31,$W:$W)>=$Q$27),Q31*$E$13,IF(OR($AA$373>=$P$26,SUMIF($C:$C,C31,$W:$W)>=$P$27),P31*$E$13,IF(OR($AA$373>=$O$26,SUMIF($C:$C,C31,$W:$W)>=$O$27),O31*$E$13,IF(OR($AA$373>=$N$26,SUMIF($C:$C,C31,$W:$W)>=$N$27),N31*$E$13,IF($AA$373>=$M$26,M31*$E$13,L31))))))))-V31)*W31),0) -> 0 | AD31: =IFERROR(X31*T31,0) -> 0 | AE31: =IFERROR(W31*H31,0) -> 0 | AF31: =IFERROR(1-(AE31/AB31),0) -> 0 | AG31: =IFERROR(SUM(W31:X31)*I31,0) -> 0 | AH31: =IFERROR(IF(V31>0,V31*W31,(Y31*W31)),0) -> 0 | AI31: =IFERROR(SUM(W31)*H31,0) -> 0 | AJ31: =AH31*$AJ$25 -> 0 | AK31: =AH31*AK$25 -> 0 | AL31: =AH31*AL$25 -> 0 | AM31: =SUM(AJ31:AL31) -> 0 | AN31: =AH31-AM31 -> 0 | AO31: =AN31-AI31 -> 0 | AP31: =IFERROR(IF(V31<>"",1-(H31/V31),IF(Y31<>"",1-(H31/Y31),1-(H31/L31))),0) -> 0.50763534 | AQ31: =H31/0.75 -> 257.08 | AR31: 4 | AS31: =(AP31-MIN($AP$65:$AP$368))/(MAX($AP$65:$AP$368)-MIN($AP$65:$AP$368))*100 -> 50.763534 | AT31: =IFERROR(1-(AI31/AH31),0) -> 0 | AU31: =IFERROR(AO31/AH31,0) -> 0 | AW31: =VLOOKUP(AX31,Sup!#REF!,8,0) -> #REF! | AX31: Premium | AY31: 0 | BC31: =IF(BE31<0,BE31,0) -> 0 | BD31: =IFERROR(IF(AND(W31="",X31=""),"",IF(OR($AA$373>=$S$26,SUMIF($C:$C,C31,$W:$W)>=$S$27),S31,IF(OR($AA$373>=$R$26,SUMIF($C:$C,C31,$W:$W)>=$R$27),R31,IF(OR($AA$373>=$Q$26,SUMIF($C:$C,C31,$W:$W)>=$Q$27),Q31,IF(OR($AA$373>=$P$26,SUMIF($C:$C,C31,$W:$W)>=$P$27),P31,IF(OR($AA$373>=$O$26,SUMIF($C:$C,C31,$W:$W)>=$O$27),O31,IF(OR($AA$373>=$N$26,SUMIF($C:$C,C31,$W:$W)>=$N$27),N31,IF($AA$373>=$M$26,M31,L31)))))))*$E$13),0) | BE31: =IF(V31="",0,(V31*W31)-(BD31*W31)) -> 0 | BM31: =BM29+24 -> #REF! | BW31: EAT CLEAN | BX31: =IFERROR(W31*U31,0) -> 0 | BY31: =VLOOKUP(B31,#REF!,13,0) -> #REF! | BZ31: 322 | CA31: =VLOOKUP(B31,Pedido!$B$16:$L$292,22,0) -> #N/A | CD31: =CD29+12 -> 36 | CE31: =CD31/12 -> 3 | CF31: =CONCATENATE(CD31,CE31) -> 363 | CG31: válido
B32: 14839602048 | C32: Creatina Monohidratada | D32: Creatina Monohidratada | E32: Sem sabor | F32: Pote | G32: 300 | H32: 74.16 | I32: 599.6 | J32: =IFERROR(IF(T32<>"",I32/T32,IF(AND(Y32="",V32=""),"",IF(V32="",I32/Y32,I32/V32))),"") | K32: =IF(Y32="","",IFERROR(1-(Y32/I32),0)) | L32: 460 | M32: =P32 -> 259.6 | N32: =P32 -> 259.6 | O32: =P32 -> 259.6 | P32: 259.6 | Q32: 259.6 | R32: 259.6 | S32: 259.6 | T32: =IF(V32>0,V32,IFERROR(IF(AND(W32<>"",X32<>""),AH32/W32,Y32),"")) | U32: =IFERROR((T32*W32)/(W32+X32),"") | Y32: =IF(AND(W32="",X32=""),"",$E$13*IF(V32<>"",V32,IF(SUMIF($C:$C,C32,$W:$W)>=$S$27,S32,IF(OR($AA$373>=$R$26,SUMIF($C:$C,C32,$W:$W)>=$R$27),R32,IF(OR($AA$373>=$Q$26,SUMIF($C:$C,C32,$W:$W)>=$Q$27),Q32,IF(OR($AA$373>=$P$26,SUMIF($C:$C,C32,$W:$W)>=$P$27),P32,IF(OR($AA$373>=$O$26,SUMIF($C:$C,C32,$W:$W)>=$O$27),O32,IF(OR($AA$373>=$N$26,SUMIF($C:$C,C32,$W:$W)>=$N$27),N32,IF($AA$373>=$M$26,M32,L32))))))))) | Z32: =IF(X32>W32,-1,IF(W32=0,0,IF(U32<(H32/0.75),-1,IF(W32<=3,0,0.0001)))) -> 0 | AA32: =IFERROR(L32*W32,0) -> 0 | AB32: =IFERROR(IF(OR($AA$373>=$S$26,SUMIF($C:$C,C32,$W:$W)>=$S$27),S32,IF(OR($AA$373>=$R$26,SUMIF($C:$C,C32,$W:$W)>=$R$27),R32,IF(OR($AA$373>=$Q$26,SUMIF($C:$C,C32,$W:$W)>=$Q$27),Q32,IF(OR($AA$373>=$P$26,SUMIF($C:$C,C32,$W:$W)>=$P$27),P32,IF(OR($AA$373>=$O$26,SUMIF($C:$C,C32,$W:$W)>=$O$27),O32,IF(OR($AA$373>=$N$26,SUMIF($C:$C,C32,$W:$W)>=$N$27),N32,IF($AA$373>=$M$26,M32,L32)))))))*W32,0) -> 0 | AC32: =IFERROR(IF(V32="",0,(IF(AND(W32="",X32=""),"",IF(OR($AA$373>=$S$26,SUMIF($C:$C,C32,$W:$W)>=$S$27),S32*$E$13,IF(OR($AA$373>=$R$26,SUMIF($C:$C,C32,$W:$W)>=$R$27),R32*$E$13,IF(OR($AA$373>=$Q$26,SUMIF($C:$C,C32,$W:$W)>=$Q$27),Q32*$E$13,IF(OR($AA$373>=$P$26,SUMIF($C:$C,C32,$W:$W)>=$P$27),P32*$E$13,IF(OR($AA$373>=$O$26,SUMIF($C:$C,C32,$W:$W)>=$O$27),O32*$E$13,IF(OR($AA$373>=$N$26,SUMIF($C:$C,C32,$W:$W)>=$N$27),N32*$E$13,IF($AA$373>=$M$26,M32*$E$13,L32))))))))-V32)*W32),0) -> 0 | AD32: =IFERROR(X32*T32,0) -> 0 | AE32: =IFERROR(W32*H32,0) -> 0 | AF32: =IFERROR(1-(AE32/AB32),0) -> 0 | AG32: =IFERROR(SUM(W32:X32)*I32,0) -> 0 | AH32: =IFERROR(IF(V32>0,V32*W32,(Y32*W32)),0) -> 0 | AI32: =IFERROR(SUM(W32)*H32,0) -> 0 | AJ32: =AH32*$AJ$25 -> 0 | AK32: =AH32*AK$25 -> 0 | AL32: =AH32*AL$25 -> 0 | AM32: =SUM(AJ32:AL32) -> 0 | AN32: =AH32-AM32 -> 0 | AO32: =AN32-AI32 -> 0 | AP32: =IFERROR(IF(V32<>"",1-(H32/V32),IF(Y32<>"",1-(H32/Y32),1-(H32/L32))),0) -> 0.83878261 | AQ32: =H32/0.75 -> 98.88 | AR32: 4 | AS32: =(AP32-MIN($AP$65:$AP$368))/(MAX($AP$65:$AP$368)-MIN($AP$65:$AP$368))*100 -> 83.878261 | AT32: =IFERROR(1-(AI32/AH32),0) -> 0 | AU32: =IFERROR(AO32/AH32,0) -> 0 | AW32: =VLOOKUP(AX32,Sup!#REF!,8,0) -> #REF! | AX32: Premium | AY32: 0 | BC32: =IF(BE32<0,BE32,0) -> 0 | BD32: =IFERROR(IF(AND(W32="",X32=""),"",IF(OR($AA$373>=$S$26,SUMIF($C:$C,C32,$W:$W)>=$S$27),S32,IF(OR($AA$373>=$R$26,SUMIF($C:$C,C32,$W:$W)>=$R$27),R32,IF(OR($AA$373>=$Q$26,SUMIF($C:$C,C32,$W:$W)>=$Q$27),Q32,IF(OR($AA$373>=$P$26,SUMIF($C:$C,C32,$W:$W)>=$P$27),P32,IF(OR($AA$373>=$O$26,SUMIF($C:$C,C32,$W:$W)>=$O$27),O32,IF(OR($AA$373>=$N$26,SUMIF($C:$C,C32,$W:$W)>=$N$27),N32,IF($AA$373>=$M$26,M32,L32)))))))*$E$13),0) | BE32: =IF(V32="",0,(V32*W32)-(BD32*W32)) -> 0 | BM32: =BM31+24 -> #REF! | BW32: EAT CLEAN | BX32: =IFERROR(W32*U32,0) -> 0 | BY32: =VLOOKUP(B32,#REF!,13,0) -> #REF! | BZ32: 236 | CA32: =VLOOKUP(B32,Pedido!$B$16:$L$292,22,0) -> #N/A | CD32: =CD31+12 -> 48 | CE32: =CD32/12 -> 4 | CF32: =CONCATENATE(CD32,CE32) -> 484 | CG32: válido
B33: 520554098 | C33: Creatina Eat | D33: Creatina Monohidratada | E33: Melancia com Morango | F33: Pote | G33: 210 | H33: 175.97 | I33: =119.9*4 -> 479.6 | L33: 343.6 | M33: 263.6 | N33: 263.6 | O33: 263.6 | P33: 263.6 | Q33: 263.6 | R33: 263.6 | S33: 263.6
B34: 520554099 | C34: Creatina Eat | D34: Creatina Monohidratada | E34: Blue Lemonade | F34: Pote | G34: 210 | H34: 175.97 | I34: 479.6 | L34: 343.6 | M34: 263.6 | N34: 263.6 | O34: 263.6 | P34: 263.6 | Q34: 263.6 | R34: 263.6 | S34: 263.6
B35: 520554034 | C35: Creatina Eat | D35: Creatina Monohidratada | E35: Maçã Verde | F35: Pote | G35: 210 | H35: 175.97 | I35: 479.6 | L35: 343.6 | M35: 263.6 | N35: 263.6 | O35: 263.6 | P35: 263.6 | Q35: 263.6 | R35: 263.6 | S35: 263.6
B36: 16129967737 | C36: Nutritional Yeast | D36: Nutritional Yeast | E36: - | F36: Pote | G36: 100g | H36: 34.6 | I36: 112.9 | J36: =IFERROR(IF(T36<>"",I36/T36,IF(AND(Y36="",V36=""),"",IF(V36="",I36/Y36,I36/V36))),"") | K36: =IF(Y36="","",IFERROR(1-(Y36/I36),0)) | L36: 59.8 | M36: =P36 -> 59.8 | N36: =P36 -> 59.8 | O36: =P36 -> 59.8 | P36: 59.8 | Q36: 59.8 | R36: 59.8 | S36: 59.8 | T36: =IF(V36>0,V36,IFERROR(IF(AND(W36<>"",X36<>""),AH36/W36,Y36),"")) | U36: =IFERROR((T36*W36)/(W36+X36),"") | Y36: =IF(AND(W36="",X36=""),"",$E$13*IF(V36<>"",V36,IF(SUMIF($C:$C,C36,$W:$W)>=$S$27,S36,IF(OR($AA$373>=$R$26,SUMIF($C:$C,C36,$W:$W)>=$R$27),R36,IF(OR($AA$373>=$Q$26,SUMIF($C:$C,C36,$W:$W)>=$Q$27),Q36,IF(OR($AA$373>=$P$26,SUMIF($C:$C,C36,$W:$W)>=$P$27),P36,IF(OR($AA$373>=$O$26,SUMIF($C:$C,C36,$W:$W)>=$O$27),O36,IF(OR($AA$373>=$N$26,SUMIF($C:$C,C36,$W:$W)>=$N$27),N36,IF($AA$373>=$M$26,M36,L36))))))))) | Z36: =IF(X36>W36,-1,IF(W36=0,0,IF(U36<(H36/0.75),-1,IF(W36<=3,0,0.0001)))) -> 0 | AA36: =IFERROR(L36*W36,0) -> 0 | AB36: =IFERROR(IF(OR($AA$373>=$S$26,SUMIF($C:$C,C36,$W:$W)>=$S$27),S36,IF(OR($AA$373>=$R$26,SUMIF($C:$C,C36,$W:$W)>=$R$27),R36,IF(OR($AA$373>=$Q$26,SUMIF($C:$C,C36,$W:$W)>=$Q$27),Q36,IF(OR($AA$373>=$P$26,SUMIF($C:$C,C36,$W:$W)>=$P$27),P36,IF(OR($AA$373>=$O$26,SUMIF($C:$C,C36,$W:$W)>=$O$27),O36,IF(OR($AA$373>=$N$26,SUMIF($C:$C,C36,$W:$W)>=$N$27),N36,IF($AA$373>=$M$26,M36,L36)))))))*W36,0) -> 0 | AC36: =IFERROR(IF(V36="",0,(IF(AND(W36="",X36=""),"",IF(OR($AA$373>=$S$26,SUMIF($C:$C,C36,$W:$W)>=$S$27),S36*$E$13,IF(OR($AA$373>=$R$26,SUMIF($C:$C,C36,$W:$W)>=$R$27),R36*$E$13,IF(OR($AA$373>=$Q$26,SUMIF($C:$C,C36,$W:$W)>=$Q$27),Q36*$E$13,IF(OR($AA$373>=$P$26,SUMIF($C:$C,C36,$W:$W)>=$P$27),P36*$E$13,IF(OR($AA$373>=$O$26,SUMIF($C:$C,C36,$W:$W)>=$O$27),O36*$E$13,IF(OR($AA$373>=$N$26,SUMIF($C:$C,C36,$W:$W)>=$N$27),N36*$E$13,IF($AA$373>=$M$26,M36*$E$13,L36))))))))-V36)*W36),0) -> 0 | AD36: =IFERROR(X36*T36,0) -> 0 | AE36: =IFERROR(W36*H36,0) -> 0 | AF36: =IFERROR(1-(AE36/AB36),0) -> 0 | AG36: =IFERROR(SUM(W36:X36)*I36,0) -> 0 | AH36: =IFERROR(IF(V36>0,V36*W36,(Y36*W36)),0) -> 0 | AI36: =IFERROR(SUM(W36)*H36,0) -> 0 | AJ36: =AH36*$AJ$25 -> 0 | AK36: =AH36*AK$25 -> 0 | AL36: =AH36*AL$25 -> 0 | AM36: =SUM(AJ36:AL36) -> 0 | AN36: =AH36-AM36 -> 0 | AO36: =AN36-AI36 -> 0 | AP36: =IFERROR(IF(V36<>"",1-(H36/V36),IF(Y36<>"",1-(H36/Y36),1-(H36/L36))),0) -> 0.42140468 | AQ36: =H36/0.75 -> 46.133333 | AR36: 4 | AS36: =(AP36-MIN($AP$65:$AP$368))/(MAX($AP$65:$AP$368)-MIN($AP$65:$AP$368))*100 -> 42.140468 | AT36: =IFERROR(1-(AI36/AH36),0) -> 0 | AU36: =IFERROR(AO36/AH36,0) -> 0 | AW36: =VLOOKUP(AX36,Sup!#REF!,8,0) -> #REF! | AX36: Premium | AY36: 0 | BC36: =IF(BE36<0,BE36,0) -> 0 | BD36: =IFERROR(IF(AND(W36="",X36=""),"",IF(OR($AA$373>=$S$26,SUMIF($C:$C,C36,$W:$W)>=$S$27),S36,IF(OR($AA$373>=$R$26,SUMIF($C:$C,C36,$W:$W)>=$R$27),R36,IF(OR($AA$373>=$Q$26,SUMIF($C:$C,C36,$W:$W)>=$Q$27),Q36,IF(OR($AA$373>=$P$26,SUMIF($C:$C,C36,$W:$W)>=$P$27),P36,IF(OR($AA$373>=$O$26,SUMIF($C:$C,C36,$W:$W)>=$O$27),O36,IF(OR($AA$373>=$N$26,SUMIF($C:$C,C36,$W:$W)>=$N$27),N36,IF($AA$373>=$M$26,M36,L36)))))))*$E$13),0) | BE36: =IF(V36="",0,(V36*W36)-(BD36*W36)) -> 0 | BM36: =BM32+24 -> #REF! | BW36: EAT CLEAN | BX36: =IFERROR(W36*U36,0) -> 0 | BY36: =VLOOKUP(B36,#REF!,13,0) -> #REF! | BZ36: 57 | CA36: =VLOOKUP(B36,Pedido!$B$16:$L$292,22,0) -> #N/A | CD36: =CD32+12 -> 60 | CE36: =CD36/12 -> 5 | CF36: =CONCATENATE(CD36,CE36) -> 605 | CG36: válido
B37: 0117898966827683 | C37: Barra de Proteína (display 12 unid) | D37: Display Barra de Proteína | E37: Chocolate Belga | F37: Barra | G37: 45g | H37: 24.13 | I37: 144.9 | J37: =IFERROR(IF(T37<>"",I37/T37,IF(AND(Y37="",V37=""),"",IF(V37="",I37/Y37,I37/V37))),"") | K37: =IF(Y37="","",IFERROR(1-(Y37/I37),0)) | L37: 84.9 | M37: =P37 -> 78.108 | N37: =P37 -> 78.108 | O37: =P37 -> 78.108 | P37: 78.108 | Q37: 78.108 | R37: 78.108 | S37: 78.108 | T37: =IF(V37>0,V37,IFERROR(IF(AND(W37<>"",X37<>""),AH37/W37,Y37),"")) | U37: =IFERROR((T37*W37)/(W37+X37),"") | Y37: =IF(AND(W37="",X37=""),"",$E$13*IF(V37<>"",V37,IF(SUMIF($C:$C,C37,$W:$W)>=$S$27,S37,IF(OR($AA$373>=$R$26,SUMIF($C:$C,C37,$W:$W)>=$R$27),R37,IF(OR($AA$373>=$Q$26,SUMIF($C:$C,C37,$W:$W)>=$Q$27),Q37,IF(OR($AA$373>=$P$26,SUMIF($C:$C,C37,$W:$W)>=$P$27),P37,IF(OR($AA$373>=$O$26,SUMIF($C:$C,C37,$W:$W)>=$O$27),O37,IF(OR($AA$373>=$N$26,SUMIF($C:$C,C37,$W:$W)>=$N$27),N37,IF($AA$373>=$M$26,M37,L37))))))))) | Z37: =IF(X37>W37,-1,IF(W37=0,0,IF(U37<(H37/0.75),-1,IF(W37<=3,0,0.0001)))) -> 0 | AA37: =IFERROR(L37*W37,0) -> 0 | AB37: =IFERROR(IF(OR($AA$373>=$S$26,SUMIF($C:$C,C37,$W:$W)>=$S$27),S37,IF(OR($AA$373>=$R$26,SUMIF($C:$C,C37,$W:$W)>=$R$27),R37,IF(OR($AA$373>=$Q$26,SUMIF($C:$C,C37,$W:$W)>=$Q$27),Q37,IF(OR($AA$373>=$P$26,SUMIF($C:$C,C37,$W:$W)>=$P$27),P37,IF(OR($AA$373>=$O$26,SUMIF($C:$C,C37,$W:$W)>=$O$27),O37,IF(OR($AA$373>=$N$26,SUMIF($C:$C,C37,$W:$W)>=$N$27),N37,IF($AA$373>=$M$26,M37,L37)))))))*W37,0) -> 0 | AC37: =IFERROR(IF(V37="",0,(IF(AND(W37="",X37=""),"",IF(OR($AA$373>=$S$26,SUMIF($C:$C,C37,$W:$W)>=$S$27),S37*$E$13,IF(OR($AA$373>=$R$26,SUMIF($C:$C,C37,$W:$W)>=$R$27),R37*$E$13,IF(OR($AA$373>=$Q$26,SUMIF($C:$C,C37,$W:$W)>=$Q$27),Q37*$E$13,IF(OR($AA$373>=$P$26,SUMIF($C:$C,C37,$W:$W)>=$P$27),P37*$E$13,IF(OR($AA$373>=$O$26,SUMIF($C:$C,C37,$W:$W)>=$O$27),O37*$E$13,IF(OR($AA$373>=$N$26,SUMIF($C:$C,C37,$W:$W)>=$N$27),N37*$E$13,IF($AA$373>=$M$26,M37*$E$13,L37))))))))-V37)*W37),0) -> 0 | AD37: =IFERROR(X37*T37,0) -> 0 | AE37: =IFERROR(W37*H37,0) -> 0 | AF37: =IFERROR(1-(AE37/AB37),0) -> 0 | AG37: =IFERROR(SUM(W37:X37)*I37,0) -> 0 | AH37: =IFERROR(IF(V37>0,V37*W37,(Y37*W37)),0) -> 0 | AI37: =IFERROR(SUM(W37)*H37,0) -> 0 | AJ37: =AH37*$AJ$25 -> 0 | AK37: =AH37*AK$25 -> 0 | AL37: =AH37*AL$25 -> 0 | AM37: =SUM(AJ37:AL37) -> 0 | AN37: =AH37-AM37 -> 0 | AO37: =AN37-AI37 -> 0 | AP37: =IFERROR(IF(V37<>"",1-(H37/V37),IF(Y37<>"",1-(H37/Y37),1-(H37/L37))),0) -> 0.71578327 | AQ37: =H37/0.75 -> 32.173333 | AR37: 12 | AS37: =(AP37-MIN($AP$65:$AP$368))/(MAX($AP$65:$AP$368)-MIN($AP$65:$AP$368))*100 -> 71.578327 | AT37: =IFERROR(1-(AI37/AH37),0) -> 0 | AU37: =IFERROR(AO37/AH37,0) -> 0 | AW37: =VLOOKUP(AX37,Sup!#REF!,8,0) -> #REF! | AX37: Premium | AY37: 0 | BC37: =IF(BE37<0,BE37,0) -> 0 | BD37: =IFERROR(IF(AND(W37="",X37=""),"",IF(OR($AA$373>=$S$26,SUMIF($C:$C,C37,$W:$W)>=$S$27),S37,IF(OR($AA$373>=$R$26,SUMIF($C:$C,C37,$W:$W)>=$R$27),R37,IF(OR($AA$373>=$Q$26,SUMIF($C:$C,C37,$W:$W)>=$Q$27),Q37,IF(OR($AA$373>=$P$26,SUMIF($C:$C,C37,$W:$W)>=$P$27),P37,IF(OR($AA$373>=$O$26,SUMIF($C:$C,C37,$W:$W)>=$O$27),O37,IF(OR($AA$373>=$N$26,SUMIF($C:$C,C37,$W:$W)>=$N$27),N37,IF($AA$373>=$M$26,M37,L37)))))))*$E$13),0) | BE37: =IF(V37="",0,(V37*W37)-(BD37*W37)) -> 0 | BM37: =BM36+24 -> #REF! | BW37: EAT CLEAN | BX37: =IFERROR(W37*U37,0) -> 0 | BY37: =VLOOKUP(B37,#REF!,13,0) -> #REF! | BZ37: 74 | CA37: =VLOOKUP(B37,Pedido!$B$16:$L$292,22,0) -> #N/A | CD37: =CD36+12 -> 72 | CE37: =CD37/12 -> 6 | CF37: =CONCATENATE(CD37,CE37) -> 726 | CG37: válido
B38: 17898966827782 | C38: Barra de Proteína (display 12 unid) | D38: Display Barra de Proteína | E38: Cookies & Cream | F38: Barra | G38: 45g | H38: 24.53 | I38: 144.9 | J38: =IFERROR(IF(T38<>"",I38/T38,IF(AND(Y38="",V38=""),"",IF(V38="",I38/Y38,I38/V38))),"") | K38: =IF(Y38="","",IFERROR(1-(Y38/I38),0)) | L38: 84.9 | M38: =P38 -> 78.108 | N38: =P38 -> 78.108 | O38: =P38 -> 78.108 | P38: 78.108 | Q38: 78.108 | R38: 78.108 | S38: 78.108 | T38: =IF(V38>0,V38,IFERROR(IF(AND(W38<>"",X38<>""),AH38/W38,Y38),"")) | U38: =IFERROR((T38*W38)/(W38+X38),"") | Y38: =IF(AND(W38="",X38=""),"",$E$13*IF(V38<>"",V38,IF(SUMIF($C:$C,C38,$W:$W)>=$S$27,S38,IF(OR($AA$373>=$R$26,SUMIF($C:$C,C38,$W:$W)>=$R$27),R38,IF(OR($AA$373>=$Q$26,SUMIF($C:$C,C38,$W:$W)>=$Q$27),Q38,IF(OR($AA$373>=$P$26,SUMIF($C:$C,C38,$W:$W)>=$P$27),P38,IF(OR($AA$373>=$O$26,SUMIF($C:$C,C38,$W:$W)>=$O$27),O38,IF(OR($AA$373>=$N$26,SUMIF($C:$C,C38,$W:$W)>=$N$27),N38,IF($AA$373>=$M$26,M38,L38))))))))) | Z38: =IF(X38>W38,-1,IF(W38=0,0,IF(U38<(H38/0.75),-1,IF(W38<=3,0,0.0001)))) -> 0 | AA38: =IFERROR(L38*W38,0) -> 0 | AB38: =IFERROR(IF(OR($AA$373>=$S$26,SUMIF($C:$C,C38,$W:$W)>=$S$27),S38,IF(OR($AA$373>=$R$26,SUMIF($C:$C,C38,$W:$W)>=$R$27),R38,IF(OR($AA$373>=$Q$26,SUMIF($C:$C,C38,$W:$W)>=$Q$27),Q38,IF(OR($AA$373>=$P$26,SUMIF($C:$C,C38,$W:$W)>=$P$27),P38,IF(OR($AA$373>=$O$26,SUMIF($C:$C,C38,$W:$W)>=$O$27),O38,IF(OR($AA$373>=$N$26,SUMIF($C:$C,C38,$W:$W)>=$N$27),N38,IF($AA$373>=$M$26,M38,L38)))))))*W38,0) -> 0 | AC38: =IFERROR(IF(V38="",0,(IF(AND(W38="",X38=""),"",IF(OR($AA$373>=$S$26,SUMIF($C:$C,C38,$W:$W)>=$S$27),S38*$E$13,IF(OR($AA$373>=$R$26,SUMIF($C:$C,C38,$W:$W)>=$R$27),R38*$E$13,IF(OR($AA$373>=$Q$26,SUMIF($C:$C,C38,$W:$W)>=$Q$27),Q38*$E$13,IF(OR($AA$373>=$P$26,SUMIF($C:$C,C38,$W:$W)>=$P$27),P38*$E$13,IF(OR($AA$373>=$O$26,SUMIF($C:$C,C38,$W:$W)>=$O$27),O38*$E$13,IF(OR($AA$373>=$N$26,SUMIF($C:$C,C38,$W:$W)>=$N$27),N38*$E$13,IF($AA$373>=$M$26,M38*$E$13,L38))))))))-V38)*W38),0) -> 0 | AD38: =IFERROR(X38*T38,0) -> 0 | AE38: =IFERROR(W38*H38,0) -> 0 | AF38: =IFERROR(1-(AE38/AB38),0) -> 0 | AG38: =IFERROR(SUM(W38:X38)*I38,0) -> 0 | AH38: =IFERROR(IF(V38>0,V38*W38,(Y38*W38)),0) -> 0 | AI38: =IFERROR(SUM(W38)*H38,0) -> 0 | AJ38: =AH38*$AJ$25 -> 0 | AK38: =AH38*AK$25 -> 0 | AL38: =AH38*AL$25 -> 0 | AM38: =SUM(AJ38:AL38) -> 0 | AN38: =AH38-AM38 -> 0 | AO38: =AN38-AI38 -> 0 | AP38: =IFERROR(IF(V38<>"",1-(H38/V38),IF(Y38<>"",1-(H38/Y38),1-(H38/L38))),0) -> 0.71107185 | AQ38: =H38/0.75 -> 32.706667 | AR38: 12 | AS38: =(AP38-MIN($AP$65:$AP$368))/(MAX($AP$65:$AP$368)-MIN($AP$65:$AP$368))*100 -> 71.107185 | AT38: =IFERROR(1-(AI38/AH38),0) -> 0 | AU38: =IFERROR(AO38/AH38,0) -> 0 | AW38: =VLOOKUP(AX38,Sup!#REF!,8,0) -> #REF! | AX38: Premium | AY38: 0 | BC38: =IF(BE38<0,BE38,0) -> 0 | BD38: =IFERROR(IF(AND(W38="",X38=""),"",IF(OR($AA$373>=$S$26,SUMIF($C:$C,C38,$W:$W)>=$S$27),S38,IF(OR($AA$373>=$R$26,SUMIF($C:$C,C38,$W:$W)>=$R$27),R38,IF(OR($AA$373>=$Q$26,SUMIF($C:$C,C38,$W:$W)>=$Q$27),Q38,IF(OR($AA$373>=$P$26,SUMIF($C:$C,C38,$W:$W)>=$P$27),P38,IF(OR($AA$373>=$O$26,SUMIF($C:$C,C38,$W:$W)>=$O$27),O38,IF(OR($AA$373>=$N$26,SUMIF($C:$C,C38,$W:$W)>=$N$27),N38,IF($AA$373>=$M$26,M38,L38)))))))*$E$13),0) | BE38: =IF(V38="",0,(V38*W38)-(BD38*W38)) -> 0 | BM38: =BM37+24 -> #REF! | BW38: EAT CLEAN | BX38: =IFERROR(W38*U38,0) -> 0 | BY38: =VLOOKUP(B38,#REF!,13,0) -> #REF! | BZ38: 74 | CA38: =VLOOKUP(B38,Pedido!$B$16:$L$292,22,0) -> #N/A | CD38: =CD37+12 -> 84 | CE38: =CD38/12 -> 7 | CF38: =CONCATENATE(CD38,CE38) -> 847 | CG38: válido
B39: 520349027 | C39: Barra de Proteína (display 12 unid) | D39: Display Barra de Proteína | E39: Doce de Leite | F39: Barra | G39: 45g | H39: 24.53 | I39: 144.9 | J39: =IFERROR(IF(T39<>"",I39/T39,IF(AND(Y39="",V39=""),"",IF(V39="",I39/Y39,I39/V39))),"") | K39: =IF(Y39="","",IFERROR(1-(Y39/I39),0)) | L39: 84.9 | M39: =P39 -> 78.108 | N39: =P39 -> 78.108 | O39: =P39 -> 78.108 | P39: 78.108 | Q39: 78.108 | R39: 78.108 | S39: 78.108 | T39: =IF(V39>0,V39,IFERROR(IF(AND(W39<>"",X39<>""),AH39/W39,Y39),"")) | U39: =IFERROR((T39*W39)/(W39+X39),"") | Y39: =IF(AND(W39="",X39=""),"",$E$13*IF(V39<>"",V39,IF(SUMIF($C:$C,C39,$W:$W)>=$S$27,S39,IF(OR($AA$373>=$R$26,SUMIF($C:$C,C39,$W:$W)>=$R$27),R39,IF(OR($AA$373>=$Q$26,SUMIF($C:$C,C39,$W:$W)>=$Q$27),Q39,IF(OR($AA$373>=$P$26,SUMIF($C:$C,C39,$W:$W)>=$P$27),P39,IF(OR($AA$373>=$O$26,SUMIF($C:$C,C39,$W:$W)>=$O$27),O39,IF(OR($AA$373>=$N$26,SUMIF($C:$C,C39,$W:$W)>=$N$27),N39,IF($AA$373>=$M$26,M39,L39))))))))) | Z39: =IF(X39>W39,-1,IF(W39=0,0,IF(U39<(H39/0.75),-1,IF(W39<=3,0,0.0001)))) -> 0 | AA39: =IFERROR(L39*W39,0) -> 0 | AB39: =IFERROR(IF(OR($AA$373>=$S$26,SUMIF($C:$C,C39,$W:$W)>=$S$27),S39,IF(OR($AA$373>=$R$26,SUMIF($C:$C,C39,$W:$W)>=$R$27),R39,IF(OR($AA$373>=$Q$26,SUMIF($C:$C,C39,$W:$W)>=$Q$27),Q39,IF(OR($AA$373>=$P$26,SUMIF($C:$C,C39,$W:$W)>=$P$27),P39,IF(OR($AA$373>=$O$26,SUMIF($C:$C,C39,$W:$W)>=$O$27),O39,IF(OR($AA$373>=$N$26,SUMIF($C:$C,C39,$W:$W)>=$N$27),N39,IF($AA$373>=$M$26,M39,L39)))))))*W39,0) -> 0 | AC39: =IFERROR(IF(V39="",0,(IF(AND(W39="",X39=""),"",IF(OR($AA$373>=$S$26,SUMIF($C:$C,C39,$W:$W)>=$S$27),S39*$E$13,IF(OR($AA$373>=$R$26,SUMIF($C:$C,C39,$W:$W)>=$R$27),R39*$E$13,IF(OR($AA$373>=$Q$26,SUMIF($C:$C,C39,$W:$W)>=$Q$27),Q39*$E$13,IF(OR($AA$373>=$P$26,SUMIF($C:$C,C39,$W:$W)>=$P$27),P39*$E$13,IF(OR($AA$373>=$O$26,SUMIF($C:$C,C39,$W:$W)>=$O$27),O39*$E$13,IF(OR($AA$373>=$N$26,SUMIF($C:$C,C39,$W:$W)>=$N$27),N39*$E$13,IF($AA$373>=$M$26,M39*$E$13,L39))))))))-V39)*W39),0) -> 0 | AD39: =IFERROR(X39*T39,0) -> 0 | AE39: =IFERROR(W39*H39,0) -> 0 | AF39: =IFERROR(1-(AE39/AB39),0) -> 0 | AG39: =IFERROR(SUM(W39:X39)*I39,0) -> 0 | AH39: =IFERROR(IF(V39>0,V39*W39,(Y39*W39)),0) -> 0 | AI39: =IFERROR(SUM(W39)*H39,0) -> 0 | AJ39: =AH39*$AJ$25 -> 0 | AK39: =AH39*AK$25 -> 0 | AL39: =AH39*AL$25 -> 0 | AM39: =SUM(AJ39:AL39) -> 0 | AN39: =AH39-AM39 -> 0 | AO39: =AN39-AI39 -> 0 | AP39: =IFERROR(IF(V39<>"",1-(H39/V39),IF(Y39<>"",1-(H39/Y39),1-(H39/L39))),0) -> 0.71107185 | AQ39: =H39/0.75 -> 32.706667 | AR39: 12 | AS39: =(AP39-MIN($AP$65:$AP$368))/(MAX($AP$65:$AP$368)-MIN($AP$65:$AP$368))*100 -> 71.107185 | AT39: =IFERROR(1-(AI39/AH39),0) -> 0 | AU39: =IFERROR(AO39/AH39,0) -> 0 | AW39: =VLOOKUP(AX39,Sup!#REF!,8,0) -> #REF! | AX39: Premium | AY39: 0 | BC39: =IF(BE39<0,BE39,0) -> 0 | BD39: =IFERROR(IF(AND(W39="",X39=""),"",IF(OR($AA$373>=$S$26,SUMIF($C:$C,C39,$W:$W)>=$S$27),S39,IF(OR($AA$373>=$R$26,SUMIF($C:$C,C39,$W:$W)>=$R$27),R39,IF(OR($AA$373>=$Q$26,SUMIF($C:$C,C39,$W:$W)>=$Q$27),Q39,IF(OR($AA$373>=$P$26,SUMIF($C:$C,C39,$W:$W)>=$P$27),P39,IF(OR($AA$373>=$O$26,SUMIF($C:$C,C39,$W:$W)>=$O$27),O39,IF(OR($AA$373>=$N$26,SUMIF($C:$C,C39,$W:$W)>=$N$27),N39,IF($AA$373>=$M$26,M39,L39)))))))*$E$13),0) | BE39: =IF(V39="",0,(V39*W39)-(BD39*W39)) -> 0 | BM39: =BM38+24 -> #REF! | BW39: EAT CLEAN | BX39: =IFERROR(W39*U39,0) -> 0 | BY39: =VLOOKUP(B39,#REF!,13,0) -> #REF! | BZ39: 74 | CA39: =VLOOKUP(B39,Pedido!$B$16:$L$292,22,0) -> #REF! | CD39: =CD38+12 -> 96 | CE39: =CD39/12 -> 8 | CF39: =CONCATENATE(CD39,CE39) -> 968 | CG39: válido
B40: 0117898966827669 | C40: Barra de Proteína (display 12 unid) | D40: Display Barra de Proteína | E40: Morango & Chocolate Branco | F40: Barra | G40: 45g | H40: 24.08 | I40: 144.9 | J40: =IFERROR(IF(T40<>"",I40/T40,IF(AND(Y40="",V40=""),"",IF(V40="",I40/Y40,I40/V40))),"") | K40: =IF(Y40="","",IFERROR(1-(Y40/I40),0)) | L40: 84.9 | M40: =P40 -> 78.108 | N40: =P40 -> 78.108 | O40: =P40 -> 78.108 | P40: 78.108 | Q40: 78.108 | R40: 78.108 | S40: 78.108 | T40: =IF(V40>0,V40,IFERROR(IF(AND(W40<>"",X40<>""),AH40/W40,Y40),"")) | U40: =IFERROR((T40*W40)/(W40+X40),"") | Y40: =IF(AND(W40="",X40=""),"",$E$13*IF(V40<>"",V40,IF(SUMIF($C:$C,C40,$W:$W)>=$S$27,S40,IF(OR($AA$373>=$R$26,SUMIF($C:$C,C40,$W:$W)>=$R$27),R40,IF(OR($AA$373>=$Q$26,SUMIF($C:$C,C40,$W:$W)>=$Q$27),Q40,IF(OR($AA$373>=$P$26,SUMIF($C:$C,C40,$W:$W)>=$P$27),P40,IF(OR($AA$373>=$O$26,SUMIF($C:$C,C40,$W:$W)>=$O$27),O40,IF(OR($AA$373>=$N$26,SUMIF($C:$C,C40,$W:$W)>=$N$27),N40,IF($AA$373>=$M$26,M40,L40))))))))) | Z40: =IF(X40>W40,-1,IF(W40=0,0,IF(U40<(H40/0.75),-1,IF(W40<=3,0,0.0001)))) -> 0 | AA40: =IFERROR(L40*W40,0) -> 0 | AB40: =IFERROR(IF(OR($AA$373>=$S$26,SUMIF($C:$C,C40,$W:$W)>=$S$27),S40,IF(OR($AA$373>=$R$26,SUMIF($C:$C,C40,$W:$W)>=$R$27),R40,IF(OR($AA$373>=$Q$26,SUMIF($C:$C,C40,$W:$W)>=$Q$27),Q40,IF(OR($AA$373>=$P$26,SUMIF($C:$C,C40,$W:$W)>=$P$27),P40,IF(OR($AA$373>=$O$26,SUMIF($C:$C,C40,$W:$W)>=$O$27),O40,IF(OR($AA$373>=$N$26,SUMIF($C:$C,C40,$W:$W)>=$N$27),N40,IF($AA$373>=$M$26,M40,L40)))))))*W40,0) -> 0 | AC40: =IFERROR(IF(V40="",0,(IF(AND(W40="",X40=""),"",IF(OR($AA$373>=$S$26,SUMIF($C:$C,C40,$W:$W)>=$S$27),S40*$E$13,IF(OR($AA$373>=$R$26,SUMIF($C:$C,C40,$W:$W)>=$R$27),R40*$E$13,IF(OR($AA$373>=$Q$26,SUMIF($C:$C,C40,$W:$W)>=$Q$27),Q40*$E$13,IF(OR($AA$373>=$P$26,SUMIF($C:$C,C40,$W:$W)>=$P$27),P40*$E$13,IF(OR($AA$373>=$O$26,SUMIF($C:$C,C40,$W:$W)>=$O$27),O40*$E$13,IF(OR($AA$373>=$N$26,SUMIF($C:$C,C40,$W:$W)>=$N$27),N40*$E$13,IF($AA$373>=$M$26,M40*$E$13,L40))))))))-V40)*W40),0) -> 0 | AD40: =IFERROR(X40*T40,0) -> 0 | AE40: =IFERROR(W40*H40,0) -> 0 | AF40: =IFERROR(1-(AE40/AB40),0) -> 0 | AG40: =IFERROR(SUM(W40:X40)*I40,0) -> 0 | AH40: =IFERROR(IF(V40>0,V40*W40,(Y40*W40)),0) -> 0 | AI40: =IFERROR(SUM(W40)*H40,0) -> 0 | AJ40: =AH40*$AJ$25 -> 0 | AK40: =AH40*AK$25 -> 0 | AL40: =AH40*AL$25 -> 0 | AM40: =SUM(AJ40:AL40) -> 0 | AN40: =AH40-AM40 -> 0 | AO40: =AN40-AI40 -> 0 | AP40: =IFERROR(IF(V40<>"",1-(H40/V40),IF(Y40<>"",1-(H40/Y40),1-(H40/L40))),0) -> 0.7163722 | AQ40: =H40/0.75 -> 32.106667 | AR40: 12 | AS40: =(AP40-MIN($AP$65:$AP$368))/(MAX($AP$65:$AP$368)-MIN($AP$65:$AP$368))*100 -> 71.63722 | AT40: =IFERROR(1-(AI40/AH40),0) -> 0 | AU40: =IFERROR(AO40/AH40,0) -> 0 | AW40: =VLOOKUP(AX40,Sup!#REF!,8,0) -> #REF! | AX40: Premium | AY40: 0 | BC40: =IF(BE40<0,BE40,0) -> 0 | BD40: =IFERROR(IF(AND(W40="",X40=""),"",IF(OR($AA$373>=$S$26,SUMIF($C:$C,C40,$W:$W)>=$S$27),S40,IF(OR($AA$373>=$R$26,SUMIF($C:$C,C40,$W:$W)>=$R$27),R40,IF(OR($AA$373>=$Q$26,SUMIF($C:$C,C40,$W:$W)>=$Q$27),Q40,IF(OR($AA$373>=$P$26,SUMIF($C:$C,C40,$W:$W)>=$P$27),P40,IF(OR($AA$373>=$O$26,SUMIF($C:$C,C40,$W:$W)>=$O$27),O40,IF(OR($AA$373>=$N$26,SUMIF($C:$C,C40,$W:$W)>=$N$27),N40,IF($AA$373>=$M$26,M40,L40)))))))*$E$13),0) | BE40: =IF(V40="",0,(V40*W40)-(BD40*W40)) -> 0 | BM40: =BM38+24 -> #REF! | BW40: EAT CLEAN | BX40: =IFERROR(W40*U40,0) -> 0 | BY40: =VLOOKUP(B40,#REF!,13,0) -> #REF! | BZ40: 74 | CA40: =VLOOKUP(B40,Pedido!$B$16:$L$292,22,0) -> #N/A | CD40: =CD38+12 -> 96 | CE40: =CD40/12 -> 8 | CF40: =CONCATENATE(CD40,CE40) -> 968 | CG40: válido
B41: 520349083 | C41: Barra de Proteína (display 12 unid) | D41: Display Barra de Proteína | E41: Pistache | F41: Barra | G41: 45g | H41: 24.08 | I41: 144.9 | J41: =IFERROR(IF(T41<>"",I41/T41,IF(AND(Y41="",V41=""),"",IF(V41="",I41/Y41,I41/V41))),"") | K41: =IF(Y41="","",IFERROR(1-(Y41/I41),0)) | L41: 84.9 | M41: =P41 -> 78.108 | N41: =P41 -> 78.108 | O41: =P41 -> 78.108 | P41: 78.108 | Q41: 78.108 | R41: 78.108 | S41: 78.108 | T41: =IF(V41>0,V41,IFERROR(IF(AND(W41<>"",X41<>""),AH41/W41,Y41),"")) | U41: =IFERROR((T41*W41)/(W41+X41),"") | Y41: =IF(AND(W41="",X41=""),"",$E$13*IF(V41<>"",V41,IF(SUMIF($C:$C,C41,$W:$W)>=$S$27,S41,IF(OR($AA$373>=$R$26,SUMIF($C:$C,C41,$W:$W)>=$R$27),R41,IF(OR($AA$373>=$Q$26,SUMIF($C:$C,C41,$W:$W)>=$Q$27),Q41,IF(OR($AA$373>=$P$26,SUMIF($C:$C,C41,$W:$W)>=$P$27),P41,IF(OR($AA$373>=$O$26,SUMIF($C:$C,C41,$W:$W)>=$O$27),O41,IF(OR($AA$373>=$N$26,SUMIF($C:$C,C41,$W:$W)>=$N$27),N41,IF($AA$373>=$M$26,M41,L41))))))))) | Z41: =IF(X41>W41,-1,IF(W41=0,0,IF(U41<(H41/0.75),-1,IF(W41<=3,0,0.0001)))) -> 0 | AA41: =IFERROR(L41*W41,0) -> 0 | AB41: =IFERROR(IF(OR($AA$373>=$S$26,SUMIF($C:$C,C41,$W:$W)>=$S$27),S41,IF(OR($AA$373>=$R$26,SUMIF($C:$C,C41,$W:$W)>=$R$27),R41,IF(OR($AA$373>=$Q$26,SUMIF($C:$C,C41,$W:$W)>=$Q$27),Q41,IF(OR($AA$373>=$P$26,SUMIF($C:$C,C41,$W:$W)>=$P$27),P41,IF(OR($AA$373>=$O$26,SUMIF($C:$C,C41,$W:$W)>=$O$27),O41,IF(OR($AA$373>=$N$26,SUMIF($C:$C,C41,$W:$W)>=$N$27),N41,IF($AA$373>=$M$26,M41,L41)))))))*W41,0) -> 0 | AC41: =IFERROR(IF(V41="",0,(IF(AND(W41="",X41=""),"",IF(OR($AA$373>=$S$26,SUMIF($C:$C,C41,$W:$W)>=$S$27),S41*$E$13,IF(OR($AA$373>=$R$26,SUMIF($C:$C,C41,$W:$W)>=$R$27),R41*$E$13,IF(OR($AA$373>=$Q$26,SUMIF($C:$C,C41,$W:$W)>=$Q$27),Q41*$E$13,IF(OR($AA$373>=$P$26,SUMIF($C:$C,C41,$W:$W)>=$P$27),P41*$E$13,IF(OR($AA$373>=$O$26,SUMIF($C:$C,C41,$W:$W)>=$O$27),O41*$E$13,IF(OR($AA$373>=$N$26,SUMIF($C:$C,C41,$W:$W)>=$N$27),N41*$E$13,IF($AA$373>=$M$26,M41*$E$13,L41))))))))-V41)*W41),0) -> 0 | AD41: =IFERROR(X41*T41,0) -> 0 | AE41: =IFERROR(W41*H41,0) -> 0 | AF41: =IFERROR(1-(AE41/AB41),0) -> 0 | AG41: =IFERROR(SUM(W41:X41)*I41,0) -> 0 | AH41: =IFERROR(IF(V41>0,V41*W41,(Y41*W41)),0) -> 0 | AI41: =IFERROR(SUM(W41)*H41,0) -> 0 | AJ41: =AH41*$AJ$25 -> 0 | AK41: =AH41*AK$25 -> 0 | AL41: =AH41*AL$25 -> 0 | AM41: =SUM(AJ41:AL41) -> 0 | AN41: =AH41-AM41 -> 0 | AO41: =AN41-AI41 -> 0 | AP41: =IFERROR(IF(V41<>"",1-(H41/V41),IF(Y41<>"",1-(H41/Y41),1-(H41/L41))),0) -> 0.7163722 | AQ41: =H41/0.75 -> 32.106667 | AR41: 12 | AS41: =(AP41-MIN($AP$65:$AP$368))/(MAX($AP$65:$AP$368)-MIN($AP$65:$AP$368))*100 -> 71.63722 | AT41: =IFERROR(1-(AI41/AH41),0) -> 0 | AU41: =IFERROR(AO41/AH41,0) -> 0 | AW41: =VLOOKUP(AX41,Sup!#REF!,8,0) -> #REF! | AX41: Premium | AY41: 0 | BC41: =IF(BE41<0,BE41,0) -> 0 | BD41: =IFERROR(IF(AND(W41="",X41=""),"",IF(OR($AA$373>=$S$26,SUMIF($C:$C,C41,$W:$W)>=$S$27),S41,IF(OR($AA$373>=$R$26,SUMIF($C:$C,C41,$W:$W)>=$R$27),R41,IF(OR($AA$373>=$Q$26,SUMIF($C:$C,C41,$W:$W)>=$Q$27),Q41,IF(OR($AA$373>=$P$26,SUMIF($C:$C,C41,$W:$W)>=$P$27),P41,IF(OR($AA$373>=$O$26,SUMIF($C:$C,C41,$W:$W)>=$O$27),O41,IF(OR($AA$373>=$N$26,SUMIF($C:$C,C41,$W:$W)>=$N$27),N41,IF($AA$373>=$M$26,M41,L41)))))))*$E$13),0) | BE41: =IF(V41="",0,(V41*W41)-(BD41*W41)) -> 0 | BM41: =BM39+24 -> #REF! | BW41: EAT CLEAN | BX41: =IFERROR(W41*U41,0) -> 0 | BY41: =VLOOKUP(B41,#REF!,13,0) -> #REF! | BZ41: 74 | CA41: =VLOOKUP(B41,Pedido!$B$16:$L$292,22,0) -> #REF! | CD41: =CD39+12 -> 108 | CE41: =CD41/12 -> 9 | CF41: =CONCATENATE(CD41,CE41) -> 1089 | CG41: válido
B42: 0117898966827676 | C42: Barra de Proteína (display 12 unid) | D42: Display Barra de Proteína | E42: Salted Caramel | F42: Barra | G42: 45g | H42: 22.9 | I42: 144.9 | J42: =IFERROR(IF(T42<>"",I42/T42,IF(AND(Y42="",V42=""),"",IF(V42="",I42/Y42,I42/V42))),"") | K42: =IF(Y42="","",IFERROR(1-(Y42/I42),0)) | L42: 84.9 | M42: =P42 -> 78.108 | N42: =P42 -> 78.108 | O42: =P42 -> 78.108 | P42: 78.108 | Q42: 78.108 | R42: 78.108 | S42: 78.108 | T42: =IF(V42>0,V42,IFERROR(IF(AND(W42<>"",X42<>""),AH42/W42,Y42),"")) | U42: =IFERROR((T42*W42)/(W42+X42),"") | Y42: =IF(AND(W42="",X42=""),"",$E$13*IF(V42<>"",V42,IF(SUMIF($C:$C,C42,$W:$W)>=$S$27,S42,IF(OR($AA$373>=$R$26,SUMIF($C:$C,C42,$W:$W)>=$R$27),R42,IF(OR($AA$373>=$Q$26,SUMIF($C:$C,C42,$W:$W)>=$Q$27),Q42,IF(OR($AA$373>=$P$26,SUMIF($C:$C,C42,$W:$W)>=$P$27),P42,IF(OR($AA$373>=$O$26,SUMIF($C:$C,C42,$W:$W)>=$O$27),O42,IF(OR($AA$373>=$N$26,SUMIF($C:$C,C42,$W:$W)>=$N$27),N42,IF($AA$373>=$M$26,M42,L42))))))))) | Z42: =IF(X42>W42,-1,IF(W42=0,0,IF(U42<(H42/0.75),-1,IF(W42<=3,0,0.0001)))) -> 0 | AA42: =IFERROR(L42*W42,0) -> 0 | AB42: =IFERROR(IF(OR($AA$373>=$S$26,SUMIF($C:$C,C42,$W:$W)>=$S$27),S42,IF(OR($AA$373>=$R$26,SUMIF($C:$C,C42,$W:$W)>=$R$27),R42,IF(OR($AA$373>=$Q$26,SUMIF($C:$C,C42,$W:$W)>=$Q$27),Q42,IF(OR($AA$373>=$P$26,SUMIF($C:$C,C42,$W:$W)>=$P$27),P42,IF(OR($AA$373>=$O$26,SUMIF($C:$C,C42,$W:$W)>=$O$27),O42,IF(OR($AA$373>=$N$26,SUMIF($C:$C,C42,$W:$W)>=$N$27),N42,IF($AA$373>=$M$26,M42,L42)))))))*W42,0) -> 0 | AC42: =IFERROR(IF(V42="",0,(IF(AND(W42="",X42=""),"",IF(OR($AA$373>=$S$26,SUMIF($C:$C,C42,$W:$W)>=$S$27),S42*$E$13,IF(OR($AA$373>=$R$26,SUMIF($C:$C,C42,$W:$W)>=$R$27),R42*$E$13,IF(OR($AA$373>=$Q$26,SUMIF($C:$C,C42,$W:$W)>=$Q$27),Q42*$E$13,IF(OR($AA$373>=$P$26,SUMIF($C:$C,C42,$W:$W)>=$P$27),P42*$E$13,IF(OR($AA$373>=$O$26,SUMIF($C:$C,C42,$W:$W)>=$O$27),O42*$E$13,IF(OR($AA$373>=$N$26,SUMIF($C:$C,C42,$W:$W)>=$N$27),N42*$E$13,IF($AA$373>=$M$26,M42*$E$13,L42))))))))-V42)*W42),0) -> 0 | AD42: =IFERROR(X42*T42,0) -> 0 | AE42: =IFERROR(W42*H42,0) -> 0 | AF42: =IFERROR(1-(AE42/AB42),0) -> 0 | AG42: =IFERROR(SUM(W42:X42)*I42,0) -> 0 | AH42: =IFERROR(IF(V42>0,V42*W42,(Y42*W42)),0) -> 0 | AI42: =IFERROR(SUM(W42)*H42,0) -> 0 | AJ42: =AH42*$AJ$25 -> 0 | AK42: =AH42*AK$25 -> 0 | AL42: =AH42*AL$25 -> 0 | AM42: =SUM(AJ42:AL42) -> 0 | AN42: =AH42-AM42 -> 0 | AO42: =AN42-AI42 -> 0 | AP42: =IFERROR(IF(V42<>"",1-(H42/V42),IF(Y42<>"",1-(H42/Y42),1-(H42/L42))),0) -> 0.73027091 | AQ42: =H42/0.75 -> 30.533333 | AR42: 12 | AS42: =(AP42-MIN($AP$65:$AP$368))/(MAX($AP$65:$AP$368)-MIN($AP$65:$AP$368))*100 -> 73.027091 | AT42: =IFERROR(1-(AI42/AH42),0) -> 0 | AU42: =IFERROR(AO42/AH42,0) -> 0 | AW42: =VLOOKUP(AX42,Sup!#REF!,8,0) -> #REF! | AX42: Premium | AY42: 0 | BC42: =IF(BE42<0,BE42,0) -> 0 | BD42: =IFERROR(IF(AND(W42="",X42=""),"",IF(OR($AA$373>=$S$26,SUMIF($C:$C,C42,$W:$W)>=$S$27),S42,IF(OR($AA$373>=$R$26,SUMIF($C:$C,C42,$W:$W)>=$R$27),R42,IF(OR($AA$373>=$Q$26,SUMIF($C:$C,C42,$W:$W)>=$Q$27),Q42,IF(OR($AA$373>=$P$26,SUMIF($C:$C,C42,$W:$W)>=$P$27),P42,IF(OR($AA$373>=$O$26,SUMIF($C:$C,C42,$W:$W)>=$O$27),O42,IF(OR($AA$373>=$N$26,SUMIF($C:$C,C42,$W:$W)>=$N$27),N42,IF($AA$373>=$M$26,M42,L42)))))))*$E$13),0) | BE42: =IF(V42="",0,(V42*W42)-(BD42*W42)) -> 0 | BM42: =BM40+24 -> #REF! | BW42: EAT CLEAN | BX42: =IFERROR(W42*U42,0) -> 0 | BY42: =VLOOKUP(B42,#REF!,13,0) -> #REF! | BZ42: 74 | CA42: =VLOOKUP(B42,Pedido!$B$16:$L$292,22,0) -> #N/A | CD42: =CD40+12 -> 108 | CE42: =CD42/12 -> 9 | CF42: =CONCATENATE(CD42,CE42) -> 1089 | CG42: válido
B43: 520255079 | C43: Pasta Monodoses | D43: Pasta Monodose Amendoim (10 unid.) | E43: Salted Caramel | F43: Pote | G43: 30g | H43: 47.28 | I43: 59 | J43: =IFERROR(IF(T43<>"",I43/T43,IF(AND(Y43="",V43=""),"",IF(V43="",I43/Y43,I43/V43))),"") | K43: =IF(Y43="","",IFERROR(1-(Y43/I43),0)) | L43: 42 | M43: 32 | N43: 32 | O43: 32 | P43: 32 | Q43: 32 | R43: 32 | S43: 32 | T43: =IF(V43>0,V43,IFERROR(IF(AND(W43<>"",X43<>""),AH43/W43,Y43),"")) | U43: =IFERROR((T43*W43)/(W43+X43),"") | Y43: =IF(AND(W43="",X43=""),"",$E$13*IF(V43<>"",V43,IF(SUMIF($C:$C,C43,$W:$W)>=$S$27,S43,IF(OR($AA$373>=$R$26,SUMIF($C:$C,C43,$W:$W)>=$R$27),R43,IF(OR($AA$373>=$Q$26,SUMIF($C:$C,C43,$W:$W)>=$Q$27),Q43,IF(OR($AA$373>=$P$26,SUMIF($C:$C,C43,$W:$W)>=$P$27),P43,IF(OR($AA$373>=$O$26,SUMIF($C:$C,C43,$W:$W)>=$O$27),O43,IF(OR($AA$373>=$N$26,SUMIF($C:$C,C43,$W:$W)>=$N$27),N43,IF($AA$373>=$M$26,M43,L43))))))))) | Z43: =IF(X43>W43,-1,IF(W43=0,0,IF(U43<(H43/0.75),-1,IF(W43<=3,0,0.0001)))) -> 0 | AA43: =IFERROR(L43*W43,0) -> 0 | AB43: =IFERROR(IF(OR($AA$373>=$S$26,SUMIF($C:$C,C43,$W:$W)>=$S$27),S43,IF(OR($AA$373>=$R$26,SUMIF($C:$C,C43,$W:$W)>=$R$27),R43,IF(OR($AA$373>=$Q$26,SUMIF($C:$C,C43,$W:$W)>=$Q$27),Q43,IF(OR($AA$373>=$P$26,SUMIF($C:$C,C43,$W:$W)>=$P$27),P43,IF(OR($AA$373>=$O$26,SUMIF($C:$C,C43,$W:$W)>=$O$27),O43,IF(OR($AA$373>=$N$26,SUMIF($C:$C,C43,$W:$W)>=$N$27),N43,IF($AA$373>=$M$26,M43,L43)))))))*W43,0) -> 0 | AC43: =IFERROR(IF(V43="",0,(IF(AND(W43="",X43=""),"",IF(OR($AA$373>=$S$26,SUMIF($C:$C,C43,$W:$W)>=$S$27),S43*$E$13,IF(OR($AA$373>=$R$26,SUMIF($C:$C,C43,$W:$W)>=$R$27),R43*$E$13,IF(OR($AA$373>=$Q$26,SUMIF($C:$C,C43,$W:$W)>=$Q$27),Q43*$E$13,IF(OR($AA$373>=$P$26,SUMIF($C:$C,C43,$W:$W)>=$P$27),P43*$E$13,IF(OR($AA$373>=$O$26,SUMIF($C:$C,C43,$W:$W)>=$O$27),O43*$E$13,IF(OR($AA$373>=$N$26,SUMIF($C:$C,C43,$W:$W)>=$N$27),N43*$E$13,IF($AA$373>=$M$26,M43*$E$13,L43))))))))-V43)*W43),0) -> 0 | AD43: =IFERROR(X43*T43,0) -> 0 | AE43: =IFERROR(W43*H43,0) -> 0 | AF43: =IFERROR(1-(AE43/AB43),0) -> 0 | AG43: =IFERROR(SUM(W43:X43)*I43,0) -> 0 | AH43: =IFERROR(IF(V43>0,V43*W43,(Y43*W43)),0) -> 0 | AI43: =IFERROR(SUM(W43)*H43,0) -> 0 | AJ43: =AH43*$AJ$25 -> 0 | AK43: =AH43*AK$25 -> 0 | AL43: =AH43*AL$25 -> 0 | AM43: =SUM(AJ43:AL43) -> 0 | AN43: =AH43-AM43 -> 0 | AO43: =AN43-AI43 -> 0 | AP43: =IFERROR(IF(V43<>"",1-(H43/V43),IF(Y43<>"",1-(H43/Y43),1-(H43/L43))),0) -> -0.12571429 | AQ43: =H43/0.75 -> 63.04 | AR43: 6 | AS43: =(AP43-MIN($AP$65:$AP$368))/(MAX($AP$65:$AP$368)-MIN($AP$65:$AP$368))*100 -> -12.571429 | AT43: =IFERROR(1-(AI43/AH43),0) -> 0 | AU43: =IFERROR(AO43/AH43,0) -> 0 | AW43: =VLOOKUP(AX43,Sup!#REF!,8,0) -> #REF! | AX43: Premium | AY43: 0 | BC43: =IF(BE43<0,BE43,0) -> 0 | BD43: =IFERROR(IF(AND(W43="",X43=""),"",IF(OR($AA$373>=$S$26,SUMIF($C:$C,C43,$W:$W)>=$S$27),S43,IF(OR($AA$373>=$R$26,SUMIF($C:$C,C43,$W:$W)>=$R$27),R43,IF(OR($AA$373>=$Q$26,SUMIF($C:$C,C43,$W:$W)>=$Q$27),Q43,IF(OR($AA$373>=$P$26,SUMIF($C:$C,C43,$W:$W)>=$P$27),P43,IF(OR($AA$373>=$O$26,SUMIF($C:$C,C43,$W:$W)>=$O$27),O43,IF(OR($AA$373>=$N$26,SUMIF($C:$C,C43,$W:$W)>=$N$27),N43,IF($AA$373>=$M$26,M43,L43)))))))*$E$13),0) | BE43: =IF(V43="",0,(V43*W43)-(BD43*W43)) -> 0 | BM43: =BM42+24 -> #REF! | BW43: EAT CLEAN | BX43: =IFERROR(W43*U43,0) -> 0 | BY43: =VLOOKUP(B43,#REF!,13,0) -> #REF! | BZ43: 99 | CA43: =VLOOKUP(B43,Pedido!$B$16:$L$292,22,0) -> #N/A | CD43: =CD42+12 -> 120 | CE43: =CD43/12 -> 10 | CF43: =CONCATENATE(CD43,CE43) -> 12010 | CG43: válido
B44: 520255080 | C44: Pasta Monodoses | D44: Pasta Monodose Amendoim (10 unid.) | E44: Chocolate Belga | F44: Pote | G44: 30g | H44: 47.28 | I44: 59 | J44: =IFERROR(IF(T44<>"",I44/T44,IF(AND(Y44="",V44=""),"",IF(V44="",I44/Y44,I44/V44))),"") | K44: =IF(Y44="","",IFERROR(1-(Y44/I44),0)) | L44: 42 | M44: 32 | N44: 32 | O44: 32 | P44: 32 | Q44: 32 | R44: 32 | S44: 32 | T44: =IF(V44>0,V44,IFERROR(IF(AND(W44<>"",X44<>""),AH44/W44,Y44),"")) | U44: =IFERROR((T44*W44)/(W44+X44),"") | Y44: =IF(AND(W44="",X44=""),"",$E$13*IF(V44<>"",V44,IF(SUMIF($C:$C,C44,$W:$W)>=$S$27,S44,IF(OR($AA$373>=$R$26,SUMIF($C:$C,C44,$W:$W)>=$R$27),R44,IF(OR($AA$373>=$Q$26,SUMIF($C:$C,C44,$W:$W)>=$Q$27),Q44,IF(OR($AA$373>=$P$26,SUMIF($C:$C,C44,$W:$W)>=$P$27),P44,IF(OR($AA$373>=$O$26,SUMIF($C:$C,C44,$W:$W)>=$O$27),O44,IF(OR($AA$373>=$N$26,SUMIF($C:$C,C44,$W:$W)>=$N$27),N44,IF($AA$373>=$M$26,M44,L44))))))))) | Z44: =IF(X44>W44,-1,IF(W44=0,0,IF(U44<(H44/0.75),-1,IF(W44<=3,0,0.0001)))) -> 0 | AA44: =IFERROR(L44*W44,0) -> 0 | AB44: =IFERROR(IF(OR($AA$373>=$S$26,SUMIF($C:$C,C44,$W:$W)>=$S$27),S44,IF(OR($AA$373>=$R$26,SUMIF($C:$C,C44,$W:$W)>=$R$27),R44,IF(OR($AA$373>=$Q$26,SUMIF($C:$C,C44,$W:$W)>=$Q$27),Q44,IF(OR($AA$373>=$P$26,SUMIF($C:$C,C44,$W:$W)>=$P$27),P44,IF(OR($AA$373>=$O$26,SUMIF($C:$C,C44,$W:$W)>=$O$27),O44,IF(OR($AA$373>=$N$26,SUMIF($C:$C,C44,$W:$W)>=$N$27),N44,IF($AA$373>=$M$26,M44,L44)))))))*W44,0) -> 0 | AC44: =IFERROR(IF(V44="",0,(IF(AND(W44="",X44=""),"",IF(OR($AA$373>=$S$26,SUMIF($C:$C,C44,$W:$W)>=$S$27),S44*$E$13,IF(OR($AA$373>=$R$26,SUMIF($C:$C,C44,$W:$W)>=$R$27),R44*$E$13,IF(OR($AA$373>=$Q$26,SUMIF($C:$C,C44,$W:$W)>=$Q$27),Q44*$E$13,IF(OR($AA$373>=$P$26,SUMIF($C:$C,C44,$W:$W)>=$P$27),P44*$E$13,IF(OR($AA$373>=$O$26,SUMIF($C:$C,C44,$W:$W)>=$O$27),O44*$E$13,IF(OR($AA$373>=$N$26,SUMIF($C:$C,C44,$W:$W)>=$N$27),N44*$E$13,IF($AA$373>=$M$26,M44*$E$13,L44))))))))-V44)*W44),0) -> 0 | AD44: =IFERROR(X44*T44,0) -> 0 | AE44: =IFERROR(W44*H44,0) -> 0 | AF44: =IFERROR(1-(AE44/AB44),0) -> 0 | AG44: =IFERROR(SUM(W44:X44)*I44,0) -> 0 | AH44: =IFERROR(IF(V44>0,V44*W44,(Y44*W44)),0) -> 0 | AI44: =IFERROR(SUM(W44)*H44,0) -> 0 | AJ44: =AH44*$AJ$25 -> 0 | AK44: =AH44*AK$25 -> 0 | AL44: =AH44*AL$25 -> 0 | AM44: =SUM(AJ44:AL44) -> 0 | AN44: =AH44-AM44 -> 0 | AO44: =AN44-AI44 -> 0 | AP44: =IFERROR(IF(V44<>"",1-(H44/V44),IF(Y44<>"",1-(H44/Y44),1-(H44/L44))),0) -> -0.12571429 | AQ44: =H44/0.75 -> 63.04 | AR44: 6 | AS44: =(AP44-MIN($AP$65:$AP$368))/(MAX($AP$65:$AP$368)-MIN($AP$65:$AP$368))*100 -> -12.571429 | AT44: =IFERROR(1-(AI44/AH44),0) -> 0 | AU44: =IFERROR(AO44/AH44,0) -> 0 | AW44: =VLOOKUP(AX44,Sup!#REF!,8,0) -> #REF! | AX44: Premium | AY44: 0 | BC44: =IF(BE44<0,BE44,0) -> 0 | BD44: =IFERROR(IF(AND(W44="",X44=""),"",IF(OR($AA$373>=$S$26,SUMIF($C:$C,C44,$W:$W)>=$S$27),S44,IF(OR($AA$373>=$R$26,SUMIF($C:$C,C44,$W:$W)>=$R$27),R44,IF(OR($AA$373>=$Q$26,SUMIF($C:$C,C44,$W:$W)>=$Q$27),Q44,IF(OR($AA$373>=$P$26,SUMIF($C:$C,C44,$W:$W)>=$P$27),P44,IF(OR($AA$373>=$O$26,SUMIF($C:$C,C44,$W:$W)>=$O$27),O44,IF(OR($AA$373>=$N$26,SUMIF($C:$C,C44,$W:$W)>=$N$27),N44,IF($AA$373>=$M$26,M44,L44)))))))*$E$13),0) | BE44: =IF(V44="",0,(V44*W44)-(BD44*W44)) -> 0 | BM44: =BM43+24 -> #REF! | BW44: EAT CLEAN | BX44: =IFERROR(W44*U44,0) -> 0 | BY44: =VLOOKUP(B44,#REF!,13,0) -> #REF! | BZ44: 99 | CA44: =VLOOKUP(B44,Pedido!$B$16:$L$292,22,0) -> #N/A | CD44: =CD43+12 -> 132 | CE44: =CD44/12 -> 11 | CF44: =CONCATENATE(CD44,CE44) -> 13211 | CG44: válido
B45: 520155027 | C45: Pasta Monodoses | D45: Pasta Monodose Castanha de Caju (10 unid.) | E45: Doce de Leite | F45: Pote | G45: 30g | H45: 47.28 | I45: 69 | J45: =IFERROR(IF(T45<>"",I45/T45,IF(AND(Y45="",V45=""),"",IF(V45="",I45/Y45,I45/V45))),"") | K45: =IF(Y45="","",IFERROR(1-(Y45/I45),0)) | L45: 50 | M45: 39 | N45: 39 | O45: 39 | P45: 39 | Q45: 39 | R45: 39 | S45: 39 | T45: =IF(V45>0,V45,IFERROR(IF(AND(W45<>"",X45<>""),AH45/W45,Y45),"")) | U45: =IFERROR((T45*W45)/(W45+X45),"") | Y45: =IF(AND(W45="",X45=""),"",$E$13*IF(V45<>"",V45,IF(SUMIF($C:$C,C45,$W:$W)>=$S$27,S45,IF(OR($AA$373>=$R$26,SUMIF($C:$C,C45,$W:$W)>=$R$27),R45,IF(OR($AA$373>=$Q$26,SUMIF($C:$C,C45,$W:$W)>=$Q$27),Q45,IF(OR($AA$373>=$P$26,SUMIF($C:$C,C45,$W:$W)>=$P$27),P45,IF(OR($AA$373>=$O$26,SUMIF($C:$C,C45,$W:$W)>=$O$27),O45,IF(OR($AA$373>=$N$26,SUMIF($C:$C,C45,$W:$W)>=$N$27),N45,IF($AA$373>=$M$26,M45,L45))))))))) | Z45: =IF(X45>W45,-1,IF(W45=0,0,IF(U45<(H45/0.75),-1,IF(W45<=3,0,0.0001)))) -> 0 | AA45: =IFERROR(L45*W45,0) -> 0 | AB45: =IFERROR(IF(OR($AA$373>=$S$26,SUMIF($C:$C,C45,$W:$W)>=$S$27),S45,IF(OR($AA$373>=$R$26,SUMIF($C:$C,C45,$W:$W)>=$R$27),R45,IF(OR($AA$373>=$Q$26,SUMIF($C:$C,C45,$W:$W)>=$Q$27),Q45,IF(OR($AA$373>=$P$26,SUMIF($C:$C,C45,$W:$W)>=$P$27),P45,IF(OR($AA$373>=$O$26,SUMIF($C:$C,C45,$W:$W)>=$O$27),O45,IF(OR($AA$373>=$N$26,SUMIF($C:$C,C45,$W:$W)>=$N$27),N45,IF($AA$373>=$M$26,M45,L45)))))))*W45,0) -> 0 | AC45: =IFERROR(IF(V45="",0,(IF(AND(W45="",X45=""),"",IF(OR($AA$373>=$S$26,SUMIF($C:$C,C45,$W:$W)>=$S$27),S45*$E$13,IF(OR($AA$373>=$R$26,SUMIF($C:$C,C45,$W:$W)>=$R$27),R45*$E$13,IF(OR($AA$373>=$Q$26,SUMIF($C:$C,C45,$W:$W)>=$Q$27),Q45*$E$13,IF(OR($AA$373>=$P$26,SUMIF($C:$C,C45,$W:$W)>=$P$27),P45*$E$13,IF(OR($AA$373>=$O$26,SUMIF($C:$C,C45,$W:$W)>=$O$27),O45*$E$13,IF(OR($AA$373>=$N$26,SUMIF($C:$C,C45,$W:$W)>=$N$27),N45*$E$13,IF($AA$373>=$M$26,M45*$E$13,L45))))))))-V45)*W45),0) -> 0 | AD45: =IFERROR(X45*T45,0) -> 0 | AE45: =IFERROR(W45*H45,0) -> 0 | AF45: =IFERROR(1-(AE45/AB45),0) -> 0 | AG45: =IFERROR(SUM(W45:X45)*I45,0) -> 0 | AH45: =IFERROR(IF(V45>0,V45*W45,(Y45*W45)),0) -> 0 | AI45: =IFERROR(SUM(W45)*H45,0) -> 0 | AJ45: =AH45*$AJ$25 -> 0 | AK45: =AH45*AK$25 -> 0 | AL45: =AH45*AL$25 -> 0 | AM45: =SUM(AJ45:AL45) -> 0 | AN45: =AH45-AM45 -> 0 | AO45: =AN45-AI45 -> 0 | AP45: =IFERROR(IF(V45<>"",1-(H45/V45),IF(Y45<>"",1-(H45/Y45),1-(H45/L45))),0) -> 0.0544 | AQ45: =H45/0.75 -> 63.04 | AR45: 6 | AS45: =(AP45-MIN($AP$65:$AP$368))/(MAX($AP$65:$AP$368)-MIN($AP$65:$AP$368))*100 -> 5.44 | AT45: =IFERROR(1-(AI45/AH45),0) -> 0 | AU45: =IFERROR(AO45/AH45,0) -> 0 | AW45: =VLOOKUP(AX45,Sup!#REF!,8,0) -> #REF! | AX45: Premium | AY45: 0 | BC45: =IF(BE45<0,BE45,0) -> 0 | BD45: =IFERROR(IF(AND(W45="",X45=""),"",IF(OR($AA$373>=$S$26,SUMIF($C:$C,C45,$W:$W)>=$S$27),S45,IF(OR($AA$373>=$R$26,SUMIF($C:$C,C45,$W:$W)>=$R$27),R45,IF(OR($AA$373>=$Q$26,SUMIF($C:$C,C45,$W:$W)>=$Q$27),Q45,IF(OR($AA$373>=$P$26,SUMIF($C:$C,C45,$W:$W)>=$P$27),P45,IF(OR($AA$373>=$O$26,SUMIF($C:$C,C45,$W:$W)>=$O$27),O45,IF(OR($AA$373>=$N$26,SUMIF($C:$C,C45,$W:$W)>=$N$27),N45,IF($AA$373>=$M$26,M45,L45)))))))*$E$13),0) | BE45: =IF(V45="",0,(V45*W45)-(BD45*W45)) -> 0 | BM45: =BM44+24 -> #REF! | BW45: EAT CLEAN | BX45: =IFERROR(W45*U45,0) -> 0 | BY45: =VLOOKUP(B45,#REF!,13,0) -> #REF! | BZ45: 99 | CA45: =VLOOKUP(B45,Pedido!$B$16:$L$292,22,0) -> #N/A | CD45: =CD44+12 -> 144 | CE45: =CD45/12 -> 12 | CF45: =CONCATENATE(CD45,CE45) -> 14412 | CG45: válido
B46: 520155023 | C46: Pasta Monodoses | D46: Pasta Monodose Castanha de Caju (10 unid.) | E46: Cookies | F46: Pote | G46: 30g | H46: 47.28 | I46: 69 | J46: =IFERROR(IF(T46<>"",I46/T46,IF(AND(Y46="",V46=""),"",IF(V46="",I46/Y46,I46/V46))),"") | K46: =IF(Y46="","",IFERROR(1-(Y46/I46),0)) | L46: 50 | M46: 39 | N46: 39 | O46: 39 | P46: 39 | Q46: 39 | R46: 39 | S46: 39 | T46: =IF(V46>0,V46,IFERROR(IF(AND(W46<>"",X46<>""),AH46/W46,Y46),"")) | U46: =IFERROR((T46*W46)/(W46+X46),"") | Y46: =IF(AND(W46="",X46=""),"",$E$13*IF(V46<>"",V46,IF(SUMIF($C:$C,C46,$W:$W)>=$S$27,S46,IF(OR($AA$373>=$R$26,SUMIF($C:$C,C46,$W:$W)>=$R$27),R46,IF(OR($AA$373>=$Q$26,SUMIF($C:$C,C46,$W:$W)>=$Q$27),Q46,IF(OR($AA$373>=$P$26,SUMIF($C:$C,C46,$W:$W)>=$P$27),P46,IF(OR($AA$373>=$O$26,SUMIF($C:$C,C46,$W:$W)>=$O$27),O46,IF(OR($AA$373>=$N$26,SUMIF($C:$C,C46,$W:$W)>=$N$27),N46,IF($AA$373>=$M$26,M46,L46))))))))) | Z46: =IF(X46>W46,-1,IF(W46=0,0,IF(U46<(H46/0.75),-1,IF(W46<=3,0,0.0001)))) -> 0 | AA46: =IFERROR(L46*W46,0) -> 0 | AB46: =IFERROR(IF(OR($AA$373>=$S$26,SUMIF($C:$C,C46,$W:$W)>=$S$27),S46,IF(OR($AA$373>=$R$26,SUMIF($C:$C,C46,$W:$W)>=$R$27),R46,IF(OR($AA$373>=$Q$26,SUMIF($C:$C,C46,$W:$W)>=$Q$27),Q46,IF(OR($AA$373>=$P$26,SUMIF($C:$C,C46,$W:$W)>=$P$27),P46,IF(OR($AA$373>=$O$26,SUMIF($C:$C,C46,$W:$W)>=$O$27),O46,IF(OR($AA$373>=$N$26,SUMIF($C:$C,C46,$W:$W)>=$N$27),N46,IF($AA$373>=$M$26,M46,L46)))))))*W46,0) -> 0 | AC46: =IFERROR(IF(V46="",0,(IF(AND(W46="",X46=""),"",IF(OR($AA$373>=$S$26,SUMIF($C:$C,C46,$W:$W)>=$S$27),S46*$E$13,IF(OR($AA$373>=$R$26,SUMIF($C:$C,C46,$W:$W)>=$R$27),R46*$E$13,IF(OR($AA$373>=$Q$26,SUMIF($C:$C,C46,$W:$W)>=$Q$27),Q46*$E$13,IF(OR($AA$373>=$P$26,SUMIF($C:$C,C46,$W:$W)>=$P$27),P46*$E$13,IF(OR($AA$373>=$O$26,SUMIF($C:$C,C46,$W:$W)>=$O$27),O46*$E$13,IF(OR($AA$373>=$N$26,SUMIF($C:$C,C46,$W:$W)>=$N$27),N46*$E$13,IF($AA$373>=$M$26,M46*$E$13,L46))))))))-V46)*W46),0) -> 0 | AD46: =IFERROR(X46*T46,0) -> 0 | AE46: =IFERROR(W46*H46,0) -> 0 | AF46: =IFERROR(1-(AE46/AB46),0) -> 0 | AG46: =IFERROR(SUM(W46:X46)*I46,0) -> 0 | AH46: =IFERROR(IF(V46>0,V46*W46,(Y46*W46)),0) -> 0 | AI46: =IFERROR(SUM(W46)*H46,0) -> 0 | AJ46: =AH46*$AJ$25 -> 0 | AK46: =AH46*AK$25 -> 0 | AL46: =AH46*AL$25 -> 0 | AM46: =SUM(AJ46:AL46) -> 0 | AN46: =AH46-AM46 -> 0 | AO46: =AN46-AI46 -> 0 | AP46: =IFERROR(IF(V46<>"",1-(H46/V46),IF(Y46<>"",1-(H46/Y46),1-(H46/L46))),0) -> 0.0544 | AQ46: =H46/0.75 -> 63.04 | AR46: 6 | AS46: =(AP46-MIN($AP$65:$AP$368))/(MAX($AP$65:$AP$368)-MIN($AP$65:$AP$368))*100 -> 5.44 | AT46: =IFERROR(1-(AI46/AH46),0) -> 0 | AU46: =IFERROR(AO46/AH46,0) -> 0 | AW46: =VLOOKUP(AX46,Sup!#REF!,8,0) -> #REF! | AX46: Premium | AY46: 0 | BC46: =IF(BE46<0,BE46,0) -> 0 | BD46: =IFERROR(IF(AND(W46="",X46=""),"",IF(OR($AA$373>=$S$26,SUMIF($C:$C,C46,$W:$W)>=$S$27),S46,IF(OR($AA$373>=$R$26,SUMIF($C:$C,C46,$W:$W)>=$R$27),R46,IF(OR($AA$373>=$Q$26,SUMIF($C:$C,C46,$W:$W)>=$Q$27),Q46,IF(OR($AA$373>=$P$26,SUMIF($C:$C,C46,$W:$W)>=$P$27),P46,IF(OR($AA$373>=$O$26,SUMIF($C:$C,C46,$W:$W)>=$O$27),O46,IF(OR($AA$373>=$N$26,SUMIF($C:$C,C46,$W:$W)>=$N$27),N46,IF($AA$373>=$M$26,M46,L46)))))))*$E$13),0) | BE46: =IF(V46="",0,(V46*W46)-(BD46*W46)) -> 0 | BM46: =BM45+24 -> #REF! | BW46: EAT CLEAN | BX46: =IFERROR(W46*U46,0) -> 0 | BY46: =VLOOKUP(B46,#REF!,13,0) -> #REF! | BZ46: 99 | CA46: =VLOOKUP(B46,Pedido!$B$16:$L$292,22,0) -> #N/A | CD46: =CD45+12 -> 156 | CE46: =CD46/12 -> 13 | CF46: =CONCATENATE(CD46,CE46) -> 15613 | CG46: válido
B47: 521355083 | C47: Pasta Monodoses | D47: Pasta Monodose de Pistache (10 unid.) | E47: Pistache | F47: Pote | G47: 30g | H47: 47.28 | I47: 99 | J47: =IFERROR(IF(T47<>"",I47/T47,IF(AND(Y47="",V47=""),"",IF(V47="",I47/Y47,I47/V47))),"") | K47: =IF(Y47="","",IFERROR(1-(Y47/I47),0)) | L47: 76 | M47: 59 | N47: 59 | O47: 59 | P47: 59 | Q47: 59 | R47: 59 | S47: 59 | T47: =IF(V47>0,V47,IFERROR(IF(AND(W47<>"",X47<>""),AH47/W47,Y47),"")) | U47: =IFERROR((T47*W47)/(W47+X47),"") | Y47: =IF(AND(W47="",X47=""),"",$E$13*IF(V47<>"",V47,IF(SUMIF($C:$C,C47,$W:$W)>=$S$27,S47,IF(OR($AA$373>=$R$26,SUMIF($C:$C,C47,$W:$W)>=$R$27),R47,IF(OR($AA$373>=$Q$26,SUMIF($C:$C,C47,$W:$W)>=$Q$27),Q47,IF(OR($AA$373>=$P$26,SUMIF($C:$C,C47,$W:$W)>=$P$27),P47,IF(OR($AA$373>=$O$26,SUMIF($C:$C,C47,$W:$W)>=$O$27),O47,IF(OR($AA$373>=$N$26,SUMIF($C:$C,C47,$W:$W)>=$N$27),N47,IF($AA$373>=$M$26,M47,L47))))))))) | Z47: =IF(X47>W47,-1,IF(W47=0,0,IF(U47<(H47/0.75),-1,IF(W47<=3,0,0.0001)))) -> 0 | AA47: =IFERROR(L47*W47,0) -> 0 | AB47: =IFERROR(IF(OR($AA$373>=$S$26,SUMIF($C:$C,C47,$W:$W)>=$S$27),S47,IF(OR($AA$373>=$R$26,SUMIF($C:$C,C47,$W:$W)>=$R$27),R47,IF(OR($AA$373>=$Q$26,SUMIF($C:$C,C47,$W:$W)>=$Q$27),Q47,IF(OR($AA$373>=$P$26,SUMIF($C:$C,C47,$W:$W)>=$P$27),P47,IF(OR($AA$373>=$O$26,SUMIF($C:$C,C47,$W:$W)>=$O$27),O47,IF(OR($AA$373>=$N$26,SUMIF($C:$C,C47,$W:$W)>=$N$27),N47,IF($AA$373>=$M$26,M47,L47)))))))*W47,0) -> 0 | AC47: =IFERROR(IF(V47="",0,(IF(AND(W47="",X47=""),"",IF(OR($AA$373>=$S$26,SUMIF($C:$C,C47,$W:$W)>=$S$27),S47*$E$13,IF(OR($AA$373>=$R$26,SUMIF($C:$C,C47,$W:$W)>=$R$27),R47*$E$13,IF(OR($AA$373>=$Q$26,SUMIF($C:$C,C47,$W:$W)>=$Q$27),Q47*$E$13,IF(OR($AA$373>=$P$26,SUMIF($C:$C,C47,$W:$W)>=$P$27),P47*$E$13,IF(OR($AA$373>=$O$26,SUMIF($C:$C,C47,$W:$W)>=$O$27),O47*$E$13,IF(OR($AA$373>=$N$26,SUMIF($C:$C,C47,$W:$W)>=$N$27),N47*$E$13,IF($AA$373>=$M$26,M47*$E$13,L47))))))))-V47)*W47),0) -> 0 | AD47: =IFERROR(X47*T47,0) -> 0 | AE47: =IFERROR(W47*H47,0) -> 0 | AF47: =IFERROR(1-(AE47/AB47),0) -> 0 | AG47: =IFERROR(SUM(W47:X47)*I47,0) -> 0 | AH47: =IFERROR(IF(V47>0,V47*W47,(Y47*W47)),0) -> 0 | AI47: =IFERROR(SUM(W47)*H47,0) -> 0 | AJ47: =AH47*$AJ$25 -> 0 | AK47: =AH47*AK$25 -> 0 | AL47: =AH47*AL$25 -> 0 | AM47: =SUM(AJ47:AL47) -> 0 | AN47: =AH47-AM47 -> 0 | AO47: =AN47-AI47 -> 0 | AP47: =IFERROR(IF(V47<>"",1-(H47/V47),IF(Y47<>"",1-(H47/Y47),1-(H47/L47))),0) -> 0.37789474 | AQ47: =H47/0.75 -> 63.04 | AR47: 6 | AS47: =(AP47-MIN($AP$65:$AP$368))/(MAX($AP$65:$AP$368)-MIN($AP$65:$AP$368))*100 -> 37.789474 | AT47: =IFERROR(1-(AI47/AH47),0) -> 0 | AU47: =IFERROR(AO47/AH47,0) -> 0 | AW47: =VLOOKUP(AX47,Sup!#REF!,8,0) -> #REF! | AX47: Premium | AY47: 0 | BC47: =IF(BE47<0,BE47,0) -> 0 | BD47: =IFERROR(IF(AND(W47="",X47=""),"",IF(OR($AA$373>=$S$26,SUMIF($C:$C,C47,$W:$W)>=$S$27),S47,IF(OR($AA$373>=$R$26,SUMIF($C:$C,C47,$W:$W)>=$R$27),R47,IF(OR($AA$373>=$Q$26,SUMIF($C:$C,C47,$W:$W)>=$Q$27),Q47,IF(OR($AA$373>=$P$26,SUMIF($C:$C,C47,$W:$W)>=$P$27),P47,IF(OR($AA$373>=$O$26,SUMIF($C:$C,C47,$W:$W)>=$O$27),O47,IF(OR($AA$373>=$N$26,SUMIF($C:$C,C47,$W:$W)>=$N$27),N47,IF($AA$373>=$M$26,M47,L47)))))))*$E$13),0) | BE47: =IF(V47="",0,(V47*W47)-(BD47*W47)) -> 0 | BM47: =BM46+24 -> #REF! | BW47: EAT CLEAN | BX47: =IFERROR(W47*U47,0) -> 0 | BY47: =VLOOKUP(B47,#REF!,13,0) -> #REF! | BZ47: 99 | CA47: =VLOOKUP(B47,Pedido!$B$16:$L$292,22,0) -> #N/A | CD47: =CD46+12 -> 168 | CE47: =CD47/12 -> 14 | CF47: =CONCATENATE(CD47,CE47) -> 16814 | CG47: válido
B48: 9962476207 | C48: Pasta Amendoim | D48: Pasta Amendoim | E48: Chocolate Belga | F48: Pote | G48: 300g | H48: 34.85 | I48: 179.4 | J48: =IFERROR(IF(T48<>"",I48/T48,IF(AND(Y48="",V48=""),"",IF(V48="",I48/Y48,I48/V48))),"") | K48: =IF(Y48="","",IFERROR(1-(Y48/I48),0)) | L48: 118.8 | M48: =P48 -> 92.9 | N48: =P48 -> 92.9 | O48: =P48 -> 92.9 | P48: 92.9 | Q48: 92.9 | R48: 92.9 | S48: 92.9 | T48: =IF(V48>0,V48,IFERROR(IF(AND(W48<>"",X48<>""),AH48/W48,Y48),"")) | U48: =IFERROR((T48*W48)/(W48+X48),"") | Y48: =IF(AND(W48="",X48=""),"",$E$13*IF(V48<>"",V48,IF(SUMIF($C:$C,C48,$W:$W)>=$S$27,S48,IF(OR($AA$373>=$R$26,SUMIF($C:$C,C48,$W:$W)>=$R$27),R48,IF(OR($AA$373>=$Q$26,SUMIF($C:$C,C48,$W:$W)>=$Q$27),Q48,IF(OR($AA$373>=$P$26,SUMIF($C:$C,C48,$W:$W)>=$P$27),P48,IF(OR($AA$373>=$O$26,SUMIF($C:$C,C48,$W:$W)>=$O$27),O48,IF(OR($AA$373>=$N$26,SUMIF($C:$C,C48,$W:$W)>=$N$27),N48,IF($AA$373>=$M$26,M48,L48))))))))) | Z48: =IF(X48>W48,-1,IF(W48=0,0,IF(U48<(H48/0.75),-1,IF(W48<=3,0,0.0001)))) -> 0 | AA48: =IFERROR(L48*W48,0) -> 0 | AB48: =IFERROR(IF(OR($AA$373>=$S$26,SUMIF($C:$C,C48,$W:$W)>=$S$27),S48,IF(OR($AA$373>=$R$26,SUMIF($C:$C,C48,$W:$W)>=$R$27),R48,IF(OR($AA$373>=$Q$26,SUMIF($C:$C,C48,$W:$W)>=$Q$27),Q48,IF(OR($AA$373>=$P$26,SUMIF($C:$C,C48,$W:$W)>=$P$27),P48,IF(OR($AA$373>=$O$26,SUMIF($C:$C,C48,$W:$W)>=$O$27),O48,IF(OR($AA$373>=$N$26,SUMIF($C:$C,C48,$W:$W)>=$N$27),N48,IF($AA$373>=$M$26,M48,L48)))))))*W48,0) -> 0 | AC48: =IFERROR(IF(V48="",0,(IF(AND(W48="",X48=""),"",IF(OR($AA$373>=$S$26,SUMIF($C:$C,C48,$W:$W)>=$S$27),S48*$E$13,IF(OR($AA$373>=$R$26,SUMIF($C:$C,C48,$W:$W)>=$R$27),R48*$E$13,IF(OR($AA$373>=$Q$26,SUMIF($C:$C,C48,$W:$W)>=$Q$27),Q48*$E$13,IF(OR($AA$373>=$P$26,SUMIF($C:$C,C48,$W:$W)>=$P$27),P48*$E$13,IF(OR($AA$373>=$O$26,SUMIF($C:$C,C48,$W:$W)>=$O$27),O48*$E$13,IF(OR($AA$373>=$N$26,SUMIF($C:$C,C48,$W:$W)>=$N$27),N48*$E$13,IF($AA$373>=$M$26,M48*$E$13,L48))))))))-V48)*W48),0) -> 0 | AD48: =IFERROR(X48*T48,0) -> 0 | AE48: =IFERROR(W48*H48,0) -> 0 | AF48: =IFERROR(1-(AE48/AB48),0) -> 0 | AG48: =IFERROR(SUM(W48:X48)*I48,0) -> 0 | AH48: =IFERROR(IF(V48>0,V48*W48,(Y48*W48)),0) -> 0 | AI48: =IFERROR(SUM(W48)*H48,0) -> 0 | AJ48: =AH48*$AJ$25 -> 0 | AK48: =AH48*AK$25 -> 0 | AL48: =AH48*AL$25 -> 0 | AM48: =SUM(AJ48:AL48) -> 0 | AN48: =AH48-AM48 -> 0 | AO48: =AN48-AI48 -> 0 | AP48: =IFERROR(IF(V48<>"",1-(H48/V48),IF(Y48<>"",1-(H48/Y48),1-(H48/L48))),0) -> 0.70664983 | AQ48: =H48/0.75 -> 46.466667 | AR48: 6 | AS48: =(AP48-MIN($AP$65:$AP$368))/(MAX($AP$65:$AP$368)-MIN($AP$65:$AP$368))*100 -> 70.664983 | AT48: =IFERROR(1-(AI48/AH48),0) -> 0 | AU48: =IFERROR(AO48/AH48,0) -> 0 | AW48: =VLOOKUP(AX48,Sup!#REF!,8,0) -> #REF! | AX48: Premium | AY48: 0 | BC48: =IF(BE48<0,BE48,0) -> 0 | BD48: =IFERROR(IF(AND(W48="",X48=""),"",IF(OR($AA$373>=$S$26,SUMIF($C:$C,C48,$W:$W)>=$S$27),S48,IF(OR($AA$373>=$R$26,SUMIF($C:$C,C48,$W:$W)>=$R$27),R48,IF(OR($AA$373>=$Q$26,SUMIF($C:$C,C48,$W:$W)>=$Q$27),Q48,IF(OR($AA$373>=$P$26,SUMIF($C:$C,C48,$W:$W)>=$P$27),P48,IF(OR($AA$373>=$O$26,SUMIF($C:$C,C48,$W:$W)>=$O$27),O48,IF(OR($AA$373>=$N$26,SUMIF($C:$C,C48,$W:$W)>=$N$27),N48,IF($AA$373>=$M$26,M48,L48)))))))*$E$13),0) | BE48: =IF(V48="",0,(V48*W48)-(BD48*W48)) -> 0 | BM48: =BM42+24 -> #REF! | BW48: EAT CLEAN | BX48: =IFERROR(W48*U48,0) -> 0 | BY48: =VLOOKUP(B48,#REF!,13,0) -> #REF! | BZ48: 99 | CA48: =VLOOKUP(B48,Pedido!$B$16:$L$292,22,0) -> #N/A | CD48: =CD42+12 -> 120 | CE48: =CD48/12 -> 10 | CF48: =CONCATENATE(CD48,CE48) -> 12010 | CG48: válido
B49: 15838521205 | C49: Pasta Amendoim | D49: Pasta Amendoim | E49: Cookies 'N' Cream | F49: Pote | G49: 300g | H49: 47.28 | I49: 179.4 | J49: =IFERROR(IF(T49<>"",I49/T49,IF(AND(Y49="",V49=""),"",IF(V49="",I49/Y49,I49/V49))),"") | K49: =IF(Y49="","",IFERROR(1-(Y49/I49),0)) | L49: 118.8 | M49: =P49 -> 92.9 | N49: =P49 -> 92.9 | O49: =P49 -> 92.9 | P49: 92.9 | Q49: 92.9 | R49: 92.9 | S49: 92.9 | T49: =IF(V49>0,V49,IFERROR(IF(AND(W49<>"",X49<>""),AH49/W49,Y49),"")) | U49: =IFERROR((T49*W49)/(W49+X49),"") | Y49: =IF(AND(W49="",X49=""),"",$E$13*IF(V49<>"",V49,IF(SUMIF($C:$C,C49,$W:$W)>=$S$27,S49,IF(OR($AA$373>=$R$26,SUMIF($C:$C,C49,$W:$W)>=$R$27),R49,IF(OR($AA$373>=$Q$26,SUMIF($C:$C,C49,$W:$W)>=$Q$27),Q49,IF(OR($AA$373>=$P$26,SUMIF($C:$C,C49,$W:$W)>=$P$27),P49,IF(OR($AA$373>=$O$26,SUMIF($C:$C,C49,$W:$W)>=$O$27),O49,IF(OR($AA$373>=$N$26,SUMIF($C:$C,C49,$W:$W)>=$N$27),N49,IF($AA$373>=$M$26,M49,L49))))))))) | Z49: =IF(X49>W49,-1,IF(W49=0,0,IF(U49<(H49/0.75),-1,IF(W49<=3,0,0.0001)))) -> 0 | AA49: =IFERROR(L49*W49,0) -> 0 | AB49: =IFERROR(IF(OR($AA$373>=$S$26,SUMIF($C:$C,C49,$W:$W)>=$S$27),S49,IF(OR($AA$373>=$R$26,SUMIF($C:$C,C49,$W:$W)>=$R$27),R49,IF(OR($AA$373>=$Q$26,SUMIF($C:$C,C49,$W:$W)>=$Q$27),Q49,IF(OR($AA$373>=$P$26,SUMIF($C:$C,C49,$W:$W)>=$P$27),P49,IF(OR($AA$373>=$O$26,SUMIF($C:$C,C49,$W:$W)>=$O$27),O49,IF(OR($AA$373>=$N$26,SUMIF($C:$C,C49,$W:$W)>=$N$27),N49,IF($AA$373>=$M$26,M49,L49)))))))*W49,0) -> 0 | AC49: =IFERROR(IF(V49="",0,(IF(AND(W49="",X49=""),"",IF(OR($AA$373>=$S$26,SUMIF($C:$C,C49,$W:$W)>=$S$27),S49*$E$13,IF(OR($AA$373>=$R$26,SUMIF($C:$C,C49,$W:$W)>=$R$27),R49*$E$13,IF(OR($AA$373>=$Q$26,SUMIF($C:$C,C49,$W:$W)>=$Q$27),Q49*$E$13,IF(OR($AA$373>=$P$26,SUMIF($C:$C,C49,$W:$W)>=$P$27),P49*$E$13,IF(OR($AA$373>=$O$26,SUMIF($C:$C,C49,$W:$W)>=$O$27),O49*$E$13,IF(OR($AA$373>=$N$26,SUMIF($C:$C,C49,$W:$W)>=$N$27),N49*$E$13,IF($AA$373>=$M$26,M49*$E$13,L49))))))))-V49)*W49),0) -> 0 | AD49: =IFERROR(X49*T49,0) -> 0 | AE49: =IFERROR(W49*H49,0) -> 0 | AF49: =IFERROR(1-(AE49/AB49),0) -> 0 | AG49: =IFERROR(SUM(W49:X49)*I49,0) -> 0 | AH49: =IFERROR(IF(V49>0,V49*W49,(Y49*W49)),0) -> 0 | AI49: =IFERROR(SUM(W49)*H49,0) -> 0 | AJ49: =AH49*$AJ$25 -> 0 | AK49: =AH49*AK$25 -> 0 | AL49: =AH49*AL$25 -> 0 | AM49: =SUM(AJ49:AL49) -> 0 | AN49: =AH49-AM49 -> 0 | AO49: =AN49-AI49 -> 0 | AP49: =IFERROR(IF(V49<>"",1-(H49/V49),IF(Y49<>"",1-(H49/Y49),1-(H49/L49))),0) -> 0.6020202 | AQ49: =H49/0.75 -> 63.04 | AR49: 6 | AS49: =(AP49-MIN($AP$65:$AP$368))/(MAX($AP$65:$AP$368)-MIN($AP$65:$AP$368))*100 -> 60.20202 | AT49: =IFERROR(1-(AI49/AH49),0) -> 0 | AU49: =IFERROR(AO49/AH49,0) -> 0 | AW49: =VLOOKUP(AX49,Sup!#REF!,8,0) -> #REF! | AX49: Premium | AY49: 0 | BC49: =IF(BE49<0,BE49,0) -> 0 | BD49: =IFERROR(IF(AND(W49="",X49=""),"",IF(OR($AA$373>=$S$26,SUMIF($C:$C,C49,$W:$W)>=$S$27),S49,IF(OR($AA$373>=$R$26,SUMIF($C:$C,C49,$W:$W)>=$R$27),R49,IF(OR($AA$373>=$Q$26,SUMIF($C:$C,C49,$W:$W)>=$Q$27),Q49,IF(OR($AA$373>=$P$26,SUMIF($C:$C,C49,$W:$W)>=$P$27),P49,IF(OR($AA$373>=$O$26,SUMIF($C:$C,C49,$W:$W)>=$O$27),O49,IF(OR($AA$373>=$N$26,SUMIF($C:$C,C49,$W:$W)>=$N$27),N49,IF($AA$373>=$M$26,M49,L49)))))))*$E$13),0) | BE49: =IF(V49="",0,(V49*W49)-(BD49*W49)) -> 0 | BM49: =BM48+24 -> #REF! | BW49: EAT CLEAN | BX49: =IFERROR(W49*U49,0) -> 0 | BY49: =VLOOKUP(B49,#REF!,13,0) -> #REF! | BZ49: 99 | CA49: =VLOOKUP(B49,Pedido!$B$16:$L$292,22,0) -> #N/A | CD49: =CD48+12 -> 132 | CE49: =CD49/12 -> 11 | CF49: =CONCATENATE(CD49,CE49) -> 13211 | CG49: válido
B50: 14653323373 | C50: Pasta Amendoim | D50: Pasta Amendoim | E50: Integral | F50: Pote | G50: 300g | H50: 49.29 | I50: 149.4 | J50: =IFERROR(IF(T50<>"",I50/T50,IF(AND(Y50="",V50=""),"",IF(V50="",I50/Y50,I50/V50))),"") | K50: =IF(Y50="","",IFERROR(1-(Y50/I50),0)) | L50: 93.6 | M50: =P50 -> 74.9 | N50: =P50 -> 74.9 | O50: =P50 -> 74.9 | P50: 74.9 | Q50: 74.9 | R50: 74.9 | S50: 74.9 | T50: =IF(V50>0,V50,IFERROR(IF(AND(W50<>"",X50<>""),AH50/W50,Y50),"")) | U50: =IFERROR((T50*W50)/(W50+X50),"") | Y50: =IF(AND(W50="",X50=""),"",$E$13*IF(V50<>"",V50,IF(SUMIF($C:$C,C50,$W:$W)>=$S$27,S50,IF(OR($AA$373>=$R$26,SUMIF($C:$C,C50,$W:$W)>=$R$27),R50,IF(OR($AA$373>=$Q$26,SUMIF($C:$C,C50,$W:$W)>=$Q$27),Q50,IF(OR($AA$373>=$P$26,SUMIF($C:$C,C50,$W:$W)>=$P$27),P50,IF(OR($AA$373>=$O$26,SUMIF($C:$C,C50,$W:$W)>=$O$27),O50,IF(OR($AA$373>=$N$26,SUMIF($C:$C,C50,$W:$W)>=$N$27),N50,IF($AA$373>=$M$26,M50,L50))))))))) | Z50: =IF(X50>W50,-1,IF(W50=0,0,IF(U50<(H50/0.75),-1,IF(W50<=3,0,0.0001)))) -> 0 | AA50: =IFERROR(L50*W50,0) -> 0 | AB50: =IFERROR(IF(OR($AA$373>=$S$26,SUMIF($C:$C,C50,$W:$W)>=$S$27),S50,IF(OR($AA$373>=$R$26,SUMIF($C:$C,C50,$W:$W)>=$R$27),R50,IF(OR($AA$373>=$Q$26,SUMIF($C:$C,C50,$W:$W)>=$Q$27),Q50,IF(OR($AA$373>=$P$26,SUMIF($C:$C,C50,$W:$W)>=$P$27),P50,IF(OR($AA$373>=$O$26,SUMIF($C:$C,C50,$W:$W)>=$O$27),O50,IF(OR($AA$373>=$N$26,SUMIF($C:$C,C50,$W:$W)>=$N$27),N50,IF($AA$373>=$M$26,M50,L50)))))))*W50,0) -> 0 | AC50: =IFERROR(IF(V50="",0,(IF(AND(W50="",X50=""),"",IF(OR($AA$373>=$S$26,SUMIF($C:$C,C50,$W:$W)>=$S$27),S50*$E$13,IF(OR($AA$373>=$R$26,SUMIF($C:$C,C50,$W:$W)>=$R$27),R50*$E$13,IF(OR($AA$373>=$Q$26,SUMIF($C:$C,C50,$W:$W)>=$Q$27),Q50*$E$13,IF(OR($AA$373>=$P$26,SUMIF($C:$C,C50,$W:$W)>=$P$27),P50*$E$13,IF(OR($AA$373>=$O$26,SUMIF($C:$C,C50,$W:$W)>=$O$27),O50*$E$13,IF(OR($AA$373>=$N$26,SUMIF($C:$C,C50,$W:$W)>=$N$27),N50*$E$13,IF($AA$373>=$M$26,M50*$E$13,L50))))))))-V50)*W50),0) -> 0 | AD50: =IFERROR(X50*T50,0) -> 0 | AE50: =IFERROR(W50*H50,0) -> 0 | AF50: =IFERROR(1-(AE50/AB50),0) -> 0 | AG50: =IFERROR(SUM(W50:X50)*I50,0) -> 0 | AH50: =IFERROR(IF(V50>0,V50*W50,(Y50*W50)),0) -> 0 | AI50: =IFERROR(SUM(W50)*H50,0) -> 0 | AJ50: =AH50*$AJ$25 -> 0 | AK50: =AH50*AK$25 -> 0 | AL50: =AH50*AL$25 -> 0 | AM50: =SUM(AJ50:AL50) -> 0 | AN50: =AH50-AM50 -> 0 | AO50: =AN50-AI50 -> 0 | AP50: =IFERROR(IF(V50<>"",1-(H50/V50),IF(Y50<>"",1-(H50/Y50),1-(H50/L50))),0) -> 0.47339744 | AQ50: =H50/0.75 -> 65.72 | AR50: 6 | AS50: =(AP50-MIN($AP$65:$AP$368))/(MAX($AP$65:$AP$368)-MIN($AP$65:$AP$368))*100 -> 47.339744 | AT50: =IFERROR(1-(AI50/AH50),0) -> 0 | AU50: =IFERROR(AO50/AH50,0) -> 0 | AW50: =VLOOKUP(AX50,Sup!#REF!,8,0) -> #REF! | AX50: Premium | AY50: 0 | BC50: =IF(BE50<0,BE50,0) -> 0 | BD50: =IFERROR(IF(AND(W50="",X50=""),"",IF(OR($AA$373>=$S$26,SUMIF($C:$C,C50,$W:$W)>=$S$27),S50,IF(OR($AA$373>=$R$26,SUMIF($C:$C,C50,$W:$W)>=$R$27),R50,IF(OR($AA$373>=$Q$26,SUMIF($C:$C,C50,$W:$W)>=$Q$27),Q50,IF(OR($AA$373>=$P$26,SUMIF($C:$C,C50,$W:$W)>=$P$27),P50,IF(OR($AA$373>=$O$26,SUMIF($C:$C,C50,$W:$W)>=$O$27),O50,IF(OR($AA$373>=$N$26,SUMIF($C:$C,C50,$W:$W)>=$N$27),N50,IF($AA$373>=$M$26,M50,L50)))))))*$E$13),0) | BE50: =IF(V50="",0,(V50*W50)-(BD50*W50)) -> 0 | BM50: =BM49+24 -> #REF! | BW50: EAT CLEAN | BX50: =IFERROR(W50*U50,0) -> 0 | BY50: =VLOOKUP(B50,#REF!,13,0) -> #REF! | BZ50: 86 | CA50: =VLOOKUP(B50,Pedido!$B$16:$L$292,22,0) -> #N/A | CD50: =CD49+12 -> 144 | CE50: =CD50/12 -> 12 | CF50: =CONCATENATE(CD50,CE50) -> 14412 | CG50: válido
B51: 9932472754 | C51: Pasta Amendoim | D51: Pasta Amendoim | E51: Salted Caramel | F51: Pote | G51: 300g | H51: 41.27 | I51: 179.4 | J51: =IFERROR(IF(T51<>"",I51/T51,IF(AND(Y51="",V51=""),"",IF(V51="",I51/Y51,I51/V51))),"") | K51: =IF(Y51="","",IFERROR(1-(Y51/I51),0)) | L51: 118.8 | M51: =P51 -> 92.9 | N51: =P51 -> 92.9 | O51: =P51 -> 92.9 | P51: 92.9 | Q51: 92.9 | R51: 92.9 | S51: 92.9 | T51: =IF(V51>0,V51,IFERROR(IF(AND(W51<>"",X51<>""),AH51/W51,Y51),"")) | U51: =IFERROR((T51*W51)/(W51+X51),"") | Y51: =IF(AND(W51="",X51=""),"",$E$13*IF(V51<>"",V51,IF(SUMIF($C:$C,C51,$W:$W)>=$S$27,S51,IF(OR($AA$373>=$R$26,SUMIF($C:$C,C51,$W:$W)>=$R$27),R51,IF(OR($AA$373>=$Q$26,SUMIF($C:$C,C51,$W:$W)>=$Q$27),Q51,IF(OR($AA$373>=$P$26,SUMIF($C:$C,C51,$W:$W)>=$P$27),P51,IF(OR($AA$373>=$O$26,SUMIF($C:$C,C51,$W:$W)>=$O$27),O51,IF(OR($AA$373>=$N$26,SUMIF($C:$C,C51,$W:$W)>=$N$27),N51,IF($AA$373>=$M$26,M51,L51))))))))) | Z51: =IF(X51>W51,-1,IF(W51=0,0,IF(U51<(H51/0.75),-1,IF(W51<=3,0,0.0001)))) -> 0 | AA51: =IFERROR(L51*W51,0) -> 0 | AB51: =IFERROR(IF(OR($AA$373>=$S$26,SUMIF($C:$C,C51,$W:$W)>=$S$27),S51,IF(OR($AA$373>=$R$26,SUMIF($C:$C,C51,$W:$W)>=$R$27),R51,IF(OR($AA$373>=$Q$26,SUMIF($C:$C,C51,$W:$W)>=$Q$27),Q51,IF(OR($AA$373>=$P$26,SUMIF($C:$C,C51,$W:$W)>=$P$27),P51,IF(OR($AA$373>=$O$26,SUMIF($C:$C,C51,$W:$W)>=$O$27),O51,IF(OR($AA$373>=$N$26,SUMIF($C:$C,C51,$W:$W)>=$N$27),N51,IF($AA$373>=$M$26,M51,L51)))))))*W51,0) -> 0 | AC51: =IFERROR(IF(V51="",0,(IF(AND(W51="",X51=""),"",IF(OR($AA$373>=$S$26,SUMIF($C:$C,C51,$W:$W)>=$S$27),S51*$E$13,IF(OR($AA$373>=$R$26,SUMIF($C:$C,C51,$W:$W)>=$R$27),R51*$E$13,IF(OR($AA$373>=$Q$26,SUMIF($C:$C,C51,$W:$W)>=$Q$27),Q51*$E$13,IF(OR($AA$373>=$P$26,SUMIF($C:$C,C51,$W:$W)>=$P$27),P51*$E$13,IF(OR($AA$373>=$O$26,SUMIF($C:$C,C51,$W:$W)>=$O$27),O51*$E$13,IF(OR($AA$373>=$N$26,SUMIF($C:$C,C51,$W:$W)>=$N$27),N51*$E$13,IF($AA$373>=$M$26,M51*$E$13,L51))))))))-V51)*W51),0) -> 0 | AD51: =IFERROR(X51*T51,0) -> 0 | AE51: =IFERROR(W51*H51,0) -> 0 | AF51: =IFERROR(1-(AE51/AB51),0) -> 0 | AG51: =IFERROR(SUM(W51:X51)*I51,0) -> 0 | AH51: =IFERROR(IF(V51>0,V51*W51,(Y51*W51)),0) -> 0 | AI51: =IFERROR(SUM(W51)*H51,0) -> 0 | AJ51: =AH51*$AJ$25 -> 0 | AK51: =AH51*AK$25 -> 0 | AL51: =AH51*AL$25 -> 0 | AM51: =SUM(AJ51:AL51) -> 0 | AN51: =AH51-AM51 -> 0 | AO51: =AN51-AI51 -> 0 | AP51: =IFERROR(IF(V51<>"",1-(H51/V51),IF(Y51<>"",1-(H51/Y51),1-(H51/L51))),0) -> 0.65260943 | AQ51: =H51/0.75 -> 55.026667 | AR51: 6 | AS51: =(AP51-MIN($AP$65:$AP$368))/(MAX($AP$65:$AP$368)-MIN($AP$65:$AP$368))*100 -> 65.260943 | AT51: =IFERROR(1-(AI51/AH51),0) -> 0 | AU51: =IFERROR(AO51/AH51,0) -> 0 | AW51: =VLOOKUP(AX51,Sup!#REF!,8,0) -> #REF! | AX51: Premium | AY51: 0 | BC51: =IF(BE51<0,BE51,0) -> 0 | BD51: =IFERROR(IF(AND(W51="",X51=""),"",IF(OR($AA$373>=$S$26,SUMIF($C:$C,C51,$W:$W)>=$S$27),S51,IF(OR($AA$373>=$R$26,SUMIF($C:$C,C51,$W:$W)>=$R$27),R51,IF(OR($AA$373>=$Q$26,SUMIF($C:$C,C51,$W:$W)>=$Q$27),Q51,IF(OR($AA$373>=$P$26,SUMIF($C:$C,C51,$W:$W)>=$P$27),P51,IF(OR($AA$373>=$O$26,SUMIF($C:$C,C51,$W:$W)>=$O$27),O51,IF(OR($AA$373>=$N$26,SUMIF($C:$C,C51,$W:$W)>=$N$27),N51,IF($AA$373>=$M$26,M51,L51)))))))*$E$13),0) | BE51: =IF(V51="",0,(V51*W51)-(BD51*W51)) -> 0 | BM51: =BM50+24 -> #REF! | BW51: EAT CLEAN | BX51: =IFERROR(W51*U51,0) -> 0 | BY51: =VLOOKUP(B51,#REF!,13,0) -> #REF! | BZ51: 99 | CA51: =VLOOKUP(B51,Pedido!$B$16:$L$292,22,0) -> #N/A | CD51: =CD50+12 -> 156 | CE51: =CD51/12 -> 13 | CF51: =CONCATENATE(CD51,CE51) -> 15613 | CG51: válido
B52: 521304083 | C52: Pasta Castanha | D52: Pasta de Pistache 300g | F52: Pote | G52: 300g | H52: 34.85 | I52: 179.4 | J52: =IFERROR(IF(T52<>"",I52/T52,IF(AND(Y52="",V52=""),"",IF(V52="",I52/Y52,I52/V52))),"") | K52: =IF(Y52="","",IFERROR(1-(Y52/I52),0)) | L52: 118.8 | M52: =P52 -> 92.9 | N52: =P52 -> 92.9 | O52: =P52 -> 92.9 | P52: 92.9 | Q52: 92.9 | R52: 92.9 | S52: 92.9 | T52: =IF(V52>0,V52,IFERROR(IF(AND(W52<>"",X52<>""),AH52/W52,Y52),"")) | U52: =IFERROR((T52*W52)/(W52+X52),"") | Y52: =IF(AND(W52="",X52=""),"",$E$13*IF(V52<>"",V52,IF(SUMIF($C:$C,C52,$W:$W)>=$S$27,S52,IF(OR($AA$373>=$R$26,SUMIF($C:$C,C52,$W:$W)>=$R$27),R52,IF(OR($AA$373>=$Q$26,SUMIF($C:$C,C52,$W:$W)>=$Q$27),Q52,IF(OR($AA$373>=$P$26,SUMIF($C:$C,C52,$W:$W)>=$P$27),P52,IF(OR($AA$373>=$O$26,SUMIF($C:$C,C52,$W:$W)>=$O$27),O52,IF(OR($AA$373>=$N$26,SUMIF($C:$C,C52,$W:$W)>=$N$27),N52,IF($AA$373>=$M$26,M52,L52))))))))) | Z52: =IF(X52>W52,-1,IF(W52=0,0,IF(U52<(H52/0.75),-1,IF(W52<=3,0,0.0001)))) -> 0 | AA52: =IFERROR(L52*W52,0) -> 0 | AB52: =IFERROR(IF(OR($AA$373>=$S$26,SUMIF($C:$C,C52,$W:$W)>=$S$27),S52,IF(OR($AA$373>=$R$26,SUMIF($C:$C,C52,$W:$W)>=$R$27),R52,IF(OR($AA$373>=$Q$26,SUMIF($C:$C,C52,$W:$W)>=$Q$27),Q52,IF(OR($AA$373>=$P$26,SUMIF($C:$C,C52,$W:$W)>=$P$27),P52,IF(OR($AA$373>=$O$26,SUMIF($C:$C,C52,$W:$W)>=$O$27),O52,IF(OR($AA$373>=$N$26,SUMIF($C:$C,C52,$W:$W)>=$N$27),N52,IF($AA$373>=$M$26,M52,L52)))))))*W52,0) -> 0 | AC52: =IFERROR(IF(V52="",0,(IF(AND(W52="",X52=""),"",IF(OR($AA$373>=$S$26,SUMIF($C:$C,C52,$W:$W)>=$S$27),S52*$E$13,IF(OR($AA$373>=$R$26,SUMIF($C:$C,C52,$W:$W)>=$R$27),R52*$E$13,IF(OR($AA$373>=$Q$26,SUMIF($C:$C,C52,$W:$W)>=$Q$27),Q52*$E$13,IF(OR($AA$373>=$P$26,SUMIF($C:$C,C52,$W:$W)>=$P$27),P52*$E$13,IF(OR($AA$373>=$O$26,SUMIF($C:$C,C52,$W:$W)>=$O$27),O52*$E$13,IF(OR($AA$373>=$N$26,SUMIF($C:$C,C52,$W:$W)>=$N$27),N52*$E$13,IF($AA$373>=$M$26,M52*$E$13,L52))))))))-V52)*W52),0) -> 0 | AD52: =IFERROR(X52*T52,0) -> 0 | AE52: =IFERROR(W52*H52,0) -> 0 | AF52: =IFERROR(1-(AE52/AB52),0) -> 0 | AG52: =IFERROR(SUM(W52:X52)*I52,0) -> 0 | AH52: =IFERROR(IF(V52>0,V52*W52,(Y52*W52)),0) -> 0 | AI52: =IFERROR(SUM(W52)*H52,0) -> 0 | AJ52: =AH52*$AJ$25 -> 0 | AK52: =AH52*AK$25 -> 0 | AL52: =AH52*AL$25 -> 0 | AM52: =SUM(AJ52:AL52) -> 0 | AN52: =AH52-AM52 -> 0 | AO52: =AN52-AI52 -> 0 | AP52: =IFERROR(IF(V52<>"",1-(H52/V52),IF(Y52<>"",1-(H52/Y52),1-(H52/L52))),0) -> 0.70664983 | AQ52: =H52/0.75 -> 46.466667 | AR52: 6 | AS52: =(AP52-MIN($AP$65:$AP$368))/(MAX($AP$65:$AP$368)-MIN($AP$65:$AP$368))*100 -> 70.664983 | AT52: =IFERROR(1-(AI52/AH52),0) -> 0 | AU52: =IFERROR(AO52/AH52,0) -> 0 | AW52: =VLOOKUP(AX52,Sup!#REF!,8,0) -> #REF! | AX52: Premium | AY52: 0 | BC52: =IF(BE52<0,BE52,0) -> 0 | BD52: =IFERROR(IF(AND(W52="",X52=""),"",IF(OR($AA$373>=$S$26,SUMIF($C:$C,C52,$W:$W)>=$S$27),S52,IF(OR($AA$373>=$R$26,SUMIF($C:$C,C52,$W:$W)>=$R$27),R52,IF(OR($AA$373>=$Q$26,SUMIF($C:$C,C52,$W:$W)>=$Q$27),Q52,IF(OR($AA$373>=$P$26,SUMIF($C:$C,C52,$W:$W)>=$P$27),P52,IF(OR($AA$373>=$O$26,SUMIF($C:$C,C52,$W:$W)>=$O$27),O52,IF(OR($AA$373>=$N$26,SUMIF($C:$C,C52,$W:$W)>=$N$27),N52,IF($AA$373>=$M$26,M52,L52)))))))*$E$13),0) | BE52: =IF(V52="",0,(V52*W52)-(BD52*W52)) -> 0 | BM52: =BM51+24 -> #REF! | BW52: EAT CLEAN | BX52: =IFERROR(W52*U52,0) -> 0 | BY52: =VLOOKUP(B52,#REF!,13,0) -> #REF! | BZ52: 99 | CA52: =VLOOKUP(B52,Pedido!$B$16:$L$292,22,0) -> #REF! | CD52: =CD51+12 -> 168 | CE52: =CD52/12 -> 14 | CF52: =CONCATENATE(CD52,CE52) -> 16814 | CG52: válido
B53: 521304095 | C53: Pasta Castanha | D53: Pasta de Avelã com Cacau 300g | F53: Pote | G53: 300g | H53: 47.28 | I53: 179.4 | J53: =IFERROR(IF(T53<>"",I53/T53,IF(AND(Y53="",V53=""),"",IF(V53="",I53/Y53,I53/V53))),"") | K53: =IF(Y53="","",IFERROR(1-(Y53/I53),0)) | L53: 118.8 | M53: =P53 -> 92.9 | N53: =P53 -> 92.9 | O53: =P53 -> 92.9 | P53: 92.9 | Q53: 92.9 | R53: 92.9 | S53: 92.9 | T53: =IF(V53>0,V53,IFERROR(IF(AND(W53<>"",X53<>""),AH53/W53,Y53),"")) | U53: =IFERROR((T53*W53)/(W53+X53),"") | Y53: =IF(AND(W53="",X53=""),"",$E$13*IF(V53<>"",V53,IF(SUMIF($C:$C,C53,$W:$W)>=$S$27,S53,IF(OR($AA$373>=$R$26,SUMIF($C:$C,C53,$W:$W)>=$R$27),R53,IF(OR($AA$373>=$Q$26,SUMIF($C:$C,C53,$W:$W)>=$Q$27),Q53,IF(OR($AA$373>=$P$26,SUMIF($C:$C,C53,$W:$W)>=$P$27),P53,IF(OR($AA$373>=$O$26,SUMIF($C:$C,C53,$W:$W)>=$O$27),O53,IF(OR($AA$373>=$N$26,SUMIF($C:$C,C53,$W:$W)>=$N$27),N53,IF($AA$373>=$M$26,M53,L53))))))))) | Z53: =IF(X53>W53,-1,IF(W53=0,0,IF(U53<(H53/0.75),-1,IF(W53<=3,0,0.0001)))) -> 0 | AA53: =IFERROR(L53*W53,0) -> 0 | AB53: =IFERROR(IF(OR($AA$373>=$S$26,SUMIF($C:$C,C53,$W:$W)>=$S$27),S53,IF(OR($AA$373>=$R$26,SUMIF($C:$C,C53,$W:$W)>=$R$27),R53,IF(OR($AA$373>=$Q$26,SUMIF($C:$C,C53,$W:$W)>=$Q$27),Q53,IF(OR($AA$373>=$P$26,SUMIF($C:$C,C53,$W:$W)>=$P$27),P53,IF(OR($AA$373>=$O$26,SUMIF($C:$C,C53,$W:$W)>=$O$27),O53,IF(OR($AA$373>=$N$26,SUMIF($C:$C,C53,$W:$W)>=$N$27),N53,IF($AA$373>=$M$26,M53,L53)))))))*W53,0) -> 0 | AC53: =IFERROR(IF(V53="",0,(IF(AND(W53="",X53=""),"",IF(OR($AA$373>=$S$26,SUMIF($C:$C,C53,$W:$W)>=$S$27),S53*$E$13,IF(OR($AA$373>=$R$26,SUMIF($C:$C,C53,$W:$W)>=$R$27),R53*$E$13,IF(OR($AA$373>=$Q$26,SUMIF($C:$C,C53,$W:$W)>=$Q$27),Q53*$E$13,IF(OR($AA$373>=$P$26,SUMIF($C:$C,C53,$W:$W)>=$P$27),P53*$E$13,IF(OR($AA$373>=$O$26,SUMIF($C:$C,C53,$W:$W)>=$O$27),O53*$E$13,IF(OR($AA$373>=$N$26,SUMIF($C:$C,C53,$W:$W)>=$N$27),N53*$E$13,IF($AA$373>=$M$26,M53*$E$13,L53))))))))-V53)*W53),0) -> 0 | AD53: =IFERROR(X53*T53,0) -> 0 | AE53: =IFERROR(W53*H53,0) -> 0 | AF53: =IFERROR(1-(AE53/AB53),0) -> 0 | AG53: =IFERROR(SUM(W53:X53)*I53,0) -> 0 | AH53: =IFERROR(IF(V53>0,V53*W53,(Y53*W53)),0) -> 0 | AI53: =IFERROR(SUM(W53)*H53,0) -> 0 | AJ53: =AH53*$AJ$25 -> 0 | AK53: =AH53*AK$25 -> 0 | AL53: =AH53*AL$25 -> 0 | AM53: =SUM(AJ53:AL53) -> 0 | AN53: =AH53-AM53 -> 0 | AO53: =AN53-AI53 -> 0 | AP53: =IFERROR(IF(V53<>"",1-(H53/V53),IF(Y53<>"",1-(H53/Y53),1-(H53/L53))),0) -> 0.6020202 | AQ53: =H53/0.75 -> 63.04 | AR53: 6 | AS53: =(AP53-MIN($AP$65:$AP$368))/(MAX($AP$65:$AP$368)-MIN($AP$65:$AP$368))*100 -> 60.20202 | AT53: =IFERROR(1-(AI53/AH53),0) -> 0 | AU53: =IFERROR(AO53/AH53,0) -> 0 | AW53: =VLOOKUP(AX53,Sup!#REF!,8,0) -> #REF! | AX53: Premium | AY53: 0 | BC53: =IF(BE53<0,BE53,0) -> 0 | BD53: =IFERROR(IF(AND(W53="",X53=""),"",IF(OR($AA$373>=$S$26,SUMIF($C:$C,C53,$W:$W)>=$S$27),S53,IF(OR($AA$373>=$R$26,SUMIF($C:$C,C53,$W:$W)>=$R$27),R53,IF(OR($AA$373>=$Q$26,SUMIF($C:$C,C53,$W:$W)>=$Q$27),Q53,IF(OR($AA$373>=$P$26,SUMIF($C:$C,C53,$W:$W)>=$P$27),P53,IF(OR($AA$373>=$O$26,SUMIF($C:$C,C53,$W:$W)>=$O$27),O53,IF(OR($AA$373>=$N$26,SUMIF($C:$C,C53,$W:$W)>=$N$27),N53,IF($AA$373>=$M$26,M53,L53)))))))*$E$13),0) | BE53: =IF(V53="",0,(V53*W53)-(BD53*W53)) -> 0 | BM53: =BM52+24 -> #REF! | BW53: EAT CLEAN | BX53: =IFERROR(W53*U53,0) -> 0 | BY53: =VLOOKUP(B53,#REF!,13,0) -> #REF! | BZ53: 99 | CA53: =VLOOKUP(B53,Pedido!$B$16:$L$292,22,0) -> #REF! | CD53: =CD52+12 -> 180 | CE53: =CD53/12 -> 15 | CF53: =CONCATENATE(CD53,CE53) -> 18015 | CG53: válido
B54: 521304097 | C54: Pasta Castanha | D54: Pasta de Macadâmia 300g | F54: Pote | G54: 300g | H54: 49.29 | I54: 149.4 | J54: =IFERROR(IF(T54<>"",I54/T54,IF(AND(Y54="",V54=""),"",IF(V54="",I54/Y54,I54/V54))),"") | K54: =IF(Y54="","",IFERROR(1-(Y54/I54),0)) | L54: 93.6 | M54: =P54 -> 74.9 | N54: =P54 -> 74.9 | O54: =P54 -> 74.9 | P54: 74.9 | Q54: 74.9 | R54: 74.9 | S54: 74.9 | T54: =IF(V54>0,V54,IFERROR(IF(AND(W54<>"",X54<>""),AH54/W54,Y54),"")) | U54: =IFERROR((T54*W54)/(W54+X54),"") | Y54: =IF(AND(W54="",X54=""),"",$E$13*IF(V54<>"",V54,IF(SUMIF($C:$C,C54,$W:$W)>=$S$27,S54,IF(OR($AA$373>=$R$26,SUMIF($C:$C,C54,$W:$W)>=$R$27),R54,IF(OR($AA$373>=$Q$26,SUMIF($C:$C,C54,$W:$W)>=$Q$27),Q54,IF(OR($AA$373>=$P$26,SUMIF($C:$C,C54,$W:$W)>=$P$27),P54,IF(OR($AA$373>=$O$26,SUMIF($C:$C,C54,$W:$W)>=$O$27),O54,IF(OR($AA$373>=$N$26,SUMIF($C:$C,C54,$W:$W)>=$N$27),N54,IF($AA$373>=$M$26,M54,L54))))))))) | Z54: =IF(X54>W54,-1,IF(W54=0,0,IF(U54<(H54/0.75),-1,IF(W54<=3,0,0.0001)))) -> 0 | AA54: =IFERROR(L54*W54,0) -> 0 | AB54: =IFERROR(IF(OR($AA$373>=$S$26,SUMIF($C:$C,C54,$W:$W)>=$S$27),S54,IF(OR($AA$373>=$R$26,SUMIF($C:$C,C54,$W:$W)>=$R$27),R54,IF(OR($AA$373>=$Q$26,SUMIF($C:$C,C54,$W:$W)>=$Q$27),Q54,IF(OR($AA$373>=$P$26,SUMIF($C:$C,C54,$W:$W)>=$P$27),P54,IF(OR($AA$373>=$O$26,SUMIF($C:$C,C54,$W:$W)>=$O$27),O54,IF(OR($AA$373>=$N$26,SUMIF($C:$C,C54,$W:$W)>=$N$27),N54,IF($AA$373>=$M$26,M54,L54)))))))*W54,0) -> 0 | AC54: =IFERROR(IF(V54="",0,(IF(AND(W54="",X54=""),"",IF(OR($AA$373>=$S$26,SUMIF($C:$C,C54,$W:$W)>=$S$27),S54*$E$13,IF(OR($AA$373>=$R$26,SUMIF($C:$C,C54,$W:$W)>=$R$27),R54*$E$13,IF(OR($AA$373>=$Q$26,SUMIF($C:$C,C54,$W:$W)>=$Q$27),Q54*$E$13,IF(OR($AA$373>=$P$26,SUMIF($C:$C,C54,$W:$W)>=$P$27),P54*$E$13,IF(OR($AA$373>=$O$26,SUMIF($C:$C,C54,$W:$W)>=$O$27),O54*$E$13,IF(OR($AA$373>=$N$26,SUMIF($C:$C,C54,$W:$W)>=$N$27),N54*$E$13,IF($AA$373>=$M$26,M54*$E$13,L54))))))))-V54)*W54),0) -> 0 | AD54: =IFERROR(X54*T54,0) -> 0 | AE54: =IFERROR(W54*H54,0) -> 0 | AF54: =IFERROR(1-(AE54/AB54),0) -> 0 | AG54: =IFERROR(SUM(W54:X54)*I54,0) -> 0 | AH54: =IFERROR(IF(V54>0,V54*W54,(Y54*W54)),0) -> 0 | AI54: =IFERROR(SUM(W54)*H54,0) -> 0 | AJ54: =AH54*$AJ$25 -> 0 | AK54: =AH54*AK$25 -> 0 | AL54: =AH54*AL$25 -> 0 | AM54: =SUM(AJ54:AL54) -> 0 | AN54: =AH54-AM54 -> 0 | AO54: =AN54-AI54 -> 0 | AP54: =IFERROR(IF(V54<>"",1-(H54/V54),IF(Y54<>"",1-(H54/Y54),1-(H54/L54))),0) -> 0.47339744 | AQ54: =H54/0.75 -> 65.72 | AR54: 6 | AS54: =(AP54-MIN($AP$65:$AP$368))/(MAX($AP$65:$AP$368)-MIN($AP$65:$AP$368))*100 -> 47.339744 | AT54: =IFERROR(1-(AI54/AH54),0) -> 0 | AU54: =IFERROR(AO54/AH54,0) -> 0 | AW54: =VLOOKUP(AX54,Sup!#REF!,8,0) -> #REF! | AX54: Premium | AY54: 0 | BC54: =IF(BE54<0,BE54,0) -> 0 | BD54: =IFERROR(IF(AND(W54="",X54=""),"",IF(OR($AA$373>=$S$26,SUMIF($C:$C,C54,$W:$W)>=$S$27),S54,IF(OR($AA$373>=$R$26,SUMIF($C:$C,C54,$W:$W)>=$R$27),R54,IF(OR($AA$373>=$Q$26,SUMIF($C:$C,C54,$W:$W)>=$Q$27),Q54,IF(OR($AA$373>=$P$26,SUMIF($C:$C,C54,$W:$W)>=$P$27),P54,IF(OR($AA$373>=$O$26,SUMIF($C:$C,C54,$W:$W)>=$O$27),O54,IF(OR($AA$373>=$N$26,SUMIF($C:$C,C54,$W:$W)>=$N$27),N54,IF($AA$373>=$M$26,M54,L54)))))))*$E$13),0) | BE54: =IF(V54="",0,(V54*W54)-(BD54*W54)) -> 0 | BM54: =BM53+24 -> #REF! | BW54: EAT CLEAN | BX54: =IFERROR(W54*U54,0) -> 0 | BY54: =VLOOKUP(B54,#REF!,13,0) -> #REF! | BZ54: 86 | CA54: =VLOOKUP(B54,Pedido!$B$16:$L$292,22,0) -> #REF! | CD54: =CD53+12 -> 192 | CE54: =CD54/12 -> 16 | CF54: =CONCATENATE(CD54,CE54) -> 19216 | CG54: válido
B55: 521304096 | C55: Pasta Castanha | D55: Pasta de Amêndoas 300g | F55: Pote | G55: 300g | H55: 41.27 | I55: 179.4 | J55: =IFERROR(IF(T55<>"",I55/T55,IF(AND(Y55="",V55=""),"",IF(V55="",I55/Y55,I55/V55))),"") | K55: =IF(Y55="","",IFERROR(1-(Y55/I55),0)) | L55: 118.8 | M55: =P55 -> 92.9 | N55: =P55 -> 92.9 | O55: =P55 -> 92.9 | P55: 92.9 | Q55: 92.9 | R55: 92.9 | S55: 92.9 | T55: =IF(V55>0,V55,IFERROR(IF(AND(W55<>"",X55<>""),AH55/W55,Y55),"")) | U55: =IFERROR((T55*W55)/(W55+X55),"") | Y55: =IF(AND(W55="",X55=""),"",$E$13*IF(V55<>"",V55,IF(SUMIF($C:$C,C55,$W:$W)>=$S$27,S55,IF(OR($AA$373>=$R$26,SUMIF($C:$C,C55,$W:$W)>=$R$27),R55,IF(OR($AA$373>=$Q$26,SUMIF($C:$C,C55,$W:$W)>=$Q$27),Q55,IF(OR($AA$373>=$P$26,SUMIF($C:$C,C55,$W:$W)>=$P$27),P55,IF(OR($AA$373>=$O$26,SUMIF($C:$C,C55,$W:$W)>=$O$27),O55,IF(OR($AA$373>=$N$26,SUMIF($C:$C,C55,$W:$W)>=$N$27),N55,IF($AA$373>=$M$26,M55,L55))))))))) | Z55: =IF(X55>W55,-1,IF(W55=0,0,IF(U55<(H55/0.75),-1,IF(W55<=3,0,0.0001)))) -> 0 | AA55: =IFERROR(L55*W55,0) -> 0 | AB55: =IFERROR(IF(OR($AA$373>=$S$26,SUMIF($C:$C,C55,$W:$W)>=$S$27),S55,IF(OR($AA$373>=$R$26,SUMIF($C:$C,C55,$W:$W)>=$R$27),R55,IF(OR($AA$373>=$Q$26,SUMIF($C:$C,C55,$W:$W)>=$Q$27),Q55,IF(OR($AA$373>=$P$26,SUMIF($C:$C,C55,$W:$W)>=$P$27),P55,IF(OR($AA$373>=$O$26,SUMIF($C:$C,C55,$W:$W)>=$O$27),O55,IF(OR($AA$373>=$N$26,SUMIF($C:$C,C55,$W:$W)>=$N$27),N55,IF($AA$373>=$M$26,M55,L55)))))))*W55,0) -> 0 | AC55: =IFERROR(IF(V55="",0,(IF(AND(W55="",X55=""),"",IF(OR($AA$373>=$S$26,SUMIF($C:$C,C55,$W:$W)>=$S$27),S55*$E$13,IF(OR($AA$373>=$R$26,SUMIF($C:$C,C55,$W:$W)>=$R$27),R55*$E$13,IF(OR($AA$373>=$Q$26,SUMIF($C:$C,C55,$W:$W)>=$Q$27),Q55*$E$13,IF(OR($AA$373>=$P$26,SUMIF($C:$C,C55,$W:$W)>=$P$27),P55*$E$13,IF(OR($AA$373>=$O$26,SUMIF($C:$C,C55,$W:$W)>=$O$27),O55*$E$13,IF(OR($AA$373>=$N$26,SUMIF($C:$C,C55,$W:$W)>=$N$27),N55*$E$13,IF($AA$373>=$M$26,M55*$E$13,L55))))))))-V55)*W55),0) -> 0 | AD55: =IFERROR(X55*T55,0) -> 0 | AE55: =IFERROR(W55*H55,0) -> 0 | AF55: =IFERROR(1-(AE55/AB55),0) -> 0 | AG55: =IFERROR(SUM(W55:X55)*I55,0) -> 0 | AH55: =IFERROR(IF(V55>0,V55*W55,(Y55*W55)),0) -> 0 | AI55: =IFERROR(SUM(W55)*H55,0) -> 0 | AJ55: =AH55*$AJ$25 -> 0 | AK55: =AH55*AK$25 -> 0 | AL55: =AH55*AL$25 -> 0 | AM55: =SUM(AJ55:AL55) -> 0 | AN55: =AH55-AM55 -> 0 | AO55: =AN55-AI55 -> 0 | AP55: =IFERROR(IF(V55<>"",1-(H55/V55),IF(Y55<>"",1-(H55/Y55),1-(H55/L55))),0) -> 0.65260943 | AQ55: =H55/0.75 -> 55.026667 | AR55: 6 | AS55: =(AP55-MIN($AP$65:$AP$368))/(MAX($AP$65:$AP$368)-MIN($AP$65:$AP$368))*100 -> 65.260943 | AT55: =IFERROR(1-(AI55/AH55),0) -> 0 | AU55: =IFERROR(AO55/AH55,0) -> 0 | AW55: =VLOOKUP(AX55,Sup!#REF!,8,0) -> #REF! | AX55: Premium | AY55: 0 | BC55: =IF(BE55<0,BE55,0) -> 0 | BD55: =IFERROR(IF(AND(W55="",X55=""),"",IF(OR($AA$373>=$S$26,SUMIF($C:$C,C55,$W:$W)>=$S$27),S55,IF(OR($AA$373>=$R$26,SUMIF($C:$C,C55,$W:$W)>=$R$27),R55,IF(OR($AA$373>=$Q$26,SUMIF($C:$C,C55,$W:$W)>=$Q$27),Q55,IF(OR($AA$373>=$P$26,SUMIF($C:$C,C55,$W:$W)>=$P$27),P55,IF(OR($AA$373>=$O$26,SUMIF($C:$C,C55,$W:$W)>=$O$27),O55,IF(OR($AA$373>=$N$26,SUMIF($C:$C,C55,$W:$W)>=$N$27),N55,IF($AA$373>=$M$26,M55,L55)))))))*$E$13),0) | BE55: =IF(V55="",0,(V55*W55)-(BD55*W55)) -> 0 | BM55: =BM54+24 -> #REF! | BW55: EAT CLEAN | BX55: =IFERROR(W55*U55,0) -> 0 | BY55: =VLOOKUP(B55,#REF!,13,0) -> #REF! | BZ55: 99 | CA55: =VLOOKUP(B55,Pedido!$B$16:$L$292,22,0) -> #N/A | CD55: =CD54+12 -> 204 | CE55: =CD55/12 -> 17 | CF55: =CONCATENATE(CD55,CE55) -> 20417 | CG55: válido
B56: 9962535985 | C56: Pasta Castanha | D56: Pasta Castanha | E56: Chocolate Belga | F56: Pote | G56: 300g | H56: 56.44 | I56: 239.4 | J56: =IFERROR(IF(T56<>"",I56/T56,IF(AND(Y56="",V56=""),"",IF(V56="",I56/Y56,I56/V56))),"") | K56: =IF(Y56="","",IFERROR(1-(Y56/I56),0)) | L56: 168.18 | M56: =P56 -> 129.9 | N56: =P56 -> 129.9 | O56: =P56 -> 129.9 | P56: 129.9 | Q56: 129.9 | R56: 129.9 | S56: 129.9 | T56: =IF(V56>0,V56,IFERROR(IF(AND(W56<>"",X56<>""),AH56/W56,Y56),"")) | U56: =IFERROR((T56*W56)/(W56+X56),"") | Y56: =IF(AND(W56="",X56=""),"",$E$13*IF(V56<>"",V56,IF(SUMIF($C:$C,C56,$W:$W)>=$S$27,S56,IF(OR($AA$373>=$R$26,SUMIF($C:$C,C56,$W:$W)>=$R$27),R56,IF(OR($AA$373>=$Q$26,SUMIF($C:$C,C56,$W:$W)>=$Q$27),Q56,IF(OR($AA$373>=$P$26,SUMIF($C:$C,C56,$W:$W)>=$P$27),P56,IF(OR($AA$373>=$O$26,SUMIF($C:$C,C56,$W:$W)>=$O$27),O56,IF(OR($AA$373>=$N$26,SUMIF($C:$C,C56,$W:$W)>=$N$27),N56,IF($AA$373>=$M$26,M56,L56))))))))) | Z56: =IF(X56>W56,-1,IF(W56=0,0,IF(U56<(H56/0.75),-1,IF(W56<=3,0,0.0001)))) -> 0 | AA56: =IFERROR(L56*W56,0) -> 0 | AB56: =IFERROR(IF(OR($AA$373>=$S$26,SUMIF($C:$C,C56,$W:$W)>=$S$27),S56,IF(OR($AA$373>=$R$26,SUMIF($C:$C,C56,$W:$W)>=$R$27),R56,IF(OR($AA$373>=$Q$26,SUMIF($C:$C,C56,$W:$W)>=$Q$27),Q56,IF(OR($AA$373>=$P$26,SUMIF($C:$C,C56,$W:$W)>=$P$27),P56,IF(OR($AA$373>=$O$26,SUMIF($C:$C,C56,$W:$W)>=$O$27),O56,IF(OR($AA$373>=$N$26,SUMIF($C:$C,C56,$W:$W)>=$N$27),N56,IF($AA$373>=$M$26,M56,L56)))))))*W56,0) -> 0 | AC56: =IFERROR(IF(V56="",0,(IF(AND(W56="",X56=""),"",IF(OR($AA$373>=$S$26,SUMIF($C:$C,C56,$W:$W)>=$S$27),S56*$E$13,IF(OR($AA$373>=$R$26,SUMIF($C:$C,C56,$W:$W)>=$R$27),R56*$E$13,IF(OR($AA$373>=$Q$26,SUMIF($C:$C,C56,$W:$W)>=$Q$27),Q56*$E$13,IF(OR($AA$373>=$P$26,SUMIF($C:$C,C56,$W:$W)>=$P$27),P56*$E$13,IF(OR($AA$373>=$O$26,SUMIF($C:$C,C56,$W:$W)>=$O$27),O56*$E$13,IF(OR($AA$373>=$N$26,SUMIF($C:$C,C56,$W:$W)>=$N$27),N56*$E$13,IF($AA$373>=$M$26,M56*$E$13,L56))))))))-V56)*W56),0) -> 0 | AD56: =IFERROR(X56*T56,0) -> 0 | AE56: =IFERROR(W56*H56,0) -> 0 | AF56: =IFERROR(1-(AE56/AB56),0) -> 0 | AG56: =IFERROR(SUM(W56:X56)*I56,0) -> 0 | AH56: =IFERROR(IF(V56>0,V56*W56,(Y56*W56)),0) -> 0 | AI56: =IFERROR(SUM(W56)*H56,0) -> 0 | AJ56: =AH56*$AJ$25 -> 0 | AK56: =AH56*AK$25 -> 0 | AL56: =AH56*AL$25 -> 0 | AM56: =SUM(AJ56:AL56) -> 0 | AN56: =AH56-AM56 -> 0 | AO56: =AN56-AI56 -> 0 | AP56: =IFERROR(IF(V56<>"",1-(H56/V56),IF(Y56<>"",1-(H56/Y56),1-(H56/L56))),0) -> 0.66440718 | AQ56: =H56/0.75 -> 75.253333 | AR56: 6 | AS56: =(AP56-MIN($AP$65:$AP$368))/(MAX($AP$65:$AP$368)-MIN($AP$65:$AP$368))*100 -> 66.440718 | AT56: =IFERROR(1-(AI56/AH56),0) -> 0 | AU56: =IFERROR(AO56/AH56,0) -> 0 | AW56: =VLOOKUP(AX56,Sup!#REF!,8,0) -> #REF! | AX56: Premium | AY56: 0 | BC56: =IF(BE56<0,BE56,0) -> 0 | BD56: =IFERROR(IF(AND(W56="",X56=""),"",IF(OR($AA$373>=$S$26,SUMIF($C:$C,C56,$W:$W)>=$S$27),S56,IF(OR($AA$373>=$R$26,SUMIF($C:$C,C56,$W:$W)>=$R$27),R56,IF(OR($AA$373>=$Q$26,SUMIF($C:$C,C56,$W:$W)>=$Q$27),Q56,IF(OR($AA$373>=$P$26,SUMIF($C:$C,C56,$W:$W)>=$P$27),P56,IF(OR($AA$373>=$O$26,SUMIF($C:$C,C56,$W:$W)>=$O$27),O56,IF(OR($AA$373>=$N$26,SUMIF($C:$C,C56,$W:$W)>=$N$27),N56,IF($AA$373>=$M$26,M56,L56)))))))*$E$13),0) | BE56: =IF(V56="",0,(V56*W56)-(BD56*W56)) -> 0 | BM56: =BM51+24 -> #REF! | BW56: EAT CLEAN | BX56: =IFERROR(W56*U56,0) -> 0 | BY56: =VLOOKUP(B56,#REF!,13,0) -> #REF! | BZ56: 136 | CA56: =VLOOKUP(B56,Pedido!$B$16:$L$292,22,0) -> #N/A | CD56: =CD51+12 -> 168 | CE56: =CD56/12 -> 14 | CF56: =CONCATENATE(CD56,CE56) -> 16814 | CG56: válido
B57: 15838521679 | C57: Pasta Castanha | D57: Pasta Castanha | E57: Cookies 'N' Cream | F57: Pote | G57: 300g | H57: 65.88 | I57: 239.4 | J57: =IFERROR(IF(T57<>"",I57/T57,IF(AND(Y57="",V57=""),"",IF(V57="",I57/Y57,I57/V57))),"") | K57: =IF(Y57="","",IFERROR(1-(Y57/I57),0)) | L57: 168.18 | M57: =P57 -> 129.9 | N57: =P57 -> 129.9 | O57: =P57 -> 129.9 | P57: 129.9 | Q57: 129.9 | R57: 129.9 | S57: 129.9 | T57: =IF(V57>0,V57,IFERROR(IF(AND(W57<>"",X57<>""),AH57/W57,Y57),"")) | U57: =IFERROR((T57*W57)/(W57+X57),"") | Y57: =IF(AND(W57="",X57=""),"",$E$13*IF(V57<>"",V57,IF(SUMIF($C:$C,C57,$W:$W)>=$S$27,S57,IF(OR($AA$373>=$R$26,SUMIF($C:$C,C57,$W:$W)>=$R$27),R57,IF(OR($AA$373>=$Q$26,SUMIF($C:$C,C57,$W:$W)>=$Q$27),Q57,IF(OR($AA$373>=$P$26,SUMIF($C:$C,C57,$W:$W)>=$P$27),P57,IF(OR($AA$373>=$O$26,SUMIF($C:$C,C57,$W:$W)>=$O$27),O57,IF(OR($AA$373>=$N$26,SUMIF($C:$C,C57,$W:$W)>=$N$27),N57,IF($AA$373>=$M$26,M57,L57))))))))) | Z57: =IF(X57>W57,-1,IF(W57=0,0,IF(U57<(H57/0.75),-1,IF(W57<=3,0,0.0001)))) -> 0 | AA57: =IFERROR(L57*W57,0) -> 0 | AB57: =IFERROR(IF(OR($AA$373>=$S$26,SUMIF($C:$C,C57,$W:$W)>=$S$27),S57,IF(OR($AA$373>=$R$26,SUMIF($C:$C,C57,$W:$W)>=$R$27),R57,IF(OR($AA$373>=$Q$26,SUMIF($C:$C,C57,$W:$W)>=$Q$27),Q57,IF(OR($AA$373>=$P$26,SUMIF($C:$C,C57,$W:$W)>=$P$27),P57,IF(OR($AA$373>=$O$26,SUMIF($C:$C,C57,$W:$W)>=$O$27),O57,IF(OR($AA$373>=$N$26,SUMIF($C:$C,C57,$W:$W)>=$N$27),N57,IF($AA$373>=$M$26,M57,L57)))))))*W57,0) -> 0 | AC57: =IFERROR(IF(V57="",0,(IF(AND(W57="",X57=""),"",IF(OR($AA$373>=$S$26,SUMIF($C:$C,C57,$W:$W)>=$S$27),S57*$E$13,IF(OR($AA$373>=$R$26,SUMIF($C:$C,C57,$W:$W)>=$R$27),R57*$E$13,IF(OR($AA$373>=$Q$26,SUMIF($C:$C,C57,$W:$W)>=$Q$27),Q57*$E$13,IF(OR($AA$373>=$P$26,SUMIF($C:$C,C57,$W:$W)>=$P$27),P57*$E$13,IF(OR($AA$373>=$O$26,SUMIF($C:$C,C57,$W:$W)>=$O$27),O57*$E$13,IF(OR($AA$373>=$N$26,SUMIF($C:$C,C57,$W:$W)>=$N$27),N57*$E$13,IF($AA$373>=$M$26,M57*$E$13,L57))))))))-V57)*W57),0) -> 0 | AD57: =IFERROR(X57*T57,0) -> 0 | AE57: =IFERROR(W57*H57,0) -> 0 | AF57: =IFERROR(1-(AE57/AB57),0) -> 0 | AG57: =IFERROR(SUM(W57:X57)*I57,0) -> 0 | AH57: =IFERROR(IF(V57>0,V57*W57,(Y57*W57)),0) -> 0 | AI57: =IFERROR(SUM(W57)*H57,0) -> 0 | AJ57: =AH57*$AJ$25 -> 0 | AK57: =AH57*AK$25 -> 0 | AL57: =AH57*AL$25 -> 0 | AM57: =SUM(AJ57:AL57) -> 0 | AN57: =AH57-AM57 -> 0 | AO57: =AN57-AI57 -> 0 | AP57: =IFERROR(IF(V57<>"",1-(H57/V57),IF(Y57<>"",1-(H57/Y57),1-(H57/L57))),0) -> 0.60827685 | AQ57: =H57/0.75 -> 87.84 | AR57: 6 | AS57: =(AP57-MIN($AP$65:$AP$368))/(MAX($AP$65:$AP$368)-MIN($AP$65:$AP$368))*100 -> 60.827685 | AT57: =IFERROR(1-(AI57/AH57),0) -> 0 | AU57: =IFERROR(AO57/AH57,0) -> 0 | AW57: =VLOOKUP(AX57,Sup!#REF!,8,0) -> #REF! | AX57: Premium | AY57: 0 | BC57: =IF(BE57<0,BE57,0) -> 0 | BD57: =IFERROR(IF(AND(W57="",X57=""),"",IF(OR($AA$373>=$S$26,SUMIF($C:$C,C57,$W:$W)>=$S$27),S57,IF(OR($AA$373>=$R$26,SUMIF($C:$C,C57,$W:$W)>=$R$27),R57,IF(OR($AA$373>=$Q$26,SUMIF($C:$C,C57,$W:$W)>=$Q$27),Q57,IF(OR($AA$373>=$P$26,SUMIF($C:$C,C57,$W:$W)>=$P$27),P57,IF(OR($AA$373>=$O$26,SUMIF($C:$C,C57,$W:$W)>=$O$27),O57,IF(OR($AA$373>=$N$26,SUMIF($C:$C,C57,$W:$W)>=$N$27),N57,IF($AA$373>=$M$26,M57,L57)))))))*$E$13),0) | BE57: =IF(V57="",0,(V57*W57)-(BD57*W57)) -> 0 | BM57: =BM56+24 -> #REF! | BW57: EAT CLEAN | BX57: =IFERROR(W57*U57,0) -> 0 | BY57: =VLOOKUP(B57,#REF!,13,0) -> #REF! | BZ57: 136 | CA57: =VLOOKUP(B57,Pedido!$B$16:$L$292,22,0) -> #N/A | CD57: =CD56+12 -> 180 | CE57: =CD57/12 -> 15 | CF57: =CONCATENATE(CD57,CE57) -> 18015 | CG57: válido
B58: 11331746667 | C58: Pasta Castanha | D58: Pasta Castanha | E58: Doce de Leite | F58: Pote | G58: 300g | H58: 76.72 | I58: 239.4 | J58: =IFERROR(IF(T58<>"",I58/T58,IF(AND(Y58="",V58=""),"",IF(V58="",I58/Y58,I58/V58))),"") | K58: =IF(Y58="","",IFERROR(1-(Y58/I58),0)) | L58: 168.18 | M58: =P58 -> 129.9 | N58: =P58 -> 129.9 | O58: =P58 -> 129.9 | P58: 129.9 | Q58: 129.9 | R58: 129.9 | S58: 129.9 | T58: =IF(V58>0,V58,IFERROR(IF(AND(W58<>"",X58<>""),AH58/W58,Y58),"")) | U58: =IFERROR((T58*W58)/(W58+X58),"") | Y58: =IF(AND(W58="",X58=""),"",$E$13*IF(V58<>"",V58,IF(SUMIF($C:$C,C58,$W:$W)>=$S$27,S58,IF(OR($AA$373>=$R$26,SUMIF($C:$C,C58,$W:$W)>=$R$27),R58,IF(OR($AA$373>=$Q$26,SUMIF($C:$C,C58,$W:$W)>=$Q$27),Q58,IF(OR($AA$373>=$P$26,SUMIF($C:$C,C58,$W:$W)>=$P$27),P58,IF(OR($AA$373>=$O$26,SUMIF($C:$C,C58,$W:$W)>=$O$27),O58,IF(OR($AA$373>=$N$26,SUMIF($C:$C,C58,$W:$W)>=$N$27),N58,IF($AA$373>=$M$26,M58,L58))))))))) | Z58: =IF(X58>W58,-1,IF(W58=0,0,IF(U58<(H58/0.75),-1,IF(W58<=3,0,0.0001)))) -> 0 | AA58: =IFERROR(L58*W58,0) -> 0 | AB58: =IFERROR(IF(OR($AA$373>=$S$26,SUMIF($C:$C,C58,$W:$W)>=$S$27),S58,IF(OR($AA$373>=$R$26,SUMIF($C:$C,C58,$W:$W)>=$R$27),R58,IF(OR($AA$373>=$Q$26,SUMIF($C:$C,C58,$W:$W)>=$Q$27),Q58,IF(OR($AA$373>=$P$26,SUMIF($C:$C,C58,$W:$W)>=$P$27),P58,IF(OR($AA$373>=$O$26,SUMIF($C:$C,C58,$W:$W)>=$O$27),O58,IF(OR($AA$373>=$N$26,SUMIF($C:$C,C58,$W:$W)>=$N$27),N58,IF($AA$373>=$M$26,M58,L58)))))))*W58,0) -> 0 | AC58: =IFERROR(IF(V58="",0,(IF(AND(W58="",X58=""),"",IF(OR($AA$373>=$S$26,SUMIF($C:$C,C58,$W:$W)>=$S$27),S58*$E$13,IF(OR($AA$373>=$R$26,SUMIF($C:$C,C58,$W:$W)>=$R$27),R58*$E$13,IF(OR($AA$373>=$Q$26,SUMIF($C:$C,C58,$W:$W)>=$Q$27),Q58*$E$13,IF(OR($AA$373>=$P$26,SUMIF($C:$C,C58,$W:$W)>=$P$27),P58*$E$13,IF(OR($AA$373>=$O$26,SUMIF($C:$C,C58,$W:$W)>=$O$27),O58*$E$13,IF(OR($AA$373>=$N$26,SUMIF($C:$C,C58,$W:$W)>=$N$27),N58*$E$13,IF($AA$373>=$M$26,M58*$E$13,L58))))))))-V58)*W58),0) -> 0 | AD58: =IFERROR(X58*T58,0) -> 0 | AE58: =IFERROR(W58*H58,0) -> 0 | AF58: =IFERROR(1-(AE58/AB58),0) -> 0 | AG58: =IFERROR(SUM(W58:X58)*I58,0) -> 0 | AH58: =IFERROR(IF(V58>0,V58*W58,(Y58*W58)),0) -> 0 | AI58: =IFERROR(SUM(W58)*H58,0) -> 0 | AJ58: =AH58*$AJ$25 -> 0 | AK58: =AH58*AK$25 -> 0 | AL58: =AH58*AL$25 -> 0 | AM58: =SUM(AJ58:AL58) -> 0 | AN58: =AH58-AM58 -> 0 | AO58: =AN58-AI58 -> 0 | AP58: =IFERROR(IF(V58<>"",1-(H58/V58),IF(Y58<>"",1-(H58/Y58),1-(H58/L58))),0) -> 0.5438221 | AQ58: =H58/0.75 -> 102.29333 | AR58: 6 | AS58: =(AP58-MIN($AP$65:$AP$368))/(MAX($AP$65:$AP$368)-MIN($AP$65:$AP$368))*100 -> 54.38221 | AT58: =IFERROR(1-(AI58/AH58),0) -> 0 | AU58: =IFERROR(AO58/AH58,0) -> 0 | AW58: =VLOOKUP(AX58,Sup!#REF!,8,0) -> #REF! | AX58: Premium | AY58: 0 | BC58: =IF(BE58<0,BE58,0) -> 0 | BD58: =IFERROR(IF(AND(W58="",X58=""),"",IF(OR($AA$373>=$S$26,SUMIF($C:$C,C58,$W:$W)>=$S$27),S58,IF(OR($AA$373>=$R$26,SUMIF($C:$C,C58,$W:$W)>=$R$27),R58,IF(OR($AA$373>=$Q$26,SUMIF($C:$C,C58,$W:$W)>=$Q$27),Q58,IF(OR($AA$373>=$P$26,SUMIF($C:$C,C58,$W:$W)>=$P$27),P58,IF(OR($AA$373>=$O$26,SUMIF($C:$C,C58,$W:$W)>=$O$27),O58,IF(OR($AA$373>=$N$26,SUMIF($C:$C,C58,$W:$W)>=$N$27),N58,IF($AA$373>=$M$26,M58,L58)))))))*$E$13),0) | BE58: =IF(V58="",0,(V58*W58)-(BD58*W58)) -> 0 | BM58: =BM57+24 -> #REF! | BW58: EAT CLEAN | BX58: =IFERROR(W58*U58,0) -> 0 | BY58: =VLOOKUP(B58,#REF!,13,0) -> #REF! | BZ58: 136 | CA58: =VLOOKUP(B58,Pedido!$B$16:$L$292,22,0) -> #N/A | CD58: =CD57+12 -> 192 | CE58: =CD58/12 -> 16 | CF58: =CONCATENATE(CD58,CE58) -> 19216 | CG58: válido
B59: 9932709230 | C59: Pasta Castanha | D59: Pasta Castanha | E59: Integral | F59: Pote | G59: 300g | H59: 60.57 | I59: 239.4 | J59: =IFERROR(IF(T59<>"",I59/T59,IF(AND(Y59="",V59=""),"",IF(V59="",I59/Y59,I59/V59))),"") | K59: =IF(Y59="","",IFERROR(1-(Y59/I59),0)) | L59: 158.28 | M59: =P59 -> 129.9 | N59: =P59 -> 129.9 | O59: =P59 -> 129.9 | P59: 129.9 | Q59: 129.9 | R59: 129.9 | S59: 129.9 | T59: =IF(V59>0,V59,IFERROR(IF(AND(W59<>"",X59<>""),AH59/W59,Y59),"")) | U59: =IFERROR((T59*W59)/(W59+X59),"") | Y59: =IF(AND(W59="",X59=""),"",$E$13*IF(V59<>"",V59,IF(SUMIF($C:$C,C59,$W:$W)>=$S$27,S59,IF(OR($AA$373>=$R$26,SUMIF($C:$C,C59,$W:$W)>=$R$27),R59,IF(OR($AA$373>=$Q$26,SUMIF($C:$C,C59,$W:$W)>=$Q$27),Q59,IF(OR($AA$373>=$P$26,SUMIF($C:$C,C59,$W:$W)>=$P$27),P59,IF(OR($AA$373>=$O$26,SUMIF($C:$C,C59,$W:$W)>=$O$27),O59,IF(OR($AA$373>=$N$26,SUMIF($C:$C,C59,$W:$W)>=$N$27),N59,IF($AA$373>=$M$26,M59,L59))))))))) | Z59: =IF(X59>W59,-1,IF(W59=0,0,IF(U59<(H59/0.75),-1,IF(W59<=3,0,0.0001)))) -> 0 | AA59: =IFERROR(L59*W59,0) -> 0 | AB59: =IFERROR(IF(OR($AA$373>=$S$26,SUMIF($C:$C,C59,$W:$W)>=$S$27),S59,IF(OR($AA$373>=$R$26,SUMIF($C:$C,C59,$W:$W)>=$R$27),R59,IF(OR($AA$373>=$Q$26,SUMIF($C:$C,C59,$W:$W)>=$Q$27),Q59,IF(OR($AA$373>=$P$26,SUMIF($C:$C,C59,$W:$W)>=$P$27),P59,IF(OR($AA$373>=$O$26,SUMIF($C:$C,C59,$W:$W)>=$O$27),O59,IF(OR($AA$373>=$N$26,SUMIF($C:$C,C59,$W:$W)>=$N$27),N59,IF($AA$373>=$M$26,M59,L59)))))))*W59,0) -> 0 | AC59: =IFERROR(IF(V59="",0,(IF(AND(W59="",X59=""),"",IF(OR($AA$373>=$S$26,SUMIF($C:$C,C59,$W:$W)>=$S$27),S59*$E$13,IF(OR($AA$373>=$R$26,SUMIF($C:$C,C59,$W:$W)>=$R$27),R59*$E$13,IF(OR($AA$373>=$Q$26,SUMIF($C:$C,C59,$W:$W)>=$Q$27),Q59*$E$13,IF(OR($AA$373>=$P$26,SUMIF($C:$C,C59,$W:$W)>=$P$27),P59*$E$13,IF(OR($AA$373>=$O$26,SUMIF($C:$C,C59,$W:$W)>=$O$27),O59*$E$13,IF(OR($AA$373>=$N$26,SUMIF($C:$C,C59,$W:$W)>=$N$27),N59*$E$13,IF($AA$373>=$M$26,M59*$E$13,L59))))))))-V59)*W59),0) -> 0 | AD59: =IFERROR(X59*T59,0) -> 0 | AE59: =IFERROR(W59*H59,0) -> 0 | AF59: =IFERROR(1-(AE59/AB59),0) -> 0 | AG59: =IFERROR(SUM(W59:X59)*I59,0) -> 0 | AH59: =IFERROR(IF(V59>0,V59*W59,(Y59*W59)),0) -> 0 | AI59: =IFERROR(SUM(W59)*H59,0) -> 0 | AJ59: =AH59*$AJ$25 -> 0 | AK59: =AH59*AK$25 -> 0 | AL59: =AH59*AL$25 -> 0 | AM59: =SUM(AJ59:AL59) -> 0 | AN59: =AH59-AM59 -> 0 | AO59: =AN59-AI59 -> 0 | AP59: =IFERROR(IF(V59<>"",1-(H59/V59),IF(Y59<>"",1-(H59/Y59),1-(H59/L59))),0) -> 0.61732373 | AQ59: =H59/0.75 -> 80.76 | AR59: 6 | AS59: =(AP59-MIN($AP$65:$AP$368))/(MAX($AP$65:$AP$368)-MIN($AP$65:$AP$368))*100 -> 61.732373 | AT59: =IFERROR(1-(AI59/AH59),0) -> 0 | AU59: =IFERROR(AO59/AH59,0) -> 0 | AW59: =VLOOKUP(AX59,Sup!#REF!,8,0) -> #REF! | AX59: Premium | AY59: 0 | BC59: =IF(BE59<0,BE59,0) -> 0 | BD59: =IFERROR(IF(AND(W59="",X59=""),"",IF(OR($AA$373>=$S$26,SUMIF($C:$C,C59,$W:$W)>=$S$27),S59,IF(OR($AA$373>=$R$26,SUMIF($C:$C,C59,$W:$W)>=$R$27),R59,IF(OR($AA$373>=$Q$26,SUMIF($C:$C,C59,$W:$W)>=$Q$27),Q59,IF(OR($AA$373>=$P$26,SUMIF($C:$C,C59,$W:$W)>=$P$27),P59,IF(OR($AA$373>=$O$26,SUMIF($C:$C,C59,$W:$W)>=$O$27),O59,IF(OR($AA$373>=$N$26,SUMIF($C:$C,C59,$W:$W)>=$N$27),N59,IF($AA$373>=$M$26,M59,L59)))))))*$E$13),0) | BE59: =IF(V59="",0,(V59*W59)-(BD59*W59)) -> 0 | BM59: =BM58+24 -> #REF! | BW59: EAT CLEAN | BX59: =IFERROR(W59*U59,0) -> 0 | BY59: =VLOOKUP(B59,#REF!,13,0) -> #REF! | BZ59: 128 | CA59: =VLOOKUP(B59,Pedido!$B$16:$L$292,22,0) -> #N/A | CD59: =CD58+12 -> 204 | CE59: =CD59/12 -> 17 | CF59: =CONCATENATE(CD59,CE59) -> 20417 | CG59: válido
B60: 9932775189 | C60: Pasta Castanha | D60: Pasta Castanha | E60: Salted Caramel | F60: Pote | G60: 300g | H60: 63.32 | I60: 239.4 | J60: =IFERROR(IF(T60<>"",I60/T60,IF(AND(Y60="",V60=""),"",IF(V60="",I60/Y60,I60/V60))),"") | K60: =IF(Y60="","",IFERROR(1-(Y60/I60),0)) | L60: 168.18 | M60: =P60 -> 129.9 | N60: =P60 -> 129.9 | O60: =P60 -> 129.9 | P60: 129.9 | Q60: 129.9 | R60: 129.9 | S60: 129.9 | T60: =IF(V60>0,V60,IFERROR(IF(AND(W60<>"",X60<>""),AH60/W60,Y60),"")) | U60: =IFERROR((T60*W60)/(W60+X60),"") | Y60: =IF(AND(W60="",X60=""),"",$E$13*IF(V60<>"",V60,IF(SUMIF($C:$C,C60,$W:$W)>=$S$27,S60,IF(OR($AA$373>=$R$26,SUMIF($C:$C,C60,$W:$W)>=$R$27),R60,IF(OR($AA$373>=$Q$26,SUMIF($C:$C,C60,$W:$W)>=$Q$27),Q60,IF(OR($AA$373>=$P$26,SUMIF($C:$C,C60,$W:$W)>=$P$27),P60,IF(OR($AA$373>=$O$26,SUMIF($C:$C,C60,$W:$W)>=$O$27),O60,IF(OR($AA$373>=$N$26,SUMIF($C:$C,C60,$W:$W)>=$N$27),N60,IF($AA$373>=$M$26,M60,L60))))))))) | Z60: =IF(X60>W60,-1,IF(W60=0,0,IF(U60<(H60/0.75),-1,IF(W60<=3,0,0.0001)))) -> 0 | AA60: =IFERROR(L60*W60,0) -> 0 | AB60: =IFERROR(IF(OR($AA$373>=$S$26,SUMIF($C:$C,C60,$W:$W)>=$S$27),S60,IF(OR($AA$373>=$R$26,SUMIF($C:$C,C60,$W:$W)>=$R$27),R60,IF(OR($AA$373>=$Q$26,SUMIF($C:$C,C60,$W:$W)>=$Q$27),Q60,IF(OR($AA$373>=$P$26,SUMIF($C:$C,C60,$W:$W)>=$P$27),P60,IF(OR($AA$373>=$O$26,SUMIF($C:$C,C60,$W:$W)>=$O$27),O60,IF(OR($AA$373>=$N$26,SUMIF($C:$C,C60,$W:$W)>=$N$27),N60,IF($AA$373>=$M$26,M60,L60)))))))*W60,0) -> 0 | AC60: =IFERROR(IF(V60="",0,(IF(AND(W60="",X60=""),"",IF(OR($AA$373>=$S$26,SUMIF($C:$C,C60,$W:$W)>=$S$27),S60*$E$13,IF(OR($AA$373>=$R$26,SUMIF($C:$C,C60,$W:$W)>=$R$27),R60*$E$13,IF(OR($AA$373>=$Q$26,SUMIF($C:$C,C60,$W:$W)>=$Q$27),Q60*$E$13,IF(OR($AA$373>=$P$26,SUMIF($C:$C,C60,$W:$W)>=$P$27),P60*$E$13,IF(OR($AA$373>=$O$26,SUMIF($C:$C,C60,$W:$W)>=$O$27),O60*$E$13,IF(OR($AA$373>=$N$26,SUMIF($C:$C,C60,$W:$W)>=$N$27),N60*$E$13,IF($AA$373>=$M$26,M60*$E$13,L60))))))))-V60)*W60),0) -> 0 | AD60: =IFERROR(X60*T60,0) -> 0 | AE60: =IFERROR(W60*H60,0) -> 0 | AF60: =IFERROR(1-(AE60/AB60),0) -> 0 | AG60: =IFERROR(SUM(W60:X60)*I60,0) -> 0 | AH60: =IFERROR(IF(V60>0,V60*W60,(Y60*W60)),0) -> 0 | AI60: =IFERROR(SUM(W60)*H60,0) -> 0 | AJ60: =AH60*$AJ$25 -> 0 | AK60: =AH60*AK$25 -> 0 | AL60: =AH60*AL$25 -> 0 | AM60: =SUM(AJ60:AL60) -> 0 | AN60: =AH60-AM60 -> 0 | AO60: =AN60-AI60 -> 0 | AP60: =IFERROR(IF(V60<>"",1-(H60/V60),IF(Y60<>"",1-(H60/Y60),1-(H60/L60))),0) -> 0.62349863 | AQ60: =H60/0.75 -> 84.426667 | AR60: 6 | AS60: =(AP60-MIN($AP$65:$AP$368))/(MAX($AP$65:$AP$368)-MIN($AP$65:$AP$368))*100 -> 62.349863 | AT60: =IFERROR(1-(AI60/AH60),0) -> 0 | AU60: =IFERROR(AO60/AH60,0) -> 0 | AW60: =VLOOKUP(AX60,Sup!#REF!,8,0) -> #REF! | AX60: Premium | AY60: 0 | BC60: =IF(BE60<0,BE60,0) -> 0 | BD60: =IFERROR(IF(AND(W60="",X60=""),"",IF(OR($AA$373>=$S$26,SUMIF($C:$C,C60,$W:$W)>=$S$27),S60,IF(OR($AA$373>=$R$26,SUMIF($C:$C,C60,$W:$W)>=$R$27),R60,IF(OR($AA$373>=$Q$26,SUMIF($C:$C,C60,$W:$W)>=$Q$27),Q60,IF(OR($AA$373>=$P$26,SUMIF($C:$C,C60,$W:$W)>=$P$27),P60,IF(OR($AA$373>=$O$26,SUMIF($C:$C,C60,$W:$W)>=$O$27),O60,IF(OR($AA$373>=$N$26,SUMIF($C:$C,C60,$W:$W)>=$N$27),N60,IF($AA$373>=$M$26,M60,L60)))))))*$E$13),0) | BE60: =IF(V60="",0,(V60*W60)-(BD60*W60)) -> 0 | BM60: =BM59+24 -> #REF! | BW60: EAT CLEAN | BX60: =IFERROR(W60*U60,0) -> 0 | BY60: =VLOOKUP(B60,#REF!,13,0) -> #REF! | BZ60: 136 | CA60: =VLOOKUP(B60,Pedido!$B$16:$L$292,22,0) -> #N/A | CD60: =CD59+12 -> 216 | CE60: =CD60/12 -> 18 | CF60: =CONCATENATE(CD60,CE60) -> 21618 | CG60: válido
B61: XACGALFUM1875 | C61: =LEFT(B61,6) -> XACGAL | D61: Mini Galão | E61: Fumê | F61: Unissex | G61: 1875 | H61: 9.9 | I61: 39.9 | J61: =IFERROR(IF(T61<>"",I61/T61,IF(AND(Y61="",V61=""),"",IF(V61="",I61/Y61,I61/V61))),"") | K61: =IF(T61="","",IFERROR(1-(T61/I61),0)) | L61: 27.9 | M61: =P61 -> 23.9 | N61: =P61 -> 23.9 | O61: =P61 -> 23.9 | P61: 23.9 | Q61: 21.9 | R61: 20.9 | S61: 19.9 | T61: =IF(V61>0,V61,IFERROR(IF(AND(W61<>"",X61<>""),AH61/W61,Y61),"")) | U61: =IFERROR((T61*W61)/(W61+X61),"") | Y61: =IF(AND(W61="",X61=""),"",$E$13*IF(V61<>"",V61,IF(SUMIF($C:$C,C61,$W:$W)>=$S$27,S61,IF(OR($AA$373>=$R$26,SUMIF($C:$C,C61,$W:$W)>=$R$27),R61,IF(OR($AA$373>=$Q$26,SUMIF($C:$C,C61,$W:$W)>=$Q$27),Q61,IF(OR($AA$373>=$P$26,SUMIF($C:$C,C61,$W:$W)>=$P$27),P61,IF(OR($AA$373>=$O$26,SUMIF($C:$C,C61,$W:$W)>=$O$27),O61,IF(OR($AA$373>=$N$26,SUMIF($C:$C,C61,$W:$W)>=$N$27),N61,IF($AA$373>=$M$26,M61,L61))))))))) | Z61: =IF(X61>W61,-1,IF(W61=0,0,IF(U61<(H61/0.75),-1,IF(W61<=3,0,0.0001)))) -> 0 | AA61: =IFERROR(L61*W61,0) -> 0 | AB61: =IFERROR(IF(OR($AA$373>=$S$26,SUMIF($C:$C,C61,$W:$W)>=$S$27),S61,IF(OR($AA$373>=$R$26,SUMIF($C:$C,C61,$W:$W)>=$R$27),R61,IF(OR($AA$373>=$Q$26,SUMIF($C:$C,C61,$W:$W)>=$Q$27),Q61,IF(OR($AA$373>=$P$26,SUMIF($C:$C,C61,$W:$W)>=$P$27),P61,IF(OR($AA$373>=$O$26,SUMIF($C:$C,C61,$W:$W)>=$O$27),O61,IF(OR($AA$373>=$N$26,SUMIF($C:$C,C61,$W:$W)>=$N$27),N61,IF($AA$373>=$M$26,M61,L61)))))))*W61,0) -> 0 | AC61: =IFERROR(IF(V61="",0,(IF(AND(W61="",X61=""),"",IF(OR($AA$373>=$S$26,SUMIF($C:$C,C61,$W:$W)>=$S$27),S61*$E$13,IF(OR($AA$373>=$R$26,SUMIF($C:$C,C61,$W:$W)>=$R$27),R61*$E$13,IF(OR($AA$373>=$Q$26,SUMIF($C:$C,C61,$W:$W)>=$Q$27),Q61*$E$13,IF(OR($AA$373>=$P$26,SUMIF($C:$C,C61,$W:$W)>=$P$27),P61*$E$13,IF(OR($AA$373>=$O$26,SUMIF($C:$C,C61,$W:$W)>=$O$27),O61*$E$13,IF(OR($AA$373>=$N$26,SUMIF($C:$C,C61,$W:$W)>=$N$27),N61*$E$13,IF($AA$373>=$M$26,M61*$E$13,L61))))))))-V61)*W61),0) -> 0 | AD61: =IFERROR(X61*T61,0) -> 0 | AE61: =IFERROR(W61*H61,0) -> 0 | AF61: =IFERROR(1-(AE61/AB61),0) -> 0 | AG61: =IFERROR(SUM(W61:X61)*I61,0) -> 0 | AH61: =IFERROR(IF(V61>0,V61*W61,(Y61*W61)),0) -> 0 | AI61: =IFERROR(SUM(W61)*H61,0) -> 0 | AJ61: =AH61*$AJ$25 -> 0 | AK61: =AH61*AK$25 -> 0 | AL61: =AH61*AL$25 -> 0 | AM61: =SUM(AJ61:AL61) -> 0 | AN61: =AH61-AM61 -> 0 | AO61: =AN61-AI61 -> 0 | AP61: =IFERROR(IF(V61<>"",1-(H61/V61),IF(Y61<>"",1-(H61/Y61),1-(H61/L61))),0) -> 0.64516129 | AQ61: =H61/0.75 -> 13.2 | AR61: 5 | AS61: - | AT61: =IFERROR(1-(AI61/AH61),0) -> 0 | AU61: =IFERROR(AO61/AH61,0) -> 0 | AW61: =VLOOKUP(AX61,Sup!#REF!,8,0) -> #REF! | AX61: Standard | AY61: 0 | BC61: =IF(BE61<0,BE61,0) -> 0 | BD61: =IFERROR(IF(AND(W61="",X61=""),"",IF(OR($AA$373>=$S$26,SUMIF($C:$C,C61,$W:$W)>=$S$27),S61,IF(OR($AA$373>=$R$26,SUMIF($C:$C,C61,$W:$W)>=$R$27),R61,IF(OR($AA$373>=$Q$26,SUMIF($C:$C,C61,$W:$W)>=$Q$27),Q61,IF(OR($AA$373>=$P$26,SUMIF($C:$C,C61,$W:$W)>=$P$27),P61,IF(OR($AA$373>=$O$26,SUMIF($C:$C,C61,$W:$W)>=$O$27),O61,IF(OR($AA$373>=$N$26,SUMIF($C:$C,C61,$W:$W)>=$N$27),N61,IF($AA$373>=$M$26,M61,L61)))))))*$E$13),0) | BE61: =IF(V61="",0,(V61*W61)-(BD61*W61)) -> 0 | BW61: SPORT NUTRITION | BX61: =IFERROR(W61*U61,0) -> 0 | BY61: =VLOOKUP(B61,#REF!,13,0) -> #REF! | BZ61: 16.9 | CA61: =VLOOKUP(B61,Pedido!$B$16:$L$292,22,0) -> #N/A | CD61: =CD60+12 -> 228 | CE61: =CD61/12 -> 19 | CF61: =CONCATENATE(CD61,CE61) -> 22819 | CG61: válido
B62: XACCOQFUM0800 | C62: =LEFT(B62,6) -> XACCOQ | D62: Coqueteleira DUX | E62: Fumê | F62: Unissex | G62: 800 | H62: 5.45 | I62: 29.9 | J62: =IFERROR(IF(T62<>"",I62/T62,IF(AND(Y62="",V62=""),"",IF(V62="",I62/Y62,I62/V62))),"") | K62: =IF(T62="","",IFERROR(1-(T62/I62),0)) | L62: 21.9 | M62: =P62 -> 18.9 | N62: =P62 -> 18.9 | O62: =P62 -> 18.9 | P62: 18.9 | Q62: 16.9 | R62: 15.9 | S62: 14.9 | T62: =IF(V62>0,V62,IFERROR(IF(AND(W62<>"",X62<>""),AH62/W62,Y62),"")) | U62: =IFERROR((T62*W62)/(W62+X62),"") | Y62: =IF(AND(W62="",X62=""),"",$E$13*IF(V62<>"",V62,IF(SUMIF($C:$C,C62,$W:$W)>=$S$27,S62,IF(OR($AA$373>=$R$26,SUMIF($C:$C,C62,$W:$W)>=$R$27),R62,IF(OR($AA$373>=$Q$26,SUMIF($C:$C,C62,$W:$W)>=$Q$27),Q62,IF(OR($AA$373>=$P$26,SUMIF($C:$C,C62,$W:$W)>=$P$27),P62,IF(OR($AA$373>=$O$26,SUMIF($C:$C,C62,$W:$W)>=$O$27),O62,IF(OR($AA$373>=$N$26,SUMIF($C:$C,C62,$W:$W)>=$N$27),N62,IF($AA$373>=$M$26,M62,L62))))))))) | Z62: =IF(X62>W62,-1,IF(W62=0,0,IF(U62<(H62/0.75),-1,IF(W62<=3,0,0.0001)))) -> 0 | AA62: =IFERROR(L62*W62,0) -> 0 | AB62: =IFERROR(IF(OR($AA$373>=$S$26,SUMIF($C:$C,C62,$W:$W)>=$S$27),S62,IF(OR($AA$373>=$R$26,SUMIF($C:$C,C62,$W:$W)>=$R$27),R62,IF(OR($AA$373>=$Q$26,SUMIF($C:$C,C62,$W:$W)>=$Q$27),Q62,IF(OR($AA$373>=$P$26,SUMIF($C:$C,C62,$W:$W)>=$P$27),P62,IF(OR($AA$373>=$O$26,SUMIF($C:$C,C62,$W:$W)>=$O$27),O62,IF(OR($AA$373>=$N$26,SUMIF($C:$C,C62,$W:$W)>=$N$27),N62,IF($AA$373>=$M$26,M62,L62)))))))*W62,0) -> 0 | AC62: =IFERROR(IF(V62="",0,(IF(AND(W62="",X62=""),"",IF(OR($AA$373>=$S$26,SUMIF($C:$C,C62,$W:$W)>=$S$27),S62*$E$13,IF(OR($AA$373>=$R$26,SUMIF($C:$C,C62,$W:$W)>=$R$27),R62*$E$13,IF(OR($AA$373>=$Q$26,SUMIF($C:$C,C62,$W:$W)>=$Q$27),Q62*$E$13,IF(OR($AA$373>=$P$26,SUMIF($C:$C,C62,$W:$W)>=$P$27),P62*$E$13,IF(OR($AA$373>=$O$26,SUMIF($C:$C,C62,$W:$W)>=$O$27),O62*$E$13,IF(OR($AA$373>=$N$26,SUMIF($C:$C,C62,$W:$W)>=$N$27),N62*$E$13,IF($AA$373>=$M$26,M62*$E$13,L62))))))))-V62)*W62),0) -> 0 | AD62: =IFERROR(X62*T62,0) -> 0 | AE62: =IFERROR(W62*H62,0) -> 0 | AF62: =IFERROR(1-(AE62/AB62),0) -> 0 | AG62: =IFERROR(SUM(W62:X62)*I62,0) -> 0 | AH62: =IFERROR(IF(V62>0,V62*W62,(Y62*W62)),0) -> 0 | AI62: =IFERROR(SUM(W62)*H62,0) -> 0 | AJ62: =AH62*$AJ$25 -> 0 | AK62: =AH62*AK$25 -> 0 | AL62: =AH62*AL$25 -> 0 | AM62: =SUM(AJ62:AL62) -> 0 | AN62: =AH62-AM62 -> 0 | AO62: =AN62-AI62 -> 0 | AP62: =IFERROR(IF(V62<>"",1-(H62/V62),IF(Y62<>"",1-(H62/Y62),1-(H62/L62))),0) -> 0.75114155 | AQ62: =H62/0.75 -> 7.2666667 | AR62: 12 | AS62: - | AT62: =IFERROR(1-(AI62/AH62),0) -> 0 | AU62: =IFERROR(AO62/AH62,0) -> 0 | AW62: =VLOOKUP(AX62,Sup!#REF!,8,0) -> #REF! | AX62: Standard | AY62: 0 | BC62: =IF(BE62<0,BE62,0) -> 0 | BD62: =IFERROR(IF(AND(W62="",X62=""),"",IF(OR($AA$373>=$S$26,SUMIF($C:$C,C62,$W:$W)>=$S$27),S62,IF(OR($AA$373>=$R$26,SUMIF($C:$C,C62,$W:$W)>=$R$27),R62,IF(OR($AA$373>=$Q$26,SUMIF($C:$C,C62,$W:$W)>=$Q$27),Q62,IF(OR($AA$373>=$P$26,SUMIF($C:$C,C62,$W:$W)>=$P$27),P62,IF(OR($AA$373>=$O$26,SUMIF($C:$C,C62,$W:$W)>=$O$27),O62,IF(OR($AA$373>=$N$26,SUMIF($C:$C,C62,$W:$W)>=$N$27),N62,IF($AA$373>=$M$26,M62,L62)))))))*$E$13),0) | BE62: =IF(V62="",0,(V62*W62)-(BD62*W62)) -> 0 | BW62: SPORT NUTRITION | BX62: =IFERROR(W62*U62,0) -> 0 | BY62: =VLOOKUP(B62,#REF!,13,0) -> #REF! | BZ62: 11.9 | CA62: =VLOOKUP(B62,Pedido!$B$16:$L$292,22,0) -> #N/A | CD62: =CD61+12 -> 240 | CE62: =CD62/12 -> 20 | CF62: =CONCATENATE(CD62,CE62) -> 24020 | CG62: válido
B63: XACSQZPRB0800 | C63: =LEFT(B63,6) -> XACSQZ | D63: Squeeze automático | E63: Prata | F63: Unissex | G63: 800 | H63: 4.38 | I63: 21.9 | J63: =IFERROR(IF(T63<>"",I63/T63,IF(AND(Y63="",V63=""),"",IF(V63="",I63/Y63,I63/V63))),"") | K63: =IF(T63="","",IFERROR(1-(T63/I63),0)) | L63: 15.9 | M63: =P63 -> 13.9 | N63: =P63 -> 13.9 | O63: =P63 -> 13.9 | P63: 13.9 | Q63: 12.9 | R63: 11.9 | S63: 10.9 | T63: =IF(V63>0,V63,IFERROR(IF(AND(W63<>"",X63<>""),AH63/W63,Y63),"")) | U63: =IFERROR((T63*W63)/(W63+X63),"") | Y63: =IF(AND(W63="",X63=""),"",$E$13*IF(V63<>"",V63,IF(SUMIF($C:$C,C63,$W:$W)>=$S$27,S63,IF(OR($AA$373>=$R$26,SUMIF($C:$C,C63,$W:$W)>=$R$27),R63,IF(OR($AA$373>=$Q$26,SUMIF($C:$C,C63,$W:$W)>=$Q$27),Q63,IF(OR($AA$373>=$P$26,SUMIF($C:$C,C63,$W:$W)>=$P$27),P63,IF(OR($AA$373>=$O$26,SUMIF($C:$C,C63,$W:$W)>=$O$27),O63,IF(OR($AA$373>=$N$26,SUMIF($C:$C,C63,$W:$W)>=$N$27),N63,IF($AA$373>=$M$26,M63,L63))))))))) | Z63: =IF(X63>W63,-1,IF(W63=0,0,IF(U63<(H63/0.75),-1,IF(W63<=3,0,0.0001)))) -> 0 | AA63: =IFERROR(L63*W63,0) -> 0 | AB63: =IFERROR(IF(OR($AA$373>=$S$26,SUMIF($C:$C,C63,$W:$W)>=$S$27),S63,IF(OR($AA$373>=$R$26,SUMIF($C:$C,C63,$W:$W)>=$R$27),R63,IF(OR($AA$373>=$Q$26,SUMIF($C:$C,C63,$W:$W)>=$Q$27),Q63,IF(OR($AA$373>=$P$26,SUMIF($C:$C,C63,$W:$W)>=$P$27),P63,IF(OR($AA$373>=$O$26,SUMIF($C:$C,C63,$W:$W)>=$O$27),O63,IF(OR($AA$373>=$N$26,SUMIF($C:$C,C63,$W:$W)>=$N$27),N63,IF($AA$373>=$M$26,M63,L63)))))))*W63,0) -> 0 | AC63: =IFERROR(IF(V63="",0,(IF(AND(W63="",X63=""),"",IF(OR($AA$373>=$S$26,SUMIF($C:$C,C63,$W:$W)>=$S$27),S63*$E$13,IF(OR($AA$373>=$R$26,SUMIF($C:$C,C63,$W:$W)>=$R$27),R63*$E$13,IF(OR($AA$373>=$Q$26,SUMIF($C:$C,C63,$W:$W)>=$Q$27),Q63*$E$13,IF(OR($AA$373>=$P$26,SUMIF($C:$C,C63,$W:$W)>=$P$27),P63*$E$13,IF(OR($AA$373>=$O$26,SUMIF($C:$C,C63,$W:$W)>=$O$27),O63*$E$13,IF(OR($AA$373>=$N$26,SUMIF($C:$C,C63,$W:$W)>=$N$27),N63*$E$13,IF($AA$373>=$M$26,M63*$E$13,L63))))))))-V63)*W63),0) -> 0 | AD63: =IFERROR(X63*T63,0) -> 0 | AE63: =IFERROR(W63*H63,0) -> 0 | AF63: =IFERROR(1-(AE63/AB63),0) -> 0 | AG63: =IFERROR(SUM(W63:X63)*I63,0) -> 0 | AH63: =IFERROR(IF(V63>0,V63*W63,(Y63*W63)),0) -> 0 | AI63: =IFERROR(SUM(W63)*H63,0) -> 0 | AJ63: =AH63*$AJ$25 -> 0 | AK63: =AH63*AK$25 -> 0 | AL63: =AH63*AL$25 -> 0 | AM63: =SUM(AJ63:AL63) -> 0 | AN63: =AH63-AM63 -> 0 | AO63: =AN63-AI63 -> 0 | AP63: =IFERROR(IF(V63<>"",1-(H63/V63),IF(Y63<>"",1-(H63/Y63),1-(H63/L63))),0) -> 0.7245283 | AQ63: =H63/0.75 -> 5.84 | AR63: - | AS63: - | AT63: =IFERROR(1-(AI63/AH63),0) -> 0 | AU63: =IFERROR(AO63/AH63,0) -> 0 | AW63: =VLOOKUP(AX63,Sup!#REF!,8,0) -> #REF! | AX63: Standard | AY63: 0 | BC63: =IF(BE63<0,BE63,0) -> 0 | BD63: =IFERROR(IF(AND(W63="",X63=""),"",IF(OR($AA$373>=$S$26,SUMIF($C:$C,C63,$W:$W)>=$S$27),S63,IF(OR($AA$373>=$R$26,SUMIF($C:$C,C63,$W:$W)>=$R$27),R63,IF(OR($AA$373>=$Q$26,SUMIF($C:$C,C63,$W:$W)>=$Q$27),Q63,IF(OR($AA$373>=$P$26,SUMIF($C:$C,C63,$W:$W)>=$P$27),P63,IF(OR($AA$373>=$O$26,SUMIF($C:$C,C63,$W:$W)>=$O$27),O63,IF(OR($AA$373>=$N$26,SUMIF($C:$C,C63,$W:$W)>=$N$27),N63,IF($AA$373>=$M$26,M63,L63)))))))*$E$13),0) | BE63: =IF(V63="",0,(V63*W63)-(BD63*W63)) -> 0 | BW63: SPORT NUTRITION | BX63: =IFERROR(W63*U63,0) -> 0 | BY63: =VLOOKUP(B63,#REF!,13,0) -> #REF! | BZ63: 9.9 | CA63: =VLOOKUP(B63,Pedido!$B$16:$L$292,22,0) -> #N/A
B64: XACSQZPTB0800 | C64: =LEFT(B64,6) -> XACSQZ | D64: Squeeze automático | E64: Preto | F64: Unissex | G64: 800 | H64: 4.38 | I64: 21.9 | J64: =IFERROR(IF(T64<>"",I64/T64,IF(AND(Y64="",V64=""),"",IF(V64="",I64/Y64,I64/V64))),"") | K64: =IF(T64="","",IFERROR(1-(T64/I64),0)) | L64: 15.9 | M64: =P64 -> 13.9 | N64: =P64 -> 13.9 | O64: =P64 -> 13.9 | P64: 13.9 | Q64: 12.9 | R64: 11.9 | S64: 10.9 | T64: =IF(V64>0,V64,IFERROR(IF(AND(W64<>"",X64<>""),AH64/W64,Y64),"")) | U64: =IFERROR((T64*W64)/(W64+X64),"") | Y64: =IF(AND(W64="",X64=""),"",$E$13*IF(V64<>"",V64,IF(SUMIF($C:$C,C64,$W:$W)>=$S$27,S64,IF(OR($AA$373>=$R$26,SUMIF($C:$C,C64,$W:$W)>=$R$27),R64,IF(OR($AA$373>=$Q$26,SUMIF($C:$C,C64,$W:$W)>=$Q$27),Q64,IF(OR($AA$373>=$P$26,SUMIF($C:$C,C64,$W:$W)>=$P$27),P64,IF(OR($AA$373>=$O$26,SUMIF($C:$C,C64,$W:$W)>=$O$27),O64,IF(OR($AA$373>=$N$26,SUMIF($C:$C,C64,$W:$W)>=$N$27),N64,IF($AA$373>=$M$26,M64,L64))))))))) | Z64: =IF(X64>W64,-1,IF(W64=0,0,IF(U64<(H64/0.75),-1,IF(W64<=3,0,0.0001)))) -> 0 | AA64: =IFERROR(L64*W64,0) -> 0 | AB64: =IFERROR(IF(OR($AA$373>=$S$26,SUMIF($C:$C,C64,$W:$W)>=$S$27),S64,IF(OR($AA$373>=$R$26,SUMIF($C:$C,C64,$W:$W)>=$R$27),R64,IF(OR($AA$373>=$Q$26,SUMIF($C:$C,C64,$W:$W)>=$Q$27),Q64,IF(OR($AA$373>=$P$26,SUMIF($C:$C,C64,$W:$W)>=$P$27),P64,IF(OR($AA$373>=$O$26,SUMIF($C:$C,C64,$W:$W)>=$O$27),O64,IF(OR($AA$373>=$N$26,SUMIF($C:$C,C64,$W:$W)>=$N$27),N64,IF($AA$373>=$M$26,M64,L64)))))))*W64,0) -> 0 | AC64: =IFERROR(IF(V64="",0,(IF(AND(W64="",X64=""),"",IF(OR($AA$373>=$S$26,SUMIF($C:$C,C64,$W:$W)>=$S$27),S64*$E$13,IF(OR($AA$373>=$R$26,SUMIF($C:$C,C64,$W:$W)>=$R$27),R64*$E$13,IF(OR($AA$373>=$Q$26,SUMIF($C:$C,C64,$W:$W)>=$Q$27),Q64*$E$13,IF(OR($AA$373>=$P$26,SUMIF($C:$C,C64,$W:$W)>=$P$27),P64*$E$13,IF(OR($AA$373>=$O$26,SUMIF($C:$C,C64,$W:$W)>=$O$27),O64*$E$13,IF(OR($AA$373>=$N$26,SUMIF($C:$C,C64,$W:$W)>=$N$27),N64*$E$13,IF($AA$373>=$M$26,M64*$E$13,L64))))))))-V64)*W64),0) -> 0 | AD64: =IFERROR(X64*T64,0) -> 0 | AE64: =IFERROR(W64*H64,0) -> 0 | AF64: =IFERROR(1-(AE64/AB64),0) -> 0 | AG64: =IFERROR(SUM(W64:X64)*I64,0) -> 0 | AH64: =IFERROR(IF(V64>0,V64*W64,(Y64*W64)),0) -> 0 | AI64: =IFERROR(SUM(W64)*H64,0) -> 0 | AJ64: =AH64*$AJ$25 -> 0 | AK64: =AH64*AK$25 -> 0 | AL64: =AH64*AL$25 -> 0 | AM64: =SUM(AJ64:AL64) -> 0 | AN64: =AH64-AM64 -> 0 | AO64: =AN64-AI64 -> 0 | AP64: =IFERROR(IF(V64<>"",1-(H64/V64),IF(Y64<>"",1-(H64/Y64),1-(H64/L64))),0) -> 0.7245283 | AQ64: =H64/0.75 -> 5.84 | AR64: - | AS64: - | AT64: =IFERROR(1-(AI64/AH64),0) -> 0 | AU64: =IFERROR(AO64/AH64,0) -> 0 | AW64: =VLOOKUP(AX64,Sup!#REF!,8,0) -> #REF! | AX64: Standard | AY64: 0 | BC64: =IF(BE64<0,BE64,0) -> 0 | BD64: =IFERROR(IF(AND(W64="",X64=""),"",IF(OR($AA$373>=$S$26,SUMIF($C:$C,C64,$W:$W)>=$S$27),S64,IF(OR($AA$373>=$R$26,SUMIF($C:$C,C64,$W:$W)>=$R$27),R64,IF(OR($AA$373>=$Q$26,SUMIF($C:$C,C64,$W:$W)>=$Q$27),Q64,IF(OR($AA$373>=$P$26,SUMIF($C:$C,C64,$W:$W)>=$P$27),P64,IF(OR($AA$373>=$O$26,SUMIF($C:$C,C64,$W:$W)>=$O$27),O64,IF(OR($AA$373>=$N$26,SUMIF($C:$C,C64,$W:$W)>=$N$27),N64,IF($AA$373>=$M$26,M64,L64)))))))*$E$13),0) | BE64: =IF(V64="",0,(V64*W64)-(BD64*W64)) -> 0 | BW64: SPORT NUTRITION | BX64: =IFERROR(W64*U64,0) -> 0 | BY64: =VLOOKUP(B64,#REF!,13,0) -> #REF! | BZ64: 9.9 | CA64: =VLOOKUP(B64,Pedido!$B$16:$L$292,22,0) -> #N/A
B65: PCPB21SSB0100 | C65: =LEFT(B65,6) -> PCPB21 | D65: BCAA 3500 | E65: Sem Sabor | F65: Pote | G65: 100 | H65: 18.09 | I65: 74.9 | J65: =IFERROR(IF(T65<>"",I65/T65,IF(AND(Y65="",V65=""),"",IF(V65="",I65/Y65,I65/V65))),"") | K65: =IF(T65="","",IFERROR(1-(T65/I65),0)) | L65: 53.9 | M65: =P65 -> 46.9 | N65: =P65 -> 46.9 | O65: =P65 -> 46.9 | P65: 46.9 | Q65: 42.9 | R65: 41.9 | S65: 39.9 | T65: =IF(V65>0,V65,IFERROR(IF(AND(W65<>"",X65<>""),AH65/W65,Y65),"")) | U65: =IFERROR((T65*W65)/(W65+X65),"") | Y65: =IF(AND(W65="",X65=""),"",$E$13*IF(V65<>"",V65,IF(SUMIF($C:$C,C65,$W:$W)>=$S$27,S65,IF(OR($AA$373>=$R$26,SUMIF($C:$C,C65,$W:$W)>=$R$27),R65,IF(OR($AA$373>=$Q$26,SUMIF($C:$C,C65,$W:$W)>=$Q$27),Q65,IF(OR($AA$373>=$P$26,SUMIF($C:$C,C65,$W:$W)>=$P$27),P65,IF(OR($AA$373>=$O$26,SUMIF($C:$C,C65,$W:$W)>=$O$27),O65,IF(OR($AA$373>=$N$26,SUMIF($C:$C,C65,$W:$W)>=$N$27),N65,IF($AA$373>=$M$26,M65,L65))))))))) | Z65: =IF(X65>W65,-1,IF(W65=0,0,IF(U65<(H65/0.75),-1,IF(W65<=3,0,0.0001)))) -> 0 | AA65: =IFERROR(L65*W65,0) -> 0 | AB65: =IFERROR(IF(OR($AA$373>=$S$26,SUMIF($C:$C,C65,$W:$W)>=$S$27),S65,IF(OR($AA$373>=$R$26,SUMIF($C:$C,C65,$W:$W)>=$R$27),R65,IF(OR($AA$373>=$Q$26,SUMIF($C:$C,C65,$W:$W)>=$Q$27),Q65,IF(OR($AA$373>=$P$26,SUMIF($C:$C,C65,$W:$W)>=$P$27),P65,IF(OR($AA$373>=$O$26,SUMIF($C:$C,C65,$W:$W)>=$O$27),O65,IF(OR($AA$373>=$N$26,SUMIF($C:$C,C65,$W:$W)>=$N$27),N65,IF($AA$373>=$M$26,M65,L65)))))))*W65,0) -> 0 | AC65: =IFERROR(IF(V65="",0,(IF(AND(W65="",X65=""),"",IF(OR($AA$373>=$S$26,SUMIF($C:$C,C65,$W:$W)>=$S$27),S65*$E$13,IF(OR($AA$373>=$R$26,SUMIF($C:$C,C65,$W:$W)>=$R$27),R65*$E$13,IF(OR($AA$373>=$Q$26,SUMIF($C:$C,C65,$W:$W)>=$Q$27),Q65*$E$13,IF(OR($AA$373>=$P$26,SUMIF($C:$C,C65,$W:$W)>=$P$27),P65*$E$13,IF(OR($AA$373>=$O$26,SUMIF($C:$C,C65,$W:$W)>=$O$27),O65*$E$13,IF(OR($AA$373>=$N$26,SUMIF($C:$C,C65,$W:$W)>=$N$27),N65*$E$13,IF($AA$373>=$M$26,M65*$E$13,L65))))))))-V65)*W65),0) -> 0 | AD65: =IFERROR(X65*T65,0) -> 0 | AE65: =IFERROR(W65*H65,0) -> 0 | AF65: =IFERROR(1-(AE65/AB65),0) -> 0 | AG65: =IFERROR(SUM(W65:X65)*I65,0) -> 0 | AH65: =IFERROR(IF(V65>0,V65*W65,(Y65*W65)),0) -> 0 | AI65: =IFERROR(SUM(W65)*H65,0) -> 0 | AJ65: =AH65*$AJ$25 -> 0 | AK65: =AH65*AK$25 -> 0 | AL65: =AH65*AL$25 -> 0 | AM65: =SUM(AJ65:AL65) -> 0 | AN65: =AH65-AM65 -> 0 | AO65: =AN65-AI65 -> 0 | AP65: =IFERROR(IF(V65<>"",1-(H65/V65),IF(Y65<>"",1-(H65/Y65),1-(H65/L65))),0) -> 0.66437848 | AQ65: =H65/0.75 -> 24.12 | AR65: 24 | AS65: =(AP65-MIN($AP$65:$AP$368))/(MAX($AP$65:$AP$368)-MIN($AP$65:$AP$368))*100 -> 66.437848 | AT65: =IFERROR(1-(AI65/AH65),0) -> 0 | AU65: =IFERROR(AO65/AH65,0) -> 0 | AW65: =VLOOKUP(AX65,Sup!#REF!,8,0) -> #REF! | AX65: Standard | AY65: 0 | BC65: =IF(BE65<0,BE65,0) -> 0 | BD65: =IFERROR(IF(AND(W65="",X65=""),"",IF(OR($AA$373>=$S$26,SUMIF($C:$C,C65,$W:$W)>=$S$27),S65,IF(OR($AA$373>=$R$26,SUMIF($C:$C,C65,$W:$W)>=$R$27),R65,IF(OR($AA$373>=$Q$26,SUMIF($C:$C,C65,$W:$W)>=$Q$27),Q65,IF(OR($AA$373>=$P$26,SUMIF($C:$C,C65,$W:$W)>=$P$27),P65,IF(OR($AA$373>=$O$26,SUMIF($C:$C,C65,$W:$W)>=$O$27),O65,IF(OR($AA$373>=$N$26,SUMIF($C:$C,C65,$W:$W)>=$N$27),N65,IF($AA$373>=$M$26,M65,L65)))))))*$E$13),0) | BE65: =IF(V65="",0,(V65*W65)-(BD65*W65)) -> 0 | BW65: SPORT NUTRITION | BX65: =IFERROR(W65*U65,0) -> 0 | BY65: =VLOOKUP(B65,#REF!,13,0) -> #REF! | BZ65: 29.9 | CA65: =VLOOKUP(B65,Pedido!$B$16:$L$292,22,0) -> #N/A
B66: PPOB41ABA0200 | C66: =LEFT(B66,6) -> PPOB41 | D66: BCAA Powder | E66: Abacaxi | F66: Pote | G66: 200 | H66: 14.23 | I66: 99.9 | J66: =IFERROR(IF(T66<>"",I66/T66,IF(AND(Y66="",V66=""),"",IF(V66="",I66/Y66,I66/V66))),"") | K66: =IF(T66="","",IFERROR(1-(T66/I66),0)) | L66: 68.9 | M66: =P66 -> 60.9 | N66: =P66 -> 60.9 | O66: =P66 -> 60.9 | P66: 60.9 | Q66: 55.9 | R66: 54.9 | S66: 52.9 | T66: =IF(V66>0,V66,IFERROR(IF(AND(W66<>"",X66<>""),AH66/W66,Y66),"")) | U66: =IFERROR((T66*W66)/(W66+X66),"") | Y66: =IF(AND(W66="",X66=""),"",$E$13*IF(V66<>"",V66,IF(SUMIF($C:$C,C66,$W:$W)>=$S$27,S66,IF(OR($AA$373>=$R$26,SUMIF($C:$C,C66,$W:$W)>=$R$27),R66,IF(OR($AA$373>=$Q$26,SUMIF($C:$C,C66,$W:$W)>=$Q$27),Q66,IF(OR($AA$373>=$P$26,SUMIF($C:$C,C66,$W:$W)>=$P$27),P66,IF(OR($AA$373>=$O$26,SUMIF($C:$C,C66,$W:$W)>=$O$27),O66,IF(OR($AA$373>=$N$26,SUMIF($C:$C,C66,$W:$W)>=$N$27),N66,IF($AA$373>=$M$26,M66,L66))))))))) | Z66: =IF(X66>W66,-1,IF(W66=0,0,IF(U66<(H66/0.75),-1,IF(W66<=3,0,0.0001)))) -> 0 | AA66: =IFERROR(L66*W66,0) -> 0 | AB66: =IFERROR(IF(OR($AA$373>=$S$26,SUMIF($C:$C,C66,$W:$W)>=$S$27),S66,IF(OR($AA$373>=$R$26,SUMIF($C:$C,C66,$W:$W)>=$R$27),R66,IF(OR($AA$373>=$Q$26,SUMIF($C:$C,C66,$W:$W)>=$Q$27),Q66,IF(OR($AA$373>=$P$26,SUMIF($C:$C,C66,$W:$W)>=$P$27),P66,IF(OR($AA$373>=$O$26,SUMIF($C:$C,C66,$W:$W)>=$O$27),O66,IF(OR($AA$373>=$N$26,SUMIF($C:$C,C66,$W:$W)>=$N$27),N66,IF($AA$373>=$M$26,M66,L66)))))))*W66,0) -> 0 | AC66: =IFERROR(IF(V66="",0,(IF(AND(W66="",X66=""),"",IF(OR($AA$373>=$S$26,SUMIF($C:$C,C66,$W:$W)>=$S$27),S66*$E$13,IF(OR($AA$373>=$R$26,SUMIF($C:$C,C66,$W:$W)>=$R$27),R66*$E$13,IF(OR($AA$373>=$Q$26,SUMIF($C:$C,C66,$W:$W)>=$Q$27),Q66*$E$13,IF(OR($AA$373>=$P$26,SUMIF($C:$C,C66,$W:$W)>=$P$27),P66*$E$13,IF(OR($AA$373>=$O$26,SUMIF($C:$C,C66,$W:$W)>=$O$27),O66*$E$13,IF(OR($AA$373>=$N$26,SUMIF($C:$C,C66,$W:$W)>=$N$27),N66*$E$13,IF($AA$373>=$M$26,M66*$E$13,L66))))))))-V66)*W66),0) -> 0 | AD66: =IFERROR(X66*T66,0) -> 0 | AE66: =IFERROR(W66*H66,0) -> 0 | AF66: =IFERROR(1-(AE66/AB66),0) -> 0 | AG66: =IFERROR(SUM(W66:X66)*I66,0) -> 0 | AH66: =IFERROR(IF(V66>0,V66*W66,(Y66*W66)),0) -> 0 | AI66: =IFERROR(SUM(W66)*H66,0) -> 0 | AJ66: =AH66*$AJ$25 -> 0 | AK66: =AH66*AK$25 -> 0 | AL66: =AH66*AL$25 -> 0 | AM66: =SUM(AJ66:AL66) -> 0 | AN66: =AH66-AM66 -> 0 | AO66: =AN66-AI66 -> 0 | AP66: =IFERROR(IF(V66<>"",1-(H66/V66),IF(Y66<>"",1-(H66/Y66),1-(H66/L66))),0) -> 0.7934688 | AQ66: =H66/0.75 -> 18.973333 | AR66: 14 | AS66: =(AP66-MIN($AP$65:$AP$368))/(MAX($AP$65:$AP$368)-MIN($AP$65:$AP$368))*100 -> 79.34688 | AT66: =IFERROR(1-(AI66/AH66),0) -> 0 | AU66: =IFERROR(AO66/AH66,0) -> 0 | AW66: =VLOOKUP(AX66,Sup!#REF!,8,0) -> #REF! | AX66: Standard | AY66: 0 | BB66: =IF($F$14="NOVO/REATIVAÇÃO",10*W66*1.4,10*W66) -> 0 | BC66: =IF(BE66<0,BE66,0) -> 0 | BD66: =IFERROR(IF(AND(W66="",X66=""),"",IF(OR($AA$373>=$S$26,SUMIF($C:$C,C66,$W:$W)>=$S$27),S66,IF(OR($AA$373>=$R$26,SUMIF($C:$C,C66,$W:$W)>=$R$27),R66,IF(OR($AA$373>=$Q$26,SUMIF($C:$C,C66,$W:$W)>=$Q$27),Q66,IF(OR($AA$373>=$P$26,SUMIF($C:$C,C66,$W:$W)>=$P$27),P66,IF(OR($AA$373>=$O$26,SUMIF($C:$C,C66,$W:$W)>=$O$27),O66,IF(OR($AA$373>=$N$26,SUMIF($C:$C,C66,$W:$W)>=$N$27),N66,IF($AA$373>=$M$26,M66,L66)))))))*$E$13),0) | BE66: =IF(V66="",0,(V66*W66)-(BD66*W66)) -> 0 | BW66: SPORT NUTRITION | BX66: =IFERROR(W66*U66,0) -> 0 | BY66: =VLOOKUP(B66,#REF!,13,0) -> #REF! | BZ66: 39.9 | CA66: =VLOOKUP(B66,Pedido!$B$16:$L$292,22,0) -> #N/A
B67: PPOB41LAR0200 | C67: =LEFT(B67,6) -> PPOB41 | D67: BCAA Powder | E67: Laranja | F67: Pote | G67: 200 | H67: 14.23 | I67: 99.9 | J67: =IFERROR(IF(T67<>"",I67/T67,IF(AND(Y67="",V67=""),"",IF(V67="",I67/Y67,I67/V67))),"") | K67: =IF(T67="","",IFERROR(1-(T67/I67),0)) | L67: 68.9 | M67: =P67 -> 60.9 | N67: =P67 -> 60.9 | O67: =P67 -> 60.9 | P67: 60.9 | Q67: 55.9 | R67: 54.9 | S67: 52.9 | T67: =IF(V67>0,V67,IFERROR(IF(AND(W67<>"",X67<>""),AH67/W67,Y67),"")) | U67: =IFERROR((T67*W67)/(W67+X67),"") | Y67: =IF(AND(W67="",X67=""),"",$E$13*IF(V67<>"",V67,IF(SUMIF($C:$C,C67,$W:$W)>=$S$27,S67,IF(OR($AA$373>=$R$26,SUMIF($C:$C,C67,$W:$W)>=$R$27),R67,IF(OR($AA$373>=$Q$26,SUMIF($C:$C,C67,$W:$W)>=$Q$27),Q67,IF(OR($AA$373>=$P$26,SUMIF($C:$C,C67,$W:$W)>=$P$27),P67,IF(OR($AA$373>=$O$26,SUMIF($C:$C,C67,$W:$W)>=$O$27),O67,IF(OR($AA$373>=$N$26,SUMIF($C:$C,C67,$W:$W)>=$N$27),N67,IF($AA$373>=$M$26,M67,L67))))))))) | Z67: =IF(X67>W67,-1,IF(W67=0,0,IF(U67<(H67/0.75),-1,IF(W67<=3,0,0.0001)))) -> 0 | AA67: =IFERROR(L67*W67,0) -> 0 | AB67: =IFERROR(IF(OR($AA$373>=$S$26,SUMIF($C:$C,C67,$W:$W)>=$S$27),S67,IF(OR($AA$373>=$R$26,SUMIF($C:$C,C67,$W:$W)>=$R$27),R67,IF(OR($AA$373>=$Q$26,SUMIF($C:$C,C67,$W:$W)>=$Q$27),Q67,IF(OR($AA$373>=$P$26,SUMIF($C:$C,C67,$W:$W)>=$P$27),P67,IF(OR($AA$373>=$O$26,SUMIF($C:$C,C67,$W:$W)>=$O$27),O67,IF(OR($AA$373>=$N$26,SUMIF($C:$C,C67,$W:$W)>=$N$27),N67,IF($AA$373>=$M$26,M67,L67)))))))*W67,0) -> 0 | AC67: =IFERROR(IF(V67="",0,(IF(AND(W67="",X67=""),"",IF(OR($AA$373>=$S$26,SUMIF($C:$C,C67,$W:$W)>=$S$27),S67*$E$13,IF(OR($AA$373>=$R$26,SUMIF($C:$C,C67,$W:$W)>=$R$27),R67*$E$13,IF(OR($AA$373>=$Q$26,SUMIF($C:$C,C67,$W:$W)>=$Q$27),Q67*$E$13,IF(OR($AA$373>=$P$26,SUMIF($C:$C,C67,$W:$W)>=$P$27),P67*$E$13,IF(OR($AA$373>=$O$26,SUMIF($C:$C,C67,$W:$W)>=$O$27),O67*$E$13,IF(OR($AA$373>=$N$26,SUMIF($C:$C,C67,$W:$W)>=$N$27),N67*$E$13,IF($AA$373>=$M$26,M67*$E$13,L67))))))))-V67)*W67),0) -> 0 | AD67: =IFERROR(X67*T67,0) -> 0 | AE67: =IFERROR(W67*H67,0) -> 0 | AF67: =IFERROR(1-(AE67/AB67),0) -> 0 | AG67: =IFERROR(SUM(W67:X67)*I67,0) -> 0 | AH67: =IFERROR(IF(V67>0,V67*W67,(Y67*W67)),0) -> 0 | AI67: =IFERROR(SUM(W67)*H67,0) -> 0 | AJ67: =AH67*$AJ$25 -> 0 | AK67: =AH67*AK$25 -> 0 | AL67: =AH67*AL$25 -> 0 | AM67: =SUM(AJ67:AL67) -> 0 | AN67: =AH67-AM67 -> 0 | AO67: =AN67-AI67 -> 0 | AP67: =IFERROR(IF(V67<>"",1-(H67/V67),IF(Y67<>"",1-(H67/Y67),1-(H67/L67))),0) -> 0.7934688 | AQ67: =H67/0.75 -> 18.973333 | AR67: 14 | AS67: =(AP67-MIN($AP$65:$AP$368))/(MAX($AP$65:$AP$368)-MIN($AP$65:$AP$368))*100 -> 79.34688 | AT67: =IFERROR(1-(AI67/AH67),0) -> 0 | AU67: =IFERROR(AO67/AH67,0) -> 0 | AW67: =VLOOKUP(AX67,Sup!#REF!,8,0) -> #REF! | AX67: Standard | AY67: 0 | BB67: =IF($F$14="NOVO/REATIVAÇÃO",10*W67*1.4,10*W67) -> 0 | BC67: =IF(BE67<0,BE67,0) -> 0 | BD67: =IFERROR(IF(AND(W67="",X67=""),"",IF(OR($AA$373>=$S$26,SUMIF($C:$C,C67,$W:$W)>=$S$27),S67,IF(OR($AA$373>=$R$26,SUMIF($C:$C,C67,$W:$W)>=$R$27),R67,IF(OR($AA$373>=$Q$26,SUMIF($C:$C,C67,$W:$W)>=$Q$27),Q67,IF(OR($AA$373>=$P$26,SUMIF($C:$C,C67,$W:$W)>=$P$27),P67,IF(OR($AA$373>=$O$26,SUMIF($C:$C,C67,$W:$W)>=$O$27),O67,IF(OR($AA$373>=$N$26,SUMIF($C:$C,C67,$W:$W)>=$N$27),N67,IF($AA$373>=$M$26,M67,L67)))))))*$E$13),0) | BE67: =IF(V67="",0,(V67*W67)-(BD67*W67)) -> 0 | BW67: SPORT NUTRITION | BX67: =IFERROR(W67*U67,0) -> 0 | BY67: =VLOOKUP(B67,#REF!,13,0) -> #REF! | BZ67: 39.9 | CA67: =VLOOKUP(B67,Pedido!$B$16:$L$292,22,0) -> #N/A
B68: PPOB41LIM0200 | C68: =LEFT(B68,6) -> PPOB41 | D68: BCAA Powder | E68: Limão | F68: Pote | G68: 200 | H68: 14.23 | I68: 99.9 | J68: =IFERROR(IF(T68<>"",I68/T68,IF(AND(Y68="",V68=""),"",IF(V68="",I68/Y68,I68/V68))),"") | K68: =IF(T68="","",IFERROR(1-(T68/I68),0)) | L68: 68.9 | M68: =P68 -> 60.9 | N68: =P68 -> 60.9 | O68: =P68 -> 60.9 | P68: 60.9 | Q68: 55.9 | R68: 54.9 | S68: 52.9 | T68: =IF(V68>0,V68,IFERROR(IF(AND(W68<>"",X68<>""),AH68/W68,Y68),"")) | U68: =IFERROR((T68*W68)/(W68+X68),"") | Y68: =IF(AND(W68="",X68=""),"",$E$13*IF(V68<>"",V68,IF(SUMIF($C:$C,C68,$W:$W)>=$S$27,S68,IF(OR($AA$373>=$R$26,SUMIF($C:$C,C68,$W:$W)>=$R$27),R68,IF(OR($AA$373>=$Q$26,SUMIF($C:$C,C68,$W:$W)>=$Q$27),Q68,IF(OR($AA$373>=$P$26,SUMIF($C:$C,C68,$W:$W)>=$P$27),P68,IF(OR($AA$373>=$O$26,SUMIF($C:$C,C68,$W:$W)>=$O$27),O68,IF(OR($AA$373>=$N$26,SUMIF($C:$C,C68,$W:$W)>=$N$27),N68,IF($AA$373>=$M$26,M68,L68))))))))) | Z68: =IF(X68>W68,-1,IF(W68=0,0,IF(U68<(H68/0.75),-1,IF(W68<=3,0,0.0001)))) -> 0 | AA68: =IFERROR(L68*W68,0) -> 0 | AB68: =IFERROR(IF(OR($AA$373>=$S$26,SUMIF($C:$C,C68,$W:$W)>=$S$27),S68,IF(OR($AA$373>=$R$26,SUMIF($C:$C,C68,$W:$W)>=$R$27),R68,IF(OR($AA$373>=$Q$26,SUMIF($C:$C,C68,$W:$W)>=$Q$27),Q68,IF(OR($AA$373>=$P$26,SUMIF($C:$C,C68,$W:$W)>=$P$27),P68,IF(OR($AA$373>=$O$26,SUMIF($C:$C,C68,$W:$W)>=$O$27),O68,IF(OR($AA$373>=$N$26,SUMIF($C:$C,C68,$W:$W)>=$N$27),N68,IF($AA$373>=$M$26,M68,L68)))))))*W68,0) -> 0 | AC68: =IFERROR(IF(V68="",0,(IF(AND(W68="",X68=""),"",IF(OR($AA$373>=$S$26,SUMIF($C:$C,C68,$W:$W)>=$S$27),S68*$E$13,IF(OR($AA$373>=$R$26,SUMIF($C:$C,C68,$W:$W)>=$R$27),R68*$E$13,IF(OR($AA$373>=$Q$26,SUMIF($C:$C,C68,$W:$W)>=$Q$27),Q68*$E$13,IF(OR($AA$373>=$P$26,SUMIF($C:$C,C68,$W:$W)>=$P$27),P68*$E$13,IF(OR($AA$373>=$O$26,SUMIF($C:$C,C68,$W:$W)>=$O$27),O68*$E$13,IF(OR($AA$373>=$N$26,SUMIF($C:$C,C68,$W:$W)>=$N$27),N68*$E$13,IF($AA$373>=$M$26,M68*$E$13,L68))))))))-V68)*W68),0) -> 0 | AD68: =IFERROR(X68*T68,0) -> 0 | AE68: =IFERROR(W68*H68,0) -> 0 | AF68: =IFERROR(1-(AE68/AB68),0) -> 0 | AG68: =IFERROR(SUM(W68:X68)*I68,0) -> 0 | AH68: =IFERROR(IF(V68>0,V68*W68,(Y68*W68)),0) -> 0 | AI68: =IFERROR(SUM(W68)*H68,0) -> 0 | AJ68: =AH68*$AJ$25 -> 0 | AK68: =AH68*AK$25 -> 0 | AL68: =AH68*AL$25 -> 0 | AM68: =SUM(AJ68:AL68) -> 0 | AN68: =AH68-AM68 -> 0 | AO68: =AN68-AI68 -> 0 | AP68: =IFERROR(IF(V68<>"",1-(H68/V68),IF(Y68<>"",1-(H68/Y68),1-(H68/L68))),0) -> 0.7934688 | AQ68: =H68/0.75 -> 18.973333 | AR68: 14 | AS68: =(AP68-MIN($AP$65:$AP$368))/(MAX($AP$65:$AP$368)-MIN($AP$65:$AP$368))*100 -> 79.34688 | AT68: =IFERROR(1-(AI68/AH68),0) -> 0 | AU68: =IFERROR(AO68/AH68,0) -> 0 | AW68: =VLOOKUP(AX68,Sup!#REF!,8,0) -> #REF! | AX68: Standard | AY68: 0 | BB68: =IF($F$14="NOVO/REATIVAÇÃO",10*W68*1.4,10*W68) -> 0 | BC68: =IF(BE68<0,BE68,0) -> 0 | BD68: =IFERROR(IF(AND(W68="",X68=""),"",IF(OR($AA$373>=$S$26,SUMIF($C:$C,C68,$W:$W)>=$S$27),S68,IF(OR($AA$373>=$R$26,SUMIF($C:$C,C68,$W:$W)>=$R$27),R68,IF(OR($AA$373>=$Q$26,SUMIF($C:$C,C68,$W:$W)>=$Q$27),Q68,IF(OR($AA$373>=$P$26,SUMIF($C:$C,C68,$W:$W)>=$P$27),P68,IF(OR($AA$373>=$O$26,SUMIF($C:$C,C68,$W:$W)>=$O$27),O68,IF(OR($AA$373>=$N$26,SUMIF($C:$C,C68,$W:$W)>=$N$27),N68,IF($AA$373>=$M$26,M68,L68)))))))*$E$13),0) | BE68: =IF(V68="",0,(V68*W68)-(BD68*W68)) -> 0 | BW68: SPORT NUTRITION | BX68: =IFERROR(W68*U68,0) -> 0 | BY68: =VLOOKUP(B68,#REF!,13,0) -> #REF! | BZ68: 39.9 | CA68: =VLOOKUP(B68,Pedido!$B$16:$L$292,22,0) -> #N/A
B69: 412043001 | C69: BETAALANINA | D69: Beta Alanina | E69: Sem Sabor | F69: Pote | G69: 120 | H69: 23 | I69: 109.9 | J69: =IFERROR(IF(T69<>"",I69/T69,IF(AND(Y69="",V69=""),"",IF(V69="",I69/Y69,I69/V69))),"") | K69: =IF(T69="","",IFERROR(1-(T69/I69),0)) | L69: 79.9 | M69: =P69 -> 69.9 | N69: =P69 -> 69.9 | O69: =P69 -> 69.9 | P69: 69.9 | Q69: 64.9 | R69: 63.9 | S69: 60.9 | T69: =IF(V69>0,V69,IFERROR(IF(AND(W69<>"",X69<>""),AH69/W69,Y69),"")) | U69: =IFERROR((T69*W69)/(W69+X69),"") | Y69: =IF(AND(W69="",X69=""),"",$E$13*IF(V69<>"",V69,IF(SUMIF($C:$C,C69,$W:$W)>=$S$27,S69,IF(OR($AA$373>=$R$26,SUMIF($C:$C,C69,$W:$W)>=$R$27),R69,IF(OR($AA$373>=$Q$26,SUMIF($C:$C,C69,$W:$W)>=$Q$27),Q69,IF(OR($AA$373>=$P$26,SUMIF($C:$C,C69,$W:$W)>=$P$27),P69,IF(OR($AA$373>=$O$26,SUMIF($C:$C,C69,$W:$W)>=$O$27),O69,IF(OR($AA$373>=$N$26,SUMIF($C:$C,C69,$W:$W)>=$N$27),N69,IF($AA$373>=$M$26,M69,L69))))))))) | Z69: =IF(X69>W69,-1,IF(W69=0,0,IF(U69<(H69/0.75),-1,IF(W69<=3,0,0.0001)))) -> 0 | AA69: =IFERROR(L69*W69,0) -> 0 | AB69: =IFERROR(IF(OR($AA$373>=$S$26,SUMIF($C:$C,C69,$W:$W)>=$S$27),S69,IF(OR($AA$373>=$R$26,SUMIF($C:$C,C69,$W:$W)>=$R$27),R69,IF(OR($AA$373>=$Q$26,SUMIF($C:$C,C69,$W:$W)>=$Q$27),Q69,IF(OR($AA$373>=$P$26,SUMIF($C:$C,C69,$W:$W)>=$P$27),P69,IF(OR($AA$373>=$O$26,SUMIF($C:$C,C69,$W:$W)>=$O$27),O69,IF(OR($AA$373>=$N$26,SUMIF($C:$C,C69,$W:$W)>=$N$27),N69,IF($AA$373>=$M$26,M69,L69)))))))*W69,0) -> 0 | AC69: =IFERROR(IF(V69="",0,(IF(AND(W69="",X69=""),"",IF(OR($AA$373>=$S$26,SUMIF($C:$C,C69,$W:$W)>=$S$27),S69*$E$13,IF(OR($AA$373>=$R$26,SUMIF($C:$C,C69,$W:$W)>=$R$27),R69*$E$13,IF(OR($AA$373>=$Q$26,SUMIF($C:$C,C69,$W:$W)>=$Q$27),Q69*$E$13,IF(OR($AA$373>=$P$26,SUMIF($C:$C,C69,$W:$W)>=$P$27),P69*$E$13,IF(OR($AA$373>=$O$26,SUMIF($C:$C,C69,$W:$W)>=$O$27),O69*$E$13,IF(OR($AA$373>=$N$26,SUMIF($C:$C,C69,$W:$W)>=$N$27),N69*$E$13,IF($AA$373>=$M$26,M69*$E$13,L69))))))))-V69)*W69),0) -> 0 | AD69: =IFERROR(X69*T69,0) -> 0 | AE69: =IFERROR(W69*H69,0) -> 0 | AF69: =IFERROR(1-(AE69/AB69),0) -> 0 | AG69: =IFERROR(SUM(W69:X69)*I69,0) -> 0 | AH69: =IFERROR(IF(V69>0,V69*W69,(Y69*W69)),0) -> 0 | AI69: =IFERROR(SUM(W69)*H69,0) -> 0 | AJ69: =AH69*$AJ$25 -> 0 | AK69: =AH69*AK$25 -> 0 | AL69: =AH69*AL$25 -> 0 | AM69: =SUM(AJ69:AL69) -> 0 | AN69: =AH69-AM69 -> 0 | AO69: =AN69-AI69 -> 0 | AP69: =IFERROR(IF(V69<>"",1-(H69/V69),IF(Y69<>"",1-(H69/Y69),1-(H69/L69))),0) -> 0.71214018 | AQ69: =H69/0.75 -> 30.666667 | AR69: 18 | AS69: =(AP69-MIN($AP$65:$AP$368))/(MAX($AP$65:$AP$368)-MIN($AP$65:$AP$368))*100 -> 71.214018 | AT69: =IFERROR(1-(AI69/AH69),0) -> 0 | AU69: =IFERROR(AO69/AH69,0) -> 0 | AW69: =VLOOKUP(AX69,Sup!#REF!,8,0) -> #REF! | AX69: Commodity | AY69: 0 | BC69: =IF(BE69<0,BE69,0) -> 0 | BD69: =IFERROR(IF(AND(W69="",X69=""),"",IF(OR($AA$373>=$S$26,SUMIF($C:$C,C69,$W:$W)>=$S$27),S69,IF(OR($AA$373>=$R$26,SUMIF($C:$C,C69,$W:$W)>=$R$27),R69,IF(OR($AA$373>=$Q$26,SUMIF($C:$C,C69,$W:$W)>=$Q$27),Q69,IF(OR($AA$373>=$P$26,SUMIF($C:$C,C69,$W:$W)>=$P$27),P69,IF(OR($AA$373>=$O$26,SUMIF($C:$C,C69,$W:$W)>=$O$27),O69,IF(OR($AA$373>=$N$26,SUMIF($C:$C,C69,$W:$W)>=$N$27),N69,IF($AA$373>=$M$26,M69,L69)))))))*$E$13),0) | BE69: =IF(V69="",0,(V69*W69)-(BD69*W69)) -> 0 | BW69: SPORT NUTRITION | BX69: =IFERROR(W69*U69,0) -> 0 | BY69: =VLOOKUP(B69,#REF!,13,0) -> #REF! | BZ69: 47.9 | CA69: =VLOOKUP(B69,Pedido!$B$16:$L$292,22,0) -> #N/A
B70: 431201001 | C70: CREAVITALIS100 | D70: Creatina Crealive - Creavitalis | E70: Sem Sabor | F70: Pote | G70: 100 | H70: 20.4 | I70: 139.9 | J70: =IFERROR(IF(T70<>"",I70/T70,IF(AND(Y70="",V70=""),"",IF(V70="",I70/Y70,I70/V70))),"") | K70: =IF(T70="","",IFERROR(1-(T70/I70),0)) | L70: 101.9 | M70: =P70 -> 89.9 | N70: =P70 -> 89.9 | O70: =P70 -> 89.9 | P70: 89.9 | Q70: 82.9 | R70: 80.9 | S70: 77.9 | T70: =IF(V70>0,V70,IFERROR(IF(AND(W70<>"",X70<>""),AH70/W70,Y70),"")) | U70: =IFERROR((T70*W70)/(W70+X70),"") | Y70: =IF(AND(W70="",X70=""),"",$E$13*IF(V70<>"",V70,IF(SUMIF($C:$C,C70,$W:$W)>=$S$27,S70,IF(OR($AA$373>=$R$26,SUMIF($C:$C,C70,$W:$W)>=$R$27),R70,IF(OR($AA$373>=$Q$26,SUMIF($C:$C,C70,$W:$W)>=$Q$27),Q70,IF(OR($AA$373>=$P$26,SUMIF($C:$C,C70,$W:$W)>=$P$27),P70,IF(OR($AA$373>=$O$26,SUMIF($C:$C,C70,$W:$W)>=$O$27),O70,IF(OR($AA$373>=$N$26,SUMIF($C:$C,C70,$W:$W)>=$N$27),N70,IF($AA$373>=$M$26,M70,L70))))))))) | Z70: =IF(X70>W70,-1,IF(W70=0,0,IF(U70<(H70/0.75),-1,IF(W70<=3,0,0.0001)))) -> 0 | AA70: =IFERROR(L70*W70,0) -> 0 | AB70: =IFERROR(IF(OR($AA$373>=$S$26,SUMIF($C:$C,C70,$W:$W)>=$S$27),S70,IF(OR($AA$373>=$R$26,SUMIF($C:$C,C70,$W:$W)>=$R$27),R70,IF(OR($AA$373>=$Q$26,SUMIF($C:$C,C70,$W:$W)>=$Q$27),Q70,IF(OR($AA$373>=$P$26,SUMIF($C:$C,C70,$W:$W)>=$P$27),P70,IF(OR($AA$373>=$O$26,SUMIF($C:$C,C70,$W:$W)>=$O$27),O70,IF(OR($AA$373>=$N$26,SUMIF($C:$C,C70,$W:$W)>=$N$27),N70,IF($AA$373>=$M$26,M70,L70)))))))*W70,0) -> 0 | AC70: =IFERROR(IF(V70="",0,(IF(AND(W70="",X70=""),"",IF(OR($AA$373>=$S$26,SUMIF($C:$C,C70,$W:$W)>=$S$27),S70*$E$13,IF(OR($AA$373>=$R$26,SUMIF($C:$C,C70,$W:$W)>=$R$27),R70*$E$13,IF(OR($AA$373>=$Q$26,SUMIF($C:$C,C70,$W:$W)>=$Q$27),Q70*$E$13,IF(OR($AA$373>=$P$26,SUMIF($C:$C,C70,$W:$W)>=$P$27),P70*$E$13,IF(OR($AA$373>=$O$26,SUMIF($C:$C,C70,$W:$W)>=$O$27),O70*$E$13,IF(OR($AA$373>=$N$26,SUMIF($C:$C,C70,$W:$W)>=$N$27),N70*$E$13,IF($AA$373>=$M$26,M70*$E$13,L70))))))))-V70)*W70),0) -> 0 | AD70: =IFERROR(X70*T70,0) -> 0 | AE70: =IFERROR(W70*H70,0) -> 0 | AF70: =IFERROR(1-(AE70/AB70),0) -> 0 | AG70: =IFERROR(SUM(W70:X70)*I70,0) -> 0 | AH70: =IFERROR(IF(V70>0,V70*W70,(Y70*W70)),0) -> 0 | AI70: =IFERROR(SUM(W70)*H70,0) -> 0 | AJ70: =AH70*$AJ$25 -> 0 | AK70: =AH70*AK$25 -> 0 | AL70: =AH70*AL$25 -> 0 | AM70: =SUM(AJ70:AL70) -> 0 | AN70: =AH70-AM70 -> 0 | AO70: =AN70-AI70 -> 0 | AP70: =IFERROR(IF(V70<>"",1-(H70/V70),IF(Y70<>"",1-(H70/Y70),1-(H70/L70))),0) -> 0.79980373 | AQ70: =H70/0.75 -> 27.2 | AR70: 18 | AS70: =(AP70-MIN($AP$65:$AP$368))/(MAX($AP$65:$AP$368)-MIN($AP$65:$AP$368))*100 -> 79.980373 | AT70: =IFERROR(1-(AI70/AH70),0) -> 0 | AU70: =IFERROR(AO70/AH70,0) -> 0 | AW70: =VLOOKUP(AX70,Sup!#REF!,8,0) -> #REF! | AX70: Commodity | AY70: 0 | BC70: =IF(BE70<0,BE70,0) -> 0 | BD70: =IFERROR(IF(AND(W70="",X70=""),"",IF(OR($AA$373>=$S$26,SUMIF($C:$C,C70,$W:$W)>=$S$27),S70,IF(OR($AA$373>=$R$26,SUMIF($C:$C,C70,$W:$W)>=$R$27),R70,IF(OR($AA$373>=$Q$26,SUMIF($C:$C,C70,$W:$W)>=$Q$27),Q70,IF(OR($AA$373>=$P$26,SUMIF($C:$C,C70,$W:$W)>=$P$27),P70,IF(OR($AA$373>=$O$26,SUMIF($C:$C,C70,$W:$W)>=$O$27),O70,IF(OR($AA$373>=$N$26,SUMIF($C:$C,C70,$W:$W)>=$N$27),N70,IF($AA$373>=$M$26,M70,L70)))))))*$E$13),0) | BE70: =IF(V70="",0,(V70*W70)-(BD70*W70)) -> 0 | BW70: SPORT NUTRITION | BX70: =IFERROR(W70*U70,0) -> 0 | BY70: =VLOOKUP(B70,#REF!,13,0) -> #REF! | BZ70: 63.9 | CA70: =VLOOKUP(B70,Pedido!$B$16:$L$292,22,0) -> #N/A
B71: 431204001 | C71: CREAVITALIS300 | D71: Creatina Crealive - Creavitalis | E71: Sem Sabor | F71: Pote | G71: 300 | H71: 56.8 | I71: 319.9 | J71: =IFERROR(IF(T71<>"",I71/T71,IF(AND(Y71="",V71=""),"",IF(V71="",I71/Y71,I71/V71))),"") | K71: =IF(T71="","",IFERROR(1-(T71/I71),0)) | L71: 228.9 | M71: =P71 -> 201.9 | N71: =P71 -> 201.9 | O71: =P71 -> 201.9 | P71: 201.9 | Q71: 186.9 | R71: 183.9 | S71: 177.9 | T71: =IF(V71>0,V71,IFERROR(IF(AND(W71<>"",X71<>""),AH71/W71,Y71),"")) | U71: =IFERROR((T71*W71)/(W71+X71),"") | Y71: =IF(AND(W71="",X71=""),"",$E$13*IF(V71<>"",V71,IF(SUMIF($C:$C,C71,$W:$W)>=$S$27,S71,IF(OR($AA$373>=$R$26,SUMIF($C:$C,C71,$W:$W)>=$R$27),R71,IF(OR($AA$373>=$Q$26,SUMIF($C:$C,C71,$W:$W)>=$Q$27),Q71,IF(OR($AA$373>=$P$26,SUMIF($C:$C,C71,$W:$W)>=$P$27),P71,IF(OR($AA$373>=$O$26,SUMIF($C:$C,C71,$W:$W)>=$O$27),O71,IF(OR($AA$373>=$N$26,SUMIF($C:$C,C71,$W:$W)>=$N$27),N71,IF($AA$373>=$M$26,M71,L71))))))))) | Z71: =IF(X71>W71,-1,IF(W71=0,0,IF(U71<(H71/0.75),-1,IF(W71<=3,0,0.0001)))) -> 0 | AA71: =IFERROR(L71*W71,0) -> 0 | AB71: =IFERROR(IF(OR($AA$373>=$S$26,SUMIF($C:$C,C71,$W:$W)>=$S$27),S71,IF(OR($AA$373>=$R$26,SUMIF($C:$C,C71,$W:$W)>=$R$27),R71,IF(OR($AA$373>=$Q$26,SUMIF($C:$C,C71,$W:$W)>=$Q$27),Q71,IF(OR($AA$373>=$P$26,SUMIF($C:$C,C71,$W:$W)>=$P$27),P71,IF(OR($AA$373>=$O$26,SUMIF($C:$C,C71,$W:$W)>=$O$27),O71,IF(OR($AA$373>=$N$26,SUMIF($C:$C,C71,$W:$W)>=$N$27),N71,IF($AA$373>=$M$26,M71,L71)))))))*W71,0) -> 0 | AC71: =IFERROR(IF(V71="",0,(IF(AND(W71="",X71=""),"",IF(OR($AA$373>=$S$26,SUMIF($C:$C,C71,$W:$W)>=$S$27),S71*$E$13,IF(OR($AA$373>=$R$26,SUMIF($C:$C,C71,$W:$W)>=$R$27),R71*$E$13,IF(OR($AA$373>=$Q$26,SUMIF($C:$C,C71,$W:$W)>=$Q$27),Q71*$E$13,IF(OR($AA$373>=$P$26,SUMIF($C:$C,C71,$W:$W)>=$P$27),P71*$E$13,IF(OR($AA$373>=$O$26,SUMIF($C:$C,C71,$W:$W)>=$O$27),O71*$E$13,IF(OR($AA$373>=$N$26,SUMIF($C:$C,C71,$W:$W)>=$N$27),N71*$E$13,IF($AA$373>=$M$26,M71*$E$13,L71))))))))-V71)*W71),0) -> 0 | AD71: =IFERROR(X71*T71,0) -> 0 | AE71: =IFERROR(W71*H71,0) -> 0 | AF71: =IFERROR(1-(AE71/AB71),0) -> 0 | AG71: =IFERROR(SUM(W71:X71)*I71,0) -> 0 | AH71: =IFERROR(IF(V71>0,V71*W71,(Y71*W71)),0) -> 0 | AI71: =IFERROR(SUM(W71)*H71,0) -> 0 | AJ71: =AH71*$AJ$25 -> 0 | AK71: =AH71*AK$25 -> 0 | AL71: =AH71*AL$25 -> 0 | AM71: =SUM(AJ71:AL71) -> 0 | AN71: =AH71-AM71 -> 0 | AO71: =AN71-AI71 -> 0 | AP71: =IFERROR(IF(V71<>"",1-(H71/V71),IF(Y71<>"",1-(H71/Y71),1-(H71/L71))),0) -> 0.75185671 | AQ71: =H71/0.75 -> 75.733333 | AR71: 6 | AS71: =(AP71-MIN($AP$65:$AP$368))/(MAX($AP$65:$AP$368)-MIN($AP$65:$AP$368))*100 -> 75.185671 | AT71: =IFERROR(1-(AI71/AH71),0) -> 0 | AU71: =IFERROR(AO71/AH71,0) -> 0 | AW71: =VLOOKUP(AX71,Sup!#REF!,8,0) -> #REF! | AX71: Commodity | AY71: 0 | BC71: =IF(BE71<0,BE71,0) -> 0 | BD71: =IFERROR(IF(AND(W71="",X71=""),"",IF(OR($AA$373>=$S$26,SUMIF($C:$C,C71,$W:$W)>=$S$27),S71,IF(OR($AA$373>=$R$26,SUMIF($C:$C,C71,$W:$W)>=$R$27),R71,IF(OR($AA$373>=$Q$26,SUMIF($C:$C,C71,$W:$W)>=$Q$27),Q71,IF(OR($AA$373>=$P$26,SUMIF($C:$C,C71,$W:$W)>=$P$27),P71,IF(OR($AA$373>=$O$26,SUMIF($C:$C,C71,$W:$W)>=$O$27),O71,IF(OR($AA$373>=$N$26,SUMIF($C:$C,C71,$W:$W)>=$N$27),N71,IF($AA$373>=$M$26,M71,L71)))))))*$E$13),0) | BE71: =IF(V71="",0,(V71*W71)-(BD71*W71)) -> 0 | BW71: SPORT NUTRITION | BX71: =IFERROR(W71*U71,0) -> 0 | BY71: =VLOOKUP(B71,#REF!,13,0) -> #REF! | BZ71: 158.9 | CA71: =VLOOKUP(B71,Pedido!$B$16:$L$292,22,0) -> #N/A
B72: PPOCRENAT0100 | C72: PPOCRE1 | D72: Creatina Creapure | E72: Sem Sabor | F72: Pote | G72: 100 | H72: 21.345555 | I72: 129.9 | J72: =IFERROR(IF(T72<>"",I72/T72,IF(AND(Y72="",V72=""),"",IF(V72="",I72/Y72,I72/V72))),"") | K72: =IF(T72="","",IFERROR(1-(T72/I72),0)) | L72: 91.9 | M72: =P72 -> 80.9 | N72: =P72 -> 80.9 | O72: =P72 -> 80.9 | P72: 80.9 | Q72: 74.9 | R72: 72.9 | S72: 69.9 | T72: =IF(V72>0,V72,IFERROR(IF(AND(W72<>"",X72<>""),AH72/W72,Y72),"")) | U72: =IFERROR((T72*W72)/(W72+X72),"") | Y72: =IF(AND(W72="",X72=""),"",$E$13*IF(V72<>"",V72,IF(SUMIF($C:$C,C72,$W:$W)>=$S$27,S72,IF(OR($AA$373>=$R$26,SUMIF($C:$C,C72,$W:$W)>=$R$27),R72,IF(OR($AA$373>=$Q$26,SUMIF($C:$C,C72,$W:$W)>=$Q$27),Q72,IF(OR($AA$373>=$P$26,SUMIF($C:$C,C72,$W:$W)>=$P$27),P72,IF(OR($AA$373>=$O$26,SUMIF($C:$C,C72,$W:$W)>=$O$27),O72,IF(OR($AA$373>=$N$26,SUMIF($C:$C,C72,$W:$W)>=$N$27),N72,IF($AA$373>=$M$26,M72,L72))))))))) | Z72: =IF(X72>W72,-1,IF(W72=0,0,IF(U72<(H72/0.75),-1,IF(W72<=3,0,0.0001)))) -> 0 | AA72: =IFERROR(L72*W72,0) -> 0 | AB72: =IFERROR(IF(OR($AA$373>=$S$26,SUMIF($C:$C,C72,$W:$W)>=$S$27),S72,IF(OR($AA$373>=$R$26,SUMIF($C:$C,C72,$W:$W)>=$R$27),R72,IF(OR($AA$373>=$Q$26,SUMIF($C:$C,C72,$W:$W)>=$Q$27),Q72,IF(OR($AA$373>=$P$26,SUMIF($C:$C,C72,$W:$W)>=$P$27),P72,IF(OR($AA$373>=$O$26,SUMIF($C:$C,C72,$W:$W)>=$O$27),O72,IF(OR($AA$373>=$N$26,SUMIF($C:$C,C72,$W:$W)>=$N$27),N72,IF($AA$373>=$M$26,M72,L72)))))))*W72,0) -> 0 | AC72: =IFERROR(IF(V72="",0,(IF(AND(W72="",X72=""),"",IF(OR($AA$373>=$S$26,SUMIF($C:$C,C72,$W:$W)>=$S$27),S72*$E$13,IF(OR($AA$373>=$R$26,SUMIF($C:$C,C72,$W:$W)>=$R$27),R72*$E$13,IF(OR($AA$373>=$Q$26,SUMIF($C:$C,C72,$W:$W)>=$Q$27),Q72*$E$13,IF(OR($AA$373>=$P$26,SUMIF($C:$C,C72,$W:$W)>=$P$27),P72*$E$13,IF(OR($AA$373>=$O$26,SUMIF($C:$C,C72,$W:$W)>=$O$27),O72*$E$13,IF(OR($AA$373>=$N$26,SUMIF($C:$C,C72,$W:$W)>=$N$27),N72*$E$13,IF($AA$373>=$M$26,M72*$E$13,L72))))))))-V72)*W72),0) -> 0 | AD72: =IFERROR(X72*T72,0) -> 0 | AE72: =IFERROR(W72*H72,0) -> 0 | AF72: =IFERROR(1-(AE72/AB72),0) -> 0 | AG72: =IFERROR(SUM(W72:X72)*I72,0) -> 0 | AH72: =IFERROR(IF(V72>0,V72*W72,(Y72*W72)),0) -> 0 | AI72: =IFERROR(SUM(W72)*H72,0) -> 0 | AJ72: =AH72*$AJ$25 -> 0 | AK72: =AH72*AK$25 -> 0 | AL72: =AH72*AL$25 -> 0 | AM72: =SUM(AJ72:AL72) -> 0 | AN72: =AH72-AM72 -> 0 | AO72: =AN72-AI72 -> 0 | AP72: =IFERROR(IF(V72<>"",1-(H72/V72),IF(Y72<>"",1-(H72/Y72),1-(H72/L72))),0) -> 0.76773063 | AQ72: =H72/0.75 -> 28.46074 | AR72: 27 | AS72: =(AP72-MIN($AP$65:$AP$368))/(MAX($AP$65:$AP$368)-MIN($AP$65:$AP$368))*100 -> 76.773063 | AT72: =IFERROR(1-(AI72/AH72),0) -> 0 | AU72: =IFERROR(AO72/AH72,0) -> 0 | AW72: =VLOOKUP(AX72,Sup!#REF!,8,0) -> #REF! | AX72: Commodity | AY72: 0 | BC72: =IF(BE72<0,BE72,0) -> 0 | BD72: =IFERROR(IF(AND(W72="",X72=""),"",IF(OR($AA$373>=$S$26,SUMIF($C:$C,C72,$W:$W)>=$S$27),S72,IF(OR($AA$373>=$R$26,SUMIF($C:$C,C72,$W:$W)>=$R$27),R72,IF(OR($AA$373>=$Q$26,SUMIF($C:$C,C72,$W:$W)>=$Q$27),Q72,IF(OR($AA$373>=$P$26,SUMIF($C:$C,C72,$W:$W)>=$P$27),P72,IF(OR($AA$373>=$O$26,SUMIF($C:$C,C72,$W:$W)>=$O$27),O72,IF(OR($AA$373>=$N$26,SUMIF($C:$C,C72,$W:$W)>=$N$27),N72,IF($AA$373>=$M$26,M72,L72)))))))*$E$13),0) | BE72: =IF(V72="",0,(V72*W72)-(BD72*W72)) -> 0 | BW72: SPORT NUTRITION | BX72: =IFERROR(W72*U72,0) -> 0 | BY72: =VLOOKUP(B72,#REF!,13,0) -> #REF! | BZ72: 55.9 | CA72: =VLOOKUP(B72,Pedido!$B$16:$L$292,22,0) -> #N/A | CC72: =SUM(CA73) -> #N/A
B73: PPOCRENAT0300 | C73: PPOCRE3 | D73: Creatina Creapure | E73: Sem Sabor | F73: Pote | G73: 300 | H73: 59.553128 | I73: 299.9 | J73: =IFERROR(IF(T73<>"",I73/T73,IF(AND(Y73="",V73=""),"",IF(V73="",I73/Y73,I73/V73))),"") | K73: =IF(T73="","",IFERROR(1-(T73/I73),0)) | L73: 206.9 | M73: =P73 -> 182.9 | N73: =P73 -> 182.9 | O73: =P73 -> 182.9 | P73: 182.9 | Q73: 168.9 | R73: 165.9 | S73: 159.9 | T73: =IF(V73>0,V73,IFERROR(IF(AND(W73<>"",X73<>""),AH73/W73,Y73),"")) | U73: =IFERROR((T73*W73)/(W73+X73),"") | Y73: =IF(AND(W73="",X73=""),"",$E$13*IF(V73<>"",V73,IF(SUMIF($C:$C,C73,$W:$W)>=$S$27,S73,IF(OR($AA$373>=$R$26,SUMIF($C:$C,C73,$W:$W)>=$R$27),R73,IF(OR($AA$373>=$Q$26,SUMIF($C:$C,C73,$W:$W)>=$Q$27),Q73,IF(OR($AA$373>=$P$26,SUMIF($C:$C,C73,$W:$W)>=$P$27),P73,IF(OR($AA$373>=$O$26,SUMIF($C:$C,C73,$W:$W)>=$O$27),O73,IF(OR($AA$373>=$N$26,SUMIF($C:$C,C73,$W:$W)>=$N$27),N73,IF($AA$373>=$M$26,M73,L73))))))))) | Z73: =IF(X73>W73,-1,IF(W73=0,0,IF(U73<(H73/0.75),-1,IF(W73<=3,0,0.0001)))) -> 0 | AA73: =IFERROR(L73*W73,0) -> 0 | AB73: =IFERROR(IF(OR($AA$373>=$S$26,SUMIF($C:$C,C73,$W:$W)>=$S$27),S73,IF(OR($AA$373>=$R$26,SUMIF($C:$C,C73,$W:$W)>=$R$27),R73,IF(OR($AA$373>=$Q$26,SUMIF($C:$C,C73,$W:$W)>=$Q$27),Q73,IF(OR($AA$373>=$P$26,SUMIF($C:$C,C73,$W:$W)>=$P$27),P73,IF(OR($AA$373>=$O$26,SUMIF($C:$C,C73,$W:$W)>=$O$27),O73,IF(OR($AA$373>=$N$26,SUMIF($C:$C,C73,$W:$W)>=$N$27),N73,IF($AA$373>=$M$26,M73,L73)))))))*W73,0) -> 0 | AC73: =IFERROR(IF(V73="",0,(IF(AND(W73="",X73=""),"",IF(OR($AA$373>=$S$26,SUMIF($C:$C,C73,$W:$W)>=$S$27),S73*$E$13,IF(OR($AA$373>=$R$26,SUMIF($C:$C,C73,$W:$W)>=$R$27),R73*$E$13,IF(OR($AA$373>=$Q$26,SUMIF($C:$C,C73,$W:$W)>=$Q$27),Q73*$E$13,IF(OR($AA$373>=$P$26,SUMIF($C:$C,C73,$W:$W)>=$P$27),P73*$E$13,IF(OR($AA$373>=$O$26,SUMIF($C:$C,C73,$W:$W)>=$O$27),O73*$E$13,IF(OR($AA$373>=$N$26,SUMIF($C:$C,C73,$W:$W)>=$N$27),N73*$E$13,IF($AA$373>=$M$26,M73*$E$13,L73))))))))-V73)*W73),0) -> 0 | AD73: =IFERROR(X73*T73,0) -> 0 | AE73: =IFERROR(W73*H73,0) -> 0 | AF73: =IFERROR(1-(AE73/AB73),0) -> 0 | AG73: =IFERROR(SUM(W73:X73)*I73,0) -> 0 | AH73: =IFERROR(IF(V73>0,V73*W73,(Y73*W73)),0) -> 0 | AI73: =IFERROR(SUM(W73)*H73,0) -> 0 | AJ73: =AH73*$AJ$25 -> 0 | AK73: =AH73*AK$25 -> 0 | AL73: =AH73*AL$25 -> 0 | AM73: =SUM(AJ73:AL73) -> 0 | AN73: =AH73-AM73 -> 0 | AO73: =AN73-AI73 -> 0 | AP73: =IFERROR(IF(V73<>"",1-(H73/V73),IF(Y73<>"",1-(H73/Y73),1-(H73/L73))),0) -> 0.71216468 | AQ73: =H73/0.75 -> 79.40417 | AR73: 18 | AS73: =(AP73-MIN($AP$65:$AP$368))/(MAX($AP$65:$AP$368)-MIN($AP$65:$AP$368))*100 -> 71.216468 | AT73: =IFERROR(1-(AI73/AH73),0) -> 0 | AU73: =IFERROR(AO73/AH73,0) -> 0 | AW73: =VLOOKUP(AX73,Sup!#REF!,8,0) -> #REF! | AX73: Commodity | AY73: 0 | BC73: =IF(BE73<0,BE73,0) -> 0 | BD73: =IFERROR(IF(AND(W73="",X73=""),"",IF(OR($AA$373>=$S$26,SUMIF($C:$C,C73,$W:$W)>=$S$27),S73,IF(OR($AA$373>=$R$26,SUMIF($C:$C,C73,$W:$W)>=$R$27),R73,IF(OR($AA$373>=$Q$26,SUMIF($C:$C,C73,$W:$W)>=$Q$27),Q73,IF(OR($AA$373>=$P$26,SUMIF($C:$C,C73,$W:$W)>=$P$27),P73,IF(OR($AA$373>=$O$26,SUMIF($C:$C,C73,$W:$W)>=$O$27),O73,IF(OR($AA$373>=$N$26,SUMIF($C:$C,C73,$W:$W)>=$N$27),N73,IF($AA$373>=$M$26,M73,L73)))))))*$E$13),0) | BE73: =IF(V73="",0,(V73*W73)-(BD73*W73)) -> 0 | BW73: SPORT NUTRITION | BX73: =IFERROR(W73*U73,0) -> 0 | BY73: =VLOOKUP(B73,#REF!,13,0) -> #REF! | BZ73: 141.9 | CA73: =VLOOKUP(B73,Pedido!$B$16:$L$292,22,0) -> #N/A | CC73: =ROUNDDOWN(CC72/12,0) -> #N/A | CF73: =IFERROR((CC73*Pedido!#REF!),0) -> 0
B74: 30000255 | C74: Mono100 | D74: Creatina Monohidratada | E74: Sem Sabor | F74: Pote | G74: 100 | H74: 6.6510758 | I74: 74.9 | J74: =IFERROR(IF(T74<>"",I74/T74,IF(AND(Y74="",V74=""),"",IF(V74="",I74/Y74,I74/V74))),"") | K74: =IF(T74="","",IFERROR(1-(T74/I74),0)) | L74: 53.9 | M74: =P74 -> 46.9 | N74: =P74 -> 46.9 | O74: =P74 -> 46.9 | P74: 46.9 | Q74: 42.9 | R74: 41.9 | S74: 39.9 | T74: =IF(V74>0,V74,IFERROR(IF(AND(W74<>"",X74<>""),AH74/W74,Y74),"")) | U74: =IFERROR((T74*W74)/(W74+X74),"") | Y74: =IF(AND(W74="",X74=""),"",$E$13*IF(V74<>"",V74,IF(SUMIF($C:$C,C74,$W:$W)>=$S$27,S74,IF(OR($AA$373>=$R$26,SUMIF($C:$C,C74,$W:$W)>=$R$27),R74,IF(OR($AA$373>=$Q$26,SUMIF($C:$C,C74,$W:$W)>=$Q$27),Q74,IF(OR($AA$373>=$P$26,SUMIF($C:$C,C74,$W:$W)>=$P$27),P74,IF(OR($AA$373>=$O$26,SUMIF($C:$C,C74,$W:$W)>=$O$27),O74,IF(OR($AA$373>=$N$26,SUMIF($C:$C,C74,$W:$W)>=$N$27),N74,IF($AA$373>=$M$26,M74,L74))))))))) | Z74: =IF(X74>W74,-1,IF(W74=0,0,IF(U74<(H74/0.75),-1,IF(W74<=3,0,0.0001)))) -> 0 | AA74: =IFERROR(L74*W74,0) -> 0 | AB74: =IFERROR(IF(OR($AA$373>=$S$26,SUMIF($C:$C,C74,$W:$W)>=$S$27),S74,IF(OR($AA$373>=$R$26,SUMIF($C:$C,C74,$W:$W)>=$R$27),R74,IF(OR($AA$373>=$Q$26,SUMIF($C:$C,C74,$W:$W)>=$Q$27),Q74,IF(OR($AA$373>=$P$26,SUMIF($C:$C,C74,$W:$W)>=$P$27),P74,IF(OR($AA$373>=$O$26,SUMIF($C:$C,C74,$W:$W)>=$O$27),O74,IF(OR($AA$373>=$N$26,SUMIF($C:$C,C74,$W:$W)>=$N$27),N74,IF($AA$373>=$M$26,M74,L74)))))))*W74,0) -> 0 | AC74: =IFERROR(IF(V74="",0,(IF(AND(W74="",X74=""),"",IF(OR($AA$373>=$S$26,SUMIF($C:$C,C74,$W:$W)>=$S$27),S74*$E$13,IF(OR($AA$373>=$R$26,SUMIF($C:$C,C74,$W:$W)>=$R$27),R74*$E$13,IF(OR($AA$373>=$Q$26,SUMIF($C:$C,C74,$W:$W)>=$Q$27),Q74*$E$13,IF(OR($AA$373>=$P$26,SUMIF($C:$C,C74,$W:$W)>=$P$27),P74*$E$13,IF(OR($AA$373>=$O$26,SUMIF($C:$C,C74,$W:$W)>=$O$27),O74*$E$13,IF(OR($AA$373>=$N$26,SUMIF($C:$C,C74,$W:$W)>=$N$27),N74*$E$13,IF($AA$373>=$M$26,M74*$E$13,L74))))))))-V74)*W74),0) -> 0 | AD74: =IFERROR(X74*T74,0) -> 0 | AE74: =IFERROR(W74*H74,0) -> 0 | AF74: =IFERROR(1-(AE74/AB74),0) -> 0 | AG74: =IFERROR(SUM(W74:X74)*I74,0) -> 0 | AH74: =IFERROR(IF(V74>0,V74*W74,(Y74*W74)),0) -> 0 | AI74: =IFERROR(SUM(W74)*H74,0) -> 0 | AJ74: =AH74*$AJ$25 -> 0 | AK74: =AH74*AK$25 -> 0 | AL74: =AH74*AL$25 -> 0 | AM74: =SUM(AJ74:AL74) -> 0 | AN74: =AH74-AM74 -> 0 | AO74: =AN74-AI74 -> 0 | AP74: =IFERROR(IF(V74<>"",1-(H74/V74),IF(Y74<>"",1-(H74/Y74),1-(H74/L74))),0) -> 0.87660342 | AQ74: =H74/0.75 -> 8.8681011 | AR74: 27 | AS74: =(AP74-MIN($AP$65:$AP$368))/(MAX($AP$65:$AP$368)-MIN($AP$65:$AP$368))*100 -> 87.660342 | AT74: =IFERROR(1-(AI74/AH74),0) -> 0 | AU74: =IFERROR(AO74/AH74,0) -> 0 | AW74: =VLOOKUP(AX74,Sup!#REF!,8,0) -> #REF! | AX74: Commodity | AY74: 0 | BC74: =IF(BE74<0,BE74,0) -> 0 | BD74: =IFERROR(IF(AND(W74="",X74=""),"",IF(OR($AA$373>=$S$26,SUMIF($C:$C,C74,$W:$W)>=$S$27),S74,IF(OR($AA$373>=$R$26,SUMIF($C:$C,C74,$W:$W)>=$R$27),R74,IF(OR($AA$373>=$Q$26,SUMIF($C:$C,C74,$W:$W)>=$Q$27),Q74,IF(OR($AA$373>=$P$26,SUMIF($C:$C,C74,$W:$W)>=$P$27),P74,IF(OR($AA$373>=$O$26,SUMIF($C:$C,C74,$W:$W)>=$O$27),O74,IF(OR($AA$373>=$N$26,SUMIF($C:$C,C74,$W:$W)>=$N$27),N74,IF($AA$373>=$M$26,M74,L74)))))))*$E$13),0) | BE74: =IF(V74="",0,(V74*W74)-(BD74*W74)) -> 0 | BW74: SPORT NUTRITION | BX74: =IFERROR(W74*U74,0) -> 0 | BY74: =VLOOKUP(B74,#REF!,13,0) -> #REF! | BZ74: 27.9 | CA74: =VLOOKUP(B74,Pedido!$B$16:$L$292,22,0) -> #N/A
B75: 30000256 | C75: Mono300 | D75: Creatina Monohidratada | E75: Sem Sabor | F75: Pote | G75: 300 | H75: 15.287936 | I75: 149.9 | J75: =IFERROR(IF(T75<>"",I75/T75,IF(AND(Y75="",V75=""),"",IF(V75="",I75/Y75,I75/V75))),"") | K75: =IF(T75="","",IFERROR(1-(T75/I75),0)) | L75: 103.9 | M75: =P75 -> 91.9 | N75: =P75 -> 91.9 | O75: =P75 -> 91.9 | P75: 91.9 | Q75: 84.9 | R75: 82.9 | S75: 79.9 | T75: =IF(V75>0,V75,IFERROR(IF(AND(W75<>"",X75<>""),AH75/W75,Y75),"")) | U75: =IFERROR((T75*W75)/(W75+X75),"") | Y75: =IF(AND(W75="",X75=""),"",$E$13*IF(V75<>"",V75,IF(SUMIF($C:$C,C75,$W:$W)>=$S$27,S75,IF(OR($AA$373>=$R$26,SUMIF($C:$C,C75,$W:$W)>=$R$27),R75,IF(OR($AA$373>=$Q$26,SUMIF($C:$C,C75,$W:$W)>=$Q$27),Q75,IF(OR($AA$373>=$P$26,SUMIF($C:$C,C75,$W:$W)>=$P$27),P75,IF(OR($AA$373>=$O$26,SUMIF($C:$C,C75,$W:$W)>=$O$27),O75,IF(OR($AA$373>=$N$26,SUMIF($C:$C,C75,$W:$W)>=$N$27),N75,IF($AA$373>=$M$26,M75,L75))))))))) | Z75: =IF(X75>W75,-1,IF(W75=0,0,IF(U75<(H75/0.75),-1,IF(W75<=3,0,0.0001)))) -> 0 | AA75: =IFERROR(L75*W75,0) -> 0 | AB75: =IFERROR(IF(OR($AA$373>=$S$26,SUMIF($C:$C,C75,$W:$W)>=$S$27),S75,IF(OR($AA$373>=$R$26,SUMIF($C:$C,C75,$W:$W)>=$R$27),R75,IF(OR($AA$373>=$Q$26,SUMIF($C:$C,C75,$W:$W)>=$Q$27),Q75,IF(OR($AA$373>=$P$26,SUMIF($C:$C,C75,$W:$W)>=$P$27),P75,IF(OR($AA$373>=$O$26,SUMIF($C:$C,C75,$W:$W)>=$O$27),O75,IF(OR($AA$373>=$N$26,SUMIF($C:$C,C75,$W:$W)>=$N$27),N75,IF($AA$373>=$M$26,M75,L75)))))))*W75,0) -> 0 | AC75: =IFERROR(IF(V75="",0,(IF(AND(W75="",X75=""),"",IF(OR($AA$373>=$S$26,SUMIF($C:$C,C75,$W:$W)>=$S$27),S75*$E$13,IF(OR($AA$373>=$R$26,SUMIF($C:$C,C75,$W:$W)>=$R$27),R75*$E$13,IF(OR($AA$373>=$Q$26,SUMIF($C:$C,C75,$W:$W)>=$Q$27),Q75*$E$13,IF(OR($AA$373>=$P$26,SUMIF($C:$C,C75,$W:$W)>=$P$27),P75*$E$13,IF(OR($AA$373>=$O$26,SUMIF($C:$C,C75,$W:$W)>=$O$27),O75*$E$13,IF(OR($AA$373>=$N$26,SUMIF($C:$C,C75,$W:$W)>=$N$27),N75*$E$13,IF($AA$373>=$M$26,M75*$E$13,L75))))))))-V75)*W75),0) -> 0 | AD75: =IFERROR(X75*T75,0) -> 0 | AE75: =IFERROR(W75*H75,0) -> 0 | AF75: =IFERROR(1-(AE75/AB75),0) -> 0 | AG75: =IFERROR(SUM(W75:X75)*I75,0) -> 0 | AH75: =IFERROR(IF(V75>0,V75*W75,(Y75*W75)),0) -> 0 | AI75: =IFERROR(SUM(W75)*H75,0) -> 0 | AJ75: =AH75*$AJ$25 -> 0 | AK75: =AH75*AK$25 -> 0 | AL75: =AH75*AL$25 -> 0 | AM75: =SUM(AJ75:AL75) -> 0 | AN75: =AH75-AM75 -> 0 | AO75: =AN75-AI75 -> 0 | AP75: =IFERROR(IF(V75<>"",1-(H75/V75),IF(Y75<>"",1-(H75/Y75),1-(H75/L75))),0) -> 0.85285913 | AQ75: =H75/0.75 -> 20.383915 | AR75: 18 | AS75: =(AP75-MIN($AP$65:$AP$368))/(MAX($AP$65:$AP$368)-MIN($AP$65:$AP$368))*100 -> 85.285913 | AT75: =IFERROR(1-(AI75/AH75),0) -> 0 | AU75: =IFERROR(AO75/AH75,0) -> 0 | AW75: =VLOOKUP(AX75,Sup!#REF!,8,0) -> #REF! | AX75: Commodity | AY75: 0 | BB75: =IF($F$14="NOVO/REATIVAÇÃO",W75*5*1.4,W75*5) -> 0 | BC75: =IF(BE75<0,BE75,0) -> 0 | BD75: =IFERROR(IF(AND(W75="",X75=""),"",IF(OR($AA$373>=$S$26,SUMIF($C:$C,C75,$W:$W)>=$S$27),S75,IF(OR($AA$373>=$R$26,SUMIF($C:$C,C75,$W:$W)>=$R$27),R75,IF(OR($AA$373>=$Q$26,SUMIF($C:$C,C75,$W:$W)>=$Q$27),Q75,IF(OR($AA$373>=$P$26,SUMIF($C:$C,C75,$W:$W)>=$P$27),P75,IF(OR($AA$373>=$O$26,SUMIF($C:$C,C75,$W:$W)>=$O$27),O75,IF(OR($AA$373>=$N$26,SUMIF($C:$C,C75,$W:$W)>=$N$27),N75,IF($AA$373>=$M$26,M75,L75)))))))*$E$13),0) | BE75: =IF(V75="",0,(V75*W75)-(BD75*W75)) -> 0 | BW75: SPORT NUTRITION | BX75: =IFERROR(W75*U75,0) -> 0 | BY75: =VLOOKUP(B75,#REF!,13,0) -> #REF! | BZ75: 65.9 | CA75: =VLOOKUP(B75,Pedido!$B$16:$L$292,22,0) -> #N/A
B76: PPOGLUNAT0100 | C76: PPOGLU1 | D76: Glutamina | E76: Sem Sabor | F76: Pote | G76: 100 | H76: 7.5804408 | I76: 44.9 | J76: =IFERROR(IF(T76<>"",I76/T76,IF(AND(Y76="",V76=""),"",IF(V76="",I76/Y76,I76/V76))),"") | K76: =IF(T76="","",IFERROR(1-(T76/I76),0)) | L76: 31.9 | M76: =P76 -> 27.9 | N76: =P76 -> 27.9 | O76: =P76 -> 27.9 | P76: 27.9 | Q76: 25.9 | R76: 24.9 | S76: 23.9 | T76: =IF(V76>0,V76,IFERROR(IF(AND(W76<>"",X76<>""),AH76/W76,Y76),"")) | U76: =IFERROR((T76*W76)/(W76+X76),"") | Y76: =IF(AND(W76="",X76=""),"",$E$13*IF(V76<>"",V76,IF(SUMIF($C:$C,C76,$W:$W)>=$S$27,S76,IF(OR($AA$373>=$R$26,SUMIF($C:$C,C76,$W:$W)>=$R$27),R76,IF(OR($AA$373>=$Q$26,SUMIF($C:$C,C76,$W:$W)>=$Q$27),Q76,IF(OR($AA$373>=$P$26,SUMIF($C:$C,C76,$W:$W)>=$P$27),P76,IF(OR($AA$373>=$O$26,SUMIF($C:$C,C76,$W:$W)>=$O$27),O76,IF(OR($AA$373>=$N$26,SUMIF($C:$C,C76,$W:$W)>=$N$27),N76,IF($AA$373>=$M$26,M76,L76))))))))) | Z76: =IF(X76>W76,-1,IF(W76=0,0,IF(U76<(H76/0.75),-1,IF(W76<=3,0,0.0001)))) -> 0 | AA76: =IFERROR(L76*W76,0) -> 0 | AB76: =IFERROR(IF(OR($AA$373>=$S$26,SUMIF($C:$C,C76,$W:$W)>=$S$27),S76,IF(OR($AA$373>=$R$26,SUMIF($C:$C,C76,$W:$W)>=$R$27),R76,IF(OR($AA$373>=$Q$26,SUMIF($C:$C,C76,$W:$W)>=$Q$27),Q76,IF(OR($AA$373>=$P$26,SUMIF($C:$C,C76,$W:$W)>=$P$27),P76,IF(OR($AA$373>=$O$26,SUMIF($C:$C,C76,$W:$W)>=$O$27),O76,IF(OR($AA$373>=$N$26,SUMIF($C:$C,C76,$W:$W)>=$N$27),N76,IF($AA$373>=$M$26,M76,L76)))))))*W76,0) -> 0 | AC76: =IFERROR(IF(V76="",0,(IF(AND(W76="",X76=""),"",IF(OR($AA$373>=$S$26,SUMIF($C:$C,C76,$W:$W)>=$S$27),S76*$E$13,IF(OR($AA$373>=$R$26,SUMIF($C:$C,C76,$W:$W)>=$R$27),R76*$E$13,IF(OR($AA$373>=$Q$26,SUMIF($C:$C,C76,$W:$W)>=$Q$27),Q76*$E$13,IF(OR($AA$373>=$P$26,SUMIF($C:$C,C76,$W:$W)>=$P$27),P76*$E$13,IF(OR($AA$373>=$O$26,SUMIF($C:$C,C76,$W:$W)>=$O$27),O76*$E$13,IF(OR($AA$373>=$N$26,SUMIF($C:$C,C76,$W:$W)>=$N$27),N76*$E$13,IF($AA$373>=$M$26,M76*$E$13,L76))))))))-V76)*W76),0) -> 0 | AD76: =IFERROR(X76*T76,0) -> 0 | AE76: =IFERROR(W76*H76,0) -> 0 | AF76: =IFERROR(1-(AE76/AB76),0) -> 0 | AG76: =IFERROR(SUM(W76:X76)*I76,0) -> 0 | AH76: =IFERROR(IF(V76>0,V76*W76,(Y76*W76)),0) -> 0 | AI76: =IFERROR(SUM(W76)*H76,0) -> 0 | AJ76: =AH76*$AJ$25 -> 0 | AK76: =AH76*AK$25 -> 0 | AL76: =AH76*AL$25 -> 0 | AM76: =SUM(AJ76:AL76) -> 0 | AN76: =AH76-AM76 -> 0 | AO76: =AN76-AI76 -> 0 | AP76: =IFERROR(IF(V76<>"",1-(H76/V76),IF(Y76<>"",1-(H76/Y76),1-(H76/L76))),0) -> 0.76236863 | AQ76: =H76/0.75 -> 10.107254 | AR76: 18 | AS76: =(AP76-MIN($AP$65:$AP$368))/(MAX($AP$65:$AP$368)-MIN($AP$65:$AP$368))*100 -> 76.236863 | AT76: =IFERROR(1-(AI76/AH76),0) -> 0 | AU76: =IFERROR(AO76/AH76,0) -> 0 | AW76: =VLOOKUP(AX76,Sup!#REF!,8,0) -> #REF! | AX76: Commodity | AY76: 0 | BC76: =IF(BE76<0,BE76,0) -> 0 | BD76: =IFERROR(IF(AND(W76="",X76=""),"",IF(OR($AA$373>=$S$26,SUMIF($C:$C,C76,$W:$W)>=$S$27),S76,IF(OR($AA$373>=$R$26,SUMIF($C:$C,C76,$W:$W)>=$R$27),R76,IF(OR($AA$373>=$Q$26,SUMIF($C:$C,C76,$W:$W)>=$Q$27),Q76,IF(OR($AA$373>=$P$26,SUMIF($C:$C,C76,$W:$W)>=$P$27),P76,IF(OR($AA$373>=$O$26,SUMIF($C:$C,C76,$W:$W)>=$O$27),O76,IF(OR($AA$373>=$N$26,SUMIF($C:$C,C76,$W:$W)>=$N$27),N76,IF($AA$373>=$M$26,M76,L76)))))))*$E$13),0) | BE76: =IF(V76="",0,(V76*W76)-(BD76*W76)) -> 0 | BW76: SPORT NUTRITION | BX76: =IFERROR(W76*U76,0) -> 0 | BY76: =VLOOKUP(B76,#REF!,13,0) -> #REF! | BZ76: 17.9 | CA76: =VLOOKUP(B76,Pedido!$B$16:$L$292,22,0) -> #N/A
B77: PPOGLUNAT0300 | C77: PPOGLU3 | D77: Glutamina | E77: Sem Sabor | F77: Pote | G77: 300 | H77: 18.253914 | I77: 94.9 | J77: =IFERROR(IF(T77<>"",I77/T77,IF(AND(Y77="",V77=""),"",IF(V77="",I77/Y77,I77/V77))),"") | K77: =IF(T77="","",IFERROR(1-(T77/I77),0)) | L77: 66.9 | M77: =P77 -> 58.9 | N77: =P77 -> 58.9 | O77: =P77 -> 58.9 | P77: 58.9 | Q77: 53.9 | R77: 52.9 | S77: 50.9 | T77: =IF(V77>0,V77,IFERROR(IF(AND(W77<>"",X77<>""),AH77/W77,Y77),"")) | U77: =IFERROR((T77*W77)/(W77+X77),"") | Y77: =IF(AND(W77="",X77=""),"",$E$13*IF(V77<>"",V77,IF(SUMIF($C:$C,C77,$W:$W)>=$S$27,S77,IF(OR($AA$373>=$R$26,SUMIF($C:$C,C77,$W:$W)>=$R$27),R77,IF(OR($AA$373>=$Q$26,SUMIF($C:$C,C77,$W:$W)>=$Q$27),Q77,IF(OR($AA$373>=$P$26,SUMIF($C:$C,C77,$W:$W)>=$P$27),P77,IF(OR($AA$373>=$O$26,SUMIF($C:$C,C77,$W:$W)>=$O$27),O77,IF(OR($AA$373>=$N$26,SUMIF($C:$C,C77,$W:$W)>=$N$27),N77,IF($AA$373>=$M$26,M77,L77))))))))) | Z77: =IF(X77>W77,-1,IF(W77=0,0,IF(U77<(H77/0.75),-1,IF(W77<=3,0,0.0001)))) -> 0 | AA77: =IFERROR(L77*W77,0) -> 0 | AB77: =IFERROR(IF(OR($AA$373>=$S$26,SUMIF($C:$C,C77,$W:$W)>=$S$27),S77,IF(OR($AA$373>=$R$26,SUMIF($C:$C,C77,$W:$W)>=$R$27),R77,IF(OR($AA$373>=$Q$26,SUMIF($C:$C,C77,$W:$W)>=$Q$27),Q77,IF(OR($AA$373>=$P$26,SUMIF($C:$C,C77,$W:$W)>=$P$27),P77,IF(OR($AA$373>=$O$26,SUMIF($C:$C,C77,$W:$W)>=$O$27),O77,IF(OR($AA$373>=$N$26,SUMIF($C:$C,C77,$W:$W)>=$N$27),N77,IF($AA$373>=$M$26,M77,L77)))))))*W77,0) -> 0 | AC77: =IFERROR(IF(V77="",0,(IF(AND(W77="",X77=""),"",IF(OR($AA$373>=$S$26,SUMIF($C:$C,C77,$W:$W)>=$S$27),S77*$E$13,IF(OR($AA$373>=$R$26,SUMIF($C:$C,C77,$W:$W)>=$R$27),R77*$E$13,IF(OR($AA$373>=$Q$26,SUMIF($C:$C,C77,$W:$W)>=$Q$27),Q77*$E$13,IF(OR($AA$373>=$P$26,SUMIF($C:$C,C77,$W:$W)>=$P$27),P77*$E$13,IF(OR($AA$373>=$O$26,SUMIF($C:$C,C77,$W:$W)>=$O$27),O77*$E$13,IF(OR($AA$373>=$N$26,SUMIF($C:$C,C77,$W:$W)>=$N$27),N77*$E$13,IF($AA$373>=$M$26,M77*$E$13,L77))))))))-V77)*W77),0) -> 0 | AD77: =IFERROR(X77*T77,0) -> 0 | AE77: =IFERROR(W77*H77,0) -> 0 | AF77: =IFERROR(1-(AE77/AB77),0) -> 0 | AG77: =IFERROR(SUM(W77:X77)*I77,0) -> 0 | AH77: =IFERROR(IF(V77>0,V77*W77,(Y77*W77)),0) -> 0 | AI77: =IFERROR(SUM(W77)*H77,0) -> 0 | AJ77: =AH77*$AJ$25 -> 0 | AK77: =AH77*AK$25 -> 0 | AL77: =AH77*AL$25 -> 0 | AM77: =SUM(AJ77:AL77) -> 0 | AN77: =AH77-AM77 -> 0 | AO77: =AN77-AI77 -> 0 | AP77: =IFERROR(IF(V77<>"",1-(H77/V77),IF(Y77<>"",1-(H77/Y77),1-(H77/L77))),0) -> 0.72714628 | AQ77: =H77/0.75 -> 24.338552 | AR77: 18 | AS77: =(AP77-MIN($AP$65:$AP$368))/(MAX($AP$65:$AP$368)-MIN($AP$65:$AP$368))*100 -> 72.714628 | AT77: =IFERROR(1-(AI77/AH77),0) -> 0 | AU77: =IFERROR(AO77/AH77,0) -> 0 | AW77: =VLOOKUP(AX77,Sup!#REF!,8,0) -> #REF! | AX77: Commodity | AY77: 0 | BB77: =IF($F$14="NOVO/REATIVAÇÃO",W77*7*1.4,W77*7) -> 0 | BC77: =IF(BE77<0,BE77,0) -> 0 | BD77: =IFERROR(IF(AND(W77="",X77=""),"",IF(OR($AA$373>=$S$26,SUMIF($C:$C,C77,$W:$W)>=$S$27),S77,IF(OR($AA$373>=$R$26,SUMIF($C:$C,C77,$W:$W)>=$R$27),R77,IF(OR($AA$373>=$Q$26,SUMIF($C:$C,C77,$W:$W)>=$Q$27),Q77,IF(OR($AA$373>=$P$26,SUMIF($C:$C,C77,$W:$W)>=$P$27),P77,IF(OR($AA$373>=$O$26,SUMIF($C:$C,C77,$W:$W)>=$O$27),O77,IF(OR($AA$373>=$N$26,SUMIF($C:$C,C77,$W:$W)>=$N$27),N77,IF($AA$373>=$M$26,M77,L77)))))))*$E$13),0) | BE77: =IF(V77="",0,(V77*W77)-(BD77*W77)) -> 0 | BW77: SPORT NUTRITION | BX77: =IFERROR(W77*U77,0) -> 0 | BY77: =VLOOKUP(B77,#REF!,13,0) -> #REF! | BZ77: 38.9 | CA77: =VLOOKUP(B77,Pedido!$B$16:$L$292,22,0) -> #N/A
B78: 420739063 | C78: energygel | D78: Display Energy Gel | E78: Caramelo | F78: Sachê | G78: 30 | H78: 8 | I78: 129.9 | J78: =IFERROR(IF(T78<>"",I78/T78,IF(AND(Y78="",V78=""),"",IF(V78="",I78/Y78,I78/V78))),"") -> 1.4611924 | K78: =IF(T78="","",IFERROR(1-(T78/I78),0)) -> 0.31562741 | L78: 88.9 | M78: =P78 -> 77.9 | N78: =P78 -> 77.9 | O78: =P78 -> 77.9 | P78: =IF(SUM($W$78:$W$85)>9,39.9,IF(SUM($W$78:$W$85)>2,44.9,77.9)) -> 77.9 | Q78: =IF(SUM($W$78:$W$85)>9,39.9,IF(SUM($W$78:$W$85)>2,44.9,71.9)) -> 71.9 | R78: =IF(SUM($W$78:$W$85)>9,39.9,IF(SUM($W$78:$W$85)>2,44.9,70.9)) -> 70.9 | S78: =IF(SUM($W$78:$W$85)>9,39.9,IF(SUM($W$78:$W$85)>2,44.9,67.9)) -> 67.9 | T78: =IF(V78>0,V78,IFERROR(IF(AND(W78<>"",X78<>""),AH78/W78,Y78),"")) -> 88.9 | U78: =IFERROR((T78*W78)/(W78+X78),"") | W78: =Pedido!L58 -> 0 | Y78: =IF(AND(W78="",X78=""),"",$E$13*IF(V78<>"",V78,IF(SUMIF($C:$C,C78,$W:$W)>=$S$27,S78,IF(OR($AA$373>=$R$26,SUMIF($C:$C,C78,$W:$W)>=$R$27),R78,IF(OR($AA$373>=$Q$26,SUMIF($C:$C,C78,$W:$W)>=$Q$27),Q78,IF(OR($AA$373>=$P$26,SUMIF($C:$C,C78,$W:$W)>=$P$27),P78,IF(OR($AA$373>=$O$26,SUMIF($C:$C,C78,$W:$W)>=$O$27),O78,IF(OR($AA$373>=$N$26,SUMIF($C:$C,C78,$W:$W)>=$N$27),N78,IF($AA$373>=$M$26,M78,L78))))))))) -> 88.9 | Z78: =IF(X78>W78,-1,IF(W78=0,0,IF(U78<(H78/0.75),-1,IF(W78<=3,0,0.0001)))) -> 0 | AA78: =IFERROR(L78*W78,0) -> 0 | AB78: =IFERROR(IF(OR($AA$373>=$S$26,SUMIF($C:$C,C78,$W:$W)>=$S$27),S78,IF(OR($AA$373>=$R$26,SUMIF($C:$C,C78,$W:$W)>=$R$27),R78,IF(OR($AA$373>=$Q$26,SUMIF($C:$C,C78,$W:$W)>=$Q$27),Q78,IF(OR($AA$373>=$P$26,SUMIF($C:$C,C78,$W:$W)>=$P$27),P78,IF(OR($AA$373>=$O$26,SUMIF($C:$C,C78,$W:$W)>=$O$27),O78,IF(OR($AA$373>=$N$26,SUMIF($C:$C,C78,$W:$W)>=$N$27),N78,IF($AA$373>=$M$26,M78,L78)))))))*W78,0) -> 0 | AC78: =IFERROR(IF(V78="",0,(IF(AND(W78="",X78=""),"",IF(OR($AA$373>=$S$26,SUMIF($C:$C,C78,$W:$W)>=$S$27),S78*$E$13,IF(OR($AA$373>=$R$26,SUMIF($C:$C,C78,$W:$W)>=$R$27),R78*$E$13,IF(OR($AA$373>=$Q$26,SUMIF($C:$C,C78,$W:$W)>=$Q$27),Q78*$E$13,IF(OR($AA$373>=$P$26,SUMIF($C:$C,C78,$W:$W)>=$P$27),P78*$E$13,IF(OR($AA$373>=$O$26,SUMIF($C:$C,C78,$W:$W)>=$O$27),O78*$E$13,IF(OR($AA$373>=$N$26,SUMIF($C:$C,C78,$W:$W)>=$N$27),N78*$E$13,IF($AA$373>=$M$26,M78*$E$13,L78))))))))-V78)*W78),0) -> 0 | AD78: =IFERROR(X78*T78,0) -> 0 | AE78: =IFERROR(W78*H78,0) -> 0 | AF78: =IFERROR(1-(AE78/AB78),0) -> 0 | AG78: =IFERROR(SUM(W78:X78)*I78,0) -> 0 | AH78: =IFERROR(IF(V78>0,V78*W78,(Y78*W78)),0) -> 0 | AI78: =IFERROR(SUM(W78)*H78,0) -> 0 | AJ78: =AH78*$AJ$25 -> 0 | AK78: =AH78*AK$25 -> 0 | AL78: =AH78*AL$25 -> 0 | AM78: =SUM(AJ78:AL78) -> 0 | AN78: =AH78-AM78 -> 0 | AO78: =AN78-AI78 -> 0 | AP78: =IFERROR(IF(V78<>"",1-(H78/V78),IF(Y78<>"",1-(H78/Y78),1-(H78/L78))),0) -> 0.91001125 | AQ78: =H78/0.75 -> 10.666667 | AR78: 19 | AS78: =(AP78-MIN($AP$65:$AP$368))/(MAX($AP$65:$AP$368)-MIN($AP$65:$AP$368))*100 -> 91.001125 | AT78: =IFERROR(1-(AI78/AH78),0) -> 0 | AU78: =IFERROR(AO78/AH78,0) -> 0 | AW78: A | AX78: Standard | AY78: 0 | BC78: =IF(BE78<0,BE78,0) -> 0 | BD78: =IFERROR(IF(AND(W78="",X78=""),"",IF(OR($AA$373>=$S$26,SUMIF($C:$C,C78,$W:$W)>=$S$27),S78,IF(OR($AA$373>=$R$26,SUMIF($C:$C,C78,$W:$W)>=$R$27),R78,IF(OR($AA$373>=$Q$26,SUMIF($C:$C,C78,$W:$W)>=$Q$27),Q78,IF(OR($AA$373>=$P$26,SUMIF($C:$C,C78,$W:$W)>=$P$27),P78,IF(OR($AA$373>=$O$26,SUMIF($C:$C,C78,$W:$W)>=$O$27),O78,IF(OR($AA$373>=$N$26,SUMIF($C:$C,C78,$W:$W)>=$N$27),N78,IF($AA$373>=$M$26,M78,L78)))))))*$E$13),0) -> 88.9 | BE78: =IF(V78="",0,(V78*W78)-(BD78*W78)) -> 0 | BW78: HIGH PERFORMANCE | BX78: =IFERROR(W78*U78,0) -> 0 | BY78: =VLOOKUP(B78,#REF!,13,0) -> #REF! | BZ78: 59.9 | CA78: =VLOOKUP(B78,Pedido!$B$16:$L$292,22,0) -> #N/A
